[{"a":"Aðalgata 10A","pn":"550","sv":"Skagafjörður","teg":"Fjölbýli","fnr":"2131123","full":1,"mat":35000,"matN":34950,"bruna":50800,"ar":1958,"fm":95.8,"herb":4,"lod":117,"ld":"2021-02","lv":22000},{"a":"Aðalgata 10B","pn":"550","sv":"Skagafjörður","teg":"Fjölbýli","fnr":"2131120","full":1,"mat":29450,"matN":29500,"bruna":43150,"ar":1956,"fm":78.4,"herb":3,"lod":231,"ld":"2013-03","lv":7028},{"a":"Aðalgata 13","pn":"550","sv":"Skagafjörður","teg":"Einbýli","fnr":"2131127","full":1,"mat":43850,"matN":44050,"bruna":49900,"ar":1897,"fm":121.6,"herb":6,"lod":345,"ld":"2010-02","lv":7300},{"a":"Aðalgata 19","pn":"550","sv":"Skagafjörður","teg":"Fjölbýli","fnr":"2131138","full":1,"mat":38590,"matN":41650,"bruna":117650,"ar":1897,"fm":290.1,"herb":null,"lod":955,"ld":"2006-06","lv":16500},{"a":"Aðalgata 20","pn":"550","sv":"Skagafjörður","teg":"Einbýli","fnr":"2131141","full":1,"mat":79550,"matN":78900,"bruna":187950,"ar":1880,"fm":511.9,"herb":8,"lod":745,"ld":"2012-09","lv":20000},{"a":"Aðalgata 4","pn":"550","sv":"Skagafjörður","teg":"Fjölbýli","fnr":"2131098","full":1,"mat":18700,"matN":20250,"bruna":65150,"ar":1946,"fm":139.4,"herb":null,"lod":155,"ld":"2017-01","lv":20000},{"a":"Aðalgata 5","pn":"550","sv":"Skagafjörður","teg":"Fjölbýli","fnr":"2131100","full":1,"mat":51000,"matN":51450,"bruna":101550,"ar":1928,"fm":203.8,"herb":7,"lod":507,"ld":"2017-04","lv":25500},{"a":"Aðalgata 6","pn":"550","sv":"Skagafjörður","teg":"Einbýli","fnr":"2131106","full":1,"mat":74210,"matN":74850,"bruna":107530,"ar":1944,"fm":232,"herb":3,"lod":396,"ld":"2022-12","lv":45000},{"a":"Aðalgata 8","pn":"550","sv":"Skagafjörður","teg":"Fjölbýli","fnr":"2131112","full":1,"mat":40550,"matN":40450,"bruna":52800,"ar":1913,"fm":116.6,"herb":3,"lod":412,"ld":"2024-01","lv":49000},{"a":"Ártún 13","pn":"550","sv":"Skagafjörður","teg":"Einbýli","fnr":"2131176","full":1,"mat":88350,"matN":88150,"bruna":103700,"ar":1987,"fm":220,"herb":4,"lod":690,"ld":"2019-10","lv":53000},{"a":"Ártún 15","pn":"550","sv":"Skagafjörður","teg":"Einbýli","fnr":"2131177","full":1,"mat":94450,"matN":94650,"bruna":122650,"ar":1985,"fm":230.9,"herb":5,"lod":690,"ld":"2024-05","lv":110000},{"a":"Ártún 17","pn":"550","sv":"Skagafjörður","teg":"Einbýli","fnr":"2131178","full":1,"mat":93350,"matN":93100,"bruna":113700,"ar":1983,"fm":246.8,"herb":6,"lod":690,"ld":"2006-07","lv":26000},{"a":"Ártún 7","pn":"550","sv":"Skagafjörður","teg":"Einbýli","fnr":"2131173","full":1,"mat":92900,"matN":92450,"bruna":129900,"ar":1983,"fm":249,"herb":7,"lod":690,"ld":"2006-11","lv":27000},{"a":"Ártún 9","pn":"550","sv":"Skagafjörður","teg":"Einbýli","fnr":"2131174","full":1,"mat":90650,"matN":90250,"bruna":117950,"ar":1985,"fm":241.1,"herb":4,"lod":760,"ld":"2022-07","lv":87000},{"a":"Barmahlíð 1","pn":"550","sv":"Skagafjörður","teg":"Einbýli","fnr":"2131180","full":1,"mat":83700,"matN":83450,"bruna":102900,"ar":1979,"fm":194.8,"herb":6,"lod":970,"ld":"2017-04","lv":45000},{"a":"Barmahlíð 2","pn":"550","sv":"Skagafjörður","teg":"Fjölbýli","fnr":"2131181","full":1,"mat":51450,"matN":50950,"bruna":55050,"ar":1982,"fm":116.7,"herb":3,"lod":999,"ld":"2024-02","lv":30000},{"a":"Barmahlíð 2","pn":"550","sv":"Skagafjörður","teg":"Fjölbýli","fnr":"2232625","full":1,"mat":69100,"matN":68200,"bruna":88000,"ar":1982,"fm":185.5,"herb":4,"lod":999,"ld":"2021-01","lv":34500},{"a":"Barmahlíð 21","pn":"550","sv":"Skagafjörður","teg":"Einbýli","fnr":"2131200","full":1,"mat":68600,"matN":68200,"bruna":77900,"ar":1977,"fm":169.6,"herb":5,"lod":945,"ld":"2025-08","lv":61500},{"a":"Barmahlíð 23","pn":"550","sv":"Skagafjörður","teg":"Einbýli","fnr":"2131201","full":1,"mat":77900,"matN":77950,"bruna":90000,"ar":1976,"fm":174.2,"herb":3,"lod":826,"ld":"2011-05","lv":26000},{"a":"Barmahlíð 25","pn":"550","sv":"Skagafjörður","teg":"Einbýli","fnr":"2131203","full":1,"mat":78100,"matN":77650,"bruna":87750,"ar":1975,"fm":182.7,"herb":5,"lod":826,"ld":"2024-07","lv":77500},{"a":"Barmahlíð 4","pn":"550","sv":"Skagafjörður","teg":"Einbýli","fnr":"2131184","full":1,"mat":104050,"matN":103700,"bruna":141300,"ar":1978,"fm":312.4,"herb":8,"lod":800,"ld":"2020-02","lv":70000},{"a":"Barmahlíð 5","pn":"550","sv":"Skagafjörður","teg":"Einbýli","fnr":"2131185","full":1,"mat":82700,"matN":82400,"bruna":97150,"ar":1976,"fm":194.2,"herb":4,"lod":1016,"ld":"2020-10","lv":56600},{"a":"Barmahlíð 7","pn":"550","sv":"Skagafjörður","teg":"Einbýli","fnr":"2131188","full":1,"mat":88650,"matN":88400,"bruna":113800,"ar":1978,"fm":210.5,"herb":6,"lod":783,"ld":"2023-02","lv":74500},{"a":"Barmahlíð 9","pn":"550","sv":"Skagafjörður","teg":"Einbýli","fnr":"2131190","full":1,"mat":80750,"matN":80650,"bruna":93600,"ar":1976,"fm":182.7,"herb":5,"lod":852,"ld":"2016-01","lv":32000},{"a":"Bárustígur 1","pn":"550","sv":"Skagafjörður","teg":"Einbýli","fnr":"2131205","full":1,"mat":66250,"matN":66100,"bruna":69600,"ar":1948,"fm":131.9,"herb":4,"lod":735,"ld":"2022-07","lv":42200},{"a":"Bárustígur 10","pn":"550","sv":"Skagafjörður","teg":"Einbýli","fnr":"2131224","full":1,"mat":59000,"matN":59100,"bruna":78350,"ar":1955,"fm":168.2,"herb":4,"lod":440,"ld":"2013-06","lv":18000},{"a":"Bárustígur 12","pn":"550","sv":"Skagafjörður","teg":"Einbýli","fnr":"2131228","full":1,"mat":55550,"matN":55750,"bruna":64590,"ar":1956,"fm":139.5,"herb":1,"lod":600,"ld":"2025-05","lv":50000},{"a":"Bárustígur 13","pn":"550","sv":"Skagafjörður","teg":"Fjölbýli","fnr":"2131231","full":1,"mat":34800,"matN":34850,"bruna":41000,"ar":1955,"fm":78.5,"herb":3,"lod":440,"ld":"2014-04","lv":11000},{"a":"Bárustígur 13","pn":"550","sv":"Skagafjörður","teg":"Fjölbýli","fnr":"2131230","full":1,"mat":51550,"matN":51250,"bruna":60660,"ar":1955,"fm":137.6,"herb":2,"lod":440,"ld":"2014-10","lv":12500},{"a":"Bárustígur 16","pn":"550","sv":"Skagafjörður","teg":"Einbýli","fnr":"2131236","full":1,"mat":58350,"matN":58600,"bruna":67950,"ar":1949,"fm":122.1,"herb":3,"lod":620,"ld":"2022-05","lv":41000},{"a":"Bárustígur 17","pn":"550","sv":"Skagafjörður","teg":"Einbýli","fnr":"2131237","full":1,"mat":48250,"matN":48350,"bruna":51150,"ar":1952,"fm":114.5,"herb":1,"lod":440,"ld":"2026-03","lv":33500},{"a":"Bárustígur 3","pn":"550","sv":"Skagafjörður","teg":"Einbýli","fnr":"2131208","full":1,"mat":47950,"matN":48050,"bruna":67250,"ar":1949,"fm":145.4,"herb":3,"lod":545,"ld":"2025-04","lv":54000},{"a":"Bárustígur 4","pn":"550","sv":"Skagafjörður","teg":"Einbýli","fnr":"2131210","full":1,"mat":51400,"matN":51400,"bruna":54800,"ar":1955,"fm":112.2,"herb":3,"lod":600,"ld":"2022-04","lv":43000},{"a":"Bárustígur 6","pn":"550","sv":"Skagafjörður","teg":"Einbýli","fnr":"2131214","full":1,"mat":65150,"matN":65050,"bruna":83400,"ar":1955,"fm":174,"herb":4,"lod":785,"ld":"2010-08","lv":17500},{"a":"Bárustígur 7","pn":"550","sv":"Skagafjörður","teg":"Einbýli","fnr":"2131216","full":1,"mat":61550,"matN":61850,"bruna":58050,"ar":1949,"fm":120.1,"herb":3,"lod":440,"ld":"2022-12","lv":53500},{"a":"Birkihlíð 10","pn":"550","sv":"Skagafjörður","teg":"Einbýli","fnr":"2131253","full":1,"mat":88700,"matN":88300,"bruna":111250,"ar":1974,"fm":249,"herb":5,"lod":800,"ld":"2023-10","lv":78000},{"a":"Birkihlíð 14","pn":"550","sv":"Skagafjörður","teg":"Einbýli","fnr":"2131259","full":1,"mat":84750,"matN":84400,"bruna":109950,"ar":1970,"fm":247,"herb":7,"lod":800,"ld":"2021-03","lv":63100},{"a":"Birkihlíð 17","pn":"550","sv":"Skagafjörður","teg":"Einbýli","fnr":"2131263","full":1,"mat":81750,"matN":81550,"bruna":96550,"ar":1974,"fm":193.4,"herb":5,"lod":864,"ld":"2012-06","lv":33000},{"a":"Birkihlíð 2","pn":"550","sv":"Skagafjörður","teg":"Einbýli","fnr":"2131240","full":1,"mat":86450,"matN":86150,"bruna":113800,"ar":1970,"fm":250,"herb":6,"lod":992,"ld":"2015-05","lv":31000},{"a":"Birkihlíð 25","pn":"550","sv":"Skagafjörður","teg":"Einbýli","fnr":"2131272","full":1,"mat":61350,"matN":61100,"bruna":64300,"ar":1975,"fm":120,"herb":3,"lod":784,"ld":"2020-03","lv":34000},{"a":"Birkihlíð 31","pn":"550","sv":"Skagafjörður","teg":"Einbýli","fnr":"2131277","full":1,"mat":73350,"matN":73350,"bruna":83300,"ar":1970,"fm":168,"herb":3,"lod":784,"ld":"2019-01","lv":43000},{"a":"Birkihlíð 37","pn":"550","sv":"Skagafjörður","teg":"Einbýli","fnr":"2131283","full":1,"mat":72850,"matN":72950,"bruna":81350,"ar":1971,"fm":159.5,"herb":3,"lod":854,"ld":"2012-10","lv":24000},{"a":"Birkihlíð 5","pn":"550","sv":"Skagafjörður","teg":"Einbýli","fnr":"2131244","full":1,"mat":76950,"matN":76900,"bruna":81950,"ar":1970,"fm":187.5,"herb":3,"lod":1045,"ld":"2022-04","lv":67000},{"a":"Brekkugata 3","pn":"550","sv":"Skagafjörður","teg":"Fjölbýli","fnr":"2131335","full":1,"mat":22600,"matN":22700,"bruna":22500,"ar":1924,"fm":43.2,"herb":1,"lod":315,"ld":"2012-06","lv":4700},{"a":"Brekkugata 5","pn":"550","sv":"Skagafjörður","teg":"Fjölbýli","fnr":"2131337","full":1,"mat":38200,"matN":37850,"bruna":48100,"ar":1958,"fm":90,"herb":2,"lod":732,"ld":"2017-06","lv":16000},{"a":"Brekkutún 1","pn":"550","sv":"Skagafjörður","teg":"Einbýli","fnr":"2216487","full":1,"mat":93350,"matN":93100,"bruna":122500,"ar":1994,"fm":179.8,"herb":3,"lod":750,"ld":"2006-11","lv":27000},{"a":"Brekkutún 12","pn":"550","sv":"Skagafjörður","teg":"Einbýli","fnr":"2216455","full":1,"mat":82600,"matN":82650,"bruna":95900,"ar":1994,"fm":167.9,"herb":3,"lod":750,"ld":"2007-06","lv":25000},{"a":"Brekkutún 9","pn":"550","sv":"Skagafjörður","teg":"Einbýli","fnr":"2131343","full":1,"mat":80650,"matN":80450,"bruna":98650,"ar":1993,"fm":166.4,"herb":4,"lod":750,"ld":"2024-03","lv":82000},{"a":"Brennihlíð 3","pn":"550","sv":"Skagafjörður","teg":"Einbýli","fnr":"2131347","full":1,"mat":88650,"matN":88450,"bruna":110800,"ar":1977,"fm":207.8,"herb":4,"lod":705,"ld":"2018-08","lv":47750},{"a":"Dalatún 1","pn":"550","sv":"Skagafjörður","teg":"Einbýli","fnr":"2131358","full":1,"mat":88650,"matN":88550,"bruna":106100,"ar":1983,"fm":211.9,"herb":4,"lod":750,"ld":"2012-06","lv":33300},{"a":"Dalatún 11","pn":"550","sv":"Skagafjörður","teg":"Einbýli","fnr":"2131372","full":1,"mat":101250,"matN":100850,"bruna":142550,"ar":1986,"fm":273.4,"herb":6,"lod":690,"ld":"2013-04","lv":36000},{"a":"Dalatún 12","pn":"550","sv":"Skagafjörður","teg":"Einbýli","fnr":"2131374","full":1,"mat":91700,"matN":91900,"bruna":124050,"ar":1987,"fm":221,"herb":5,"lod":690,"ld":"2013-11","lv":40000},{"a":"Dalatún 13","pn":"550","sv":"Skagafjörður","teg":"Einbýli","fnr":"2131375","full":1,"mat":94100,"matN":94250,"bruna":115600,"ar":1990,"fm":221.6,"herb":5,"lod":750,"ld":"2019-12","lv":62000},{"a":"Dalatún 14","pn":"550","sv":"Skagafjörður","teg":"Einbýli","fnr":"2131376","full":1,"mat":93000,"matN":93200,"bruna":109750,"ar":1981,"fm":236.7,"herb":5,"lod":801,"ld":"2016-01","lv":41500},{"a":"Dalatún 17","pn":"550","sv":"Skagafjörður","teg":"Einbýli","fnr":"2131380","full":1,"mat":83200,"matN":83490,"bruna":97300,"ar":1981,"fm":210.3,"herb":5,"lod":690,"ld":"2021-05","lv":52500},{"a":"Dalatún 19","pn":"550","sv":"Skagafjörður","teg":"Einbýli","fnr":"2131383","full":1,"mat":84450,"matN":84550,"bruna":95950,"ar":1981,"fm":211.5,"herb":4,"lod":801,"ld":"2023-02","lv":83000},{"a":"Dalatún 3","pn":"550","sv":"Skagafjörður","teg":"Einbýli","fnr":"2131360","full":1,"mat":80050,"matN":79400,"bruna":99950,"ar":1982,"fm":185,"herb":3,"lod":690,"ld":"2017-10","lv":41200},{"a":"Dalatún 6","pn":"550","sv":"Skagafjörður","teg":"Einbýli","fnr":"2131365","full":1,"mat":107750,"matN":107600,"bruna":158750,"ar":1981,"fm":315,"herb":6,"lod":690,"ld":"2014-06","lv":45000},{"a":"Drekahlíð 4","pn":"550","sv":"Skagafjörður","teg":"Einbýli","fnr":"2131388","full":1,"mat":84100,"matN":84000,"bruna":109300,"ar":1981,"fm":218.5,"herb":5,"lod":705,"ld":"2010-07","lv":25000},{"a":"Drekahlíð 5","pn":"550","sv":"Skagafjörður","teg":"Einbýli","fnr":"2131389","full":1,"mat":88700,"matN":88700,"bruna":97750,"ar":1988,"fm":192.7,"herb":4,"lod":705,"ld":"2015-09","lv":36500},{"a":"Drekahlíð 9","pn":"550","sv":"Skagafjörður","teg":"Einbýli","fnr":"2131396","full":1,"mat":79800,"matN":79650,"bruna":98050,"ar":1979,"fm":180.1,"herb":5,"lod":705,"ld":"2013-05","lv":31000},{"a":"Eskihlíð 6","pn":"550","sv":"Skagafjörður","teg":"Einbýli","fnr":"2131448","full":1,"mat":79800,"matN":79900,"bruna":92650,"ar":1980,"fm":173.2,"herb":4,"lod":705,"ld":"2023-06","lv":74000},{"a":"Eskihlíð 8","pn":"550","sv":"Skagafjörður","teg":"Einbýli","fnr":"2131452","full":1,"mat":82950,"matN":82800,"bruna":113650,"ar":1979,"fm":191.7,"herb":3,"lod":705,"ld":"2019-08","lv":43000},{"a":"Eyrartún 10","pn":"550","sv":"Skagafjörður","teg":"Einbýli","fnr":"2220822","full":1,"mat":83000,"matN":82950,"bruna":93300,"ar":1995,"fm":174.8,"herb":4,"lod":750,"ld":"2023-06","lv":78000},{"a":"Eyrartún 12","pn":"550","sv":"Skagafjörður","teg":"Einbýli","fnr":"2219220","full":1,"mat":85050,"matN":85200,"bruna":108450,"ar":1994,"fm":169.2,"herb":2,"lod":750,"ld":"2019-05","lv":45000},{"a":"Eyrartún 6","pn":"550","sv":"Skagafjörður","teg":"Einbýli","fnr":"2219786","full":1,"mat":69750,"matN":69850,"bruna":77850,"ar":1995,"fm":127.5,"herb":2,"lod":750,"ld":"2019-05","lv":36300},{"a":"Fellstún 1","pn":"550","sv":"Skagafjörður","teg":"Einbýli","fnr":"2131456","full":1,"mat":76400,"matN":76250,"bruna":98550,"ar":1984,"fm":161.5,"herb":3,"lod":773,"ld":"2007-05","lv":26500},{"a":"Fellstún 12","pn":"550","sv":"Skagafjörður","teg":"Einbýli","fnr":"2131474","full":1,"mat":87500,"matN":87450,"bruna":98650,"ar":1986,"fm":221.4,"herb":6,"lod":690,"ld":"2010-07","lv":28500},{"a":"Fellstún 2","pn":"550","sv":"Skagafjörður","teg":"Einbýli","fnr":"2131457","full":1,"mat":95250,"matN":95000,"bruna":123550,"ar":1987,"fm":223.7,"herb":4,"lod":761,"ld":"2017-07","lv":48500},{"a":"Fellstún 20","pn":"550","sv":"Skagafjörður","teg":"Fjölbýli","fnr":"2261062","full":1,"mat":46350,"matN":46100,"bruna":46550,"ar":2001,"fm":91.3,"herb":2,"lod":803,"ld":"2021-09","lv":33000},{"a":"Fellstún 20","pn":"550","sv":"Skagafjörður","teg":"Fjölbýli","fnr":"2261063","full":1,"mat":88750,"matN":87800,"bruna":133250,"ar":2001,"fm":248.7,"herb":4,"lod":803,"ld":"2021-09","lv":67000},{"a":"Fellstún 4","pn":"550","sv":"Skagafjörður","teg":"Einbýli","fnr":"2131460","full":1,"mat":70350,"matN":70350,"bruna":77850,"ar":1985,"fm":140.6,"herb":4,"lod":690,"ld":"2017-01","lv":31000},{"a":"Fellstún 6","pn":"550","sv":"Skagafjörður","teg":"Einbýli","fnr":"2131463","full":1,"mat":67400,"matN":67500,"bruna":73200,"ar":1985,"fm":135.2,"herb":2,"lod":690,"ld":"2025-07","lv":68500},{"a":"Fornós 10","pn":"550","sv":"Skagafjörður","teg":"Einbýli","fnr":"2131499","full":1,"mat":80400,"matN":80100,"bruna":100050,"ar":1971,"fm":202.3,"herb":4,"lod":768,"ld":"2017-11","lv":36500},{"a":"Fornós 11","pn":"550","sv":"Skagafjörður","teg":"Einbýli","fnr":"2131502","full":1,"mat":77050,"matN":77250,"bruna":80650,"ar":1977,"fm":166.5,"herb":4,"lod":669,"ld":"2021-11","lv":42500},{"a":"Fornós 12","pn":"550","sv":"Skagafjörður","teg":"Einbýli","fnr":"2131503","full":1,"mat":79000,"matN":78900,"bruna":91100,"ar":1969,"fm":190.6,"herb":4,"lod":868,"ld":"2013-10","lv":17800},{"a":"Fornós 14","pn":"550","sv":"Skagafjörður","teg":"Einbýli","fnr":"2131507","full":1,"mat":74100,"matN":74050,"bruna":82700,"ar":1977,"fm":163,"herb":4,"lod":1045,"ld":"2015-03","lv":25500},{"a":"Fornós 4","pn":"550","sv":"Skagafjörður","teg":"Einbýli","fnr":"2131489","full":1,"mat":58050,"matN":58150,"bruna":58800,"ar":1971,"fm":108.7,"herb":5,"lod":858,"ld":"2007-02","lv":14600},{"a":"Fornós 5","pn":"550","sv":"Skagafjörður","teg":"Einbýli","fnr":"2131490","full":1,"mat":58300,"matN":58400,"bruna":59620,"ar":1967,"fm":123.8,"herb":3,"lod":690,"ld":"2015-02","lv":20000},{"a":"Fornós 8","pn":"550","sv":"Skagafjörður","teg":"Einbýli","fnr":"2131495","full":1,"mat":67150,"matN":67500,"bruna":84350,"ar":1965,"fm":150.5,"herb":4,"lod":400,"ld":"2017-05","lv":34750},{"a":"Fornós 9","pn":"550","sv":"Skagafjörður","teg":"Einbýli","fnr":"2131497","full":1,"mat":72650,"matN":72650,"bruna":84750,"ar":1978,"fm":151.4,"herb":4,"lod":669,"ld":"2024-01","lv":55000},{"a":"Freyjugata 10","pn":"550","sv":"Skagafjörður","teg":"Einbýli","fnr":"2131519","full":1,"mat":29850,"matN":30100,"bruna":31300,"ar":1922,"fm":74.5,"herb":1,"lod":262,"ld":"2024-07","lv":41635},{"a":"Freyjugata 10B","pn":"550","sv":"Skagafjörður","teg":"Fjölbýli","fnr":"2131520","full":1,"mat":37750,"matN":37600,"bruna":42540,"ar":1951,"fm":97.7,"herb":2,"lod":365,"ld":"2006-06","lv":6900},{"a":"Freyjugata 13","pn":"550","sv":"Skagafjörður","teg":"Einbýli","fnr":"2131526","full":1,"mat":32450,"matN":32800,"bruna":32400,"ar":1932,"fm":66.3,"herb":2,"lod":197,"ld":"2009-09","lv":5000},{"a":"Freyjugata 17","pn":"550","sv":"Skagafjörður","teg":"Fjölbýli","fnr":"2131528","full":1,"mat":28700,"matN":28750,"bruna":27550,"ar":1933,"fm":60.8,"herb":2,"lod":627,"ld":"2022-10","lv":21000},{"a":"Freyjugata 19","pn":"550","sv":"Skagafjörður","teg":"Einbýli","fnr":"2131533","full":1,"mat":62900,"matN":63100,"bruna":71600,"ar":1935,"fm":142.8,"herb":5,"lod":448,"ld":"2015-09","lv":14000},{"a":"Freyjugata 21","pn":"550","sv":"Skagafjörður","teg":"Fjölbýli","fnr":"2131534","full":1,"mat":38600,"matN":38600,"bruna":50900,"ar":1938,"fm":95.9,"herb":2,"lod":418,"ld":"2026-03","lv":34550},{"a":"Freyjugata 26","pn":"550","sv":"Skagafjörður","teg":"Fjölbýli","fnr":"2131545","full":1,"mat":17700,"matN":17800,"bruna":23700,"ar":1954,"fm":36.6,"herb":1,"lod":400,"ld":"2012-07","lv":4300},{"a":"Freyjugata 26","pn":"550","sv":"Skagafjörður","teg":"Fjölbýli","fnr":"2131543","full":1,"mat":27800,"matN":27700,"bruna":33500,"ar":1954,"fm":68.4,"herb":2,"lod":400,"ld":"2017-08","lv":15000},{"a":"Freyjugata 26","pn":"550","sv":"Skagafjörður","teg":"Fjölbýli","fnr":"2131544","full":1,"mat":27300,"matN":27250,"bruna":36900,"ar":1954,"fm":67.1,"herb":2,"lod":400,"ld":"2022-04","lv":18000},{"a":"Freyjugata 26A","pn":"550","sv":"Skagafjörður","teg":"Fjölbýli","fnr":"2131547","full":1,"mat":39150,"matN":39050,"bruna":48750,"ar":1954,"fm":104.4,"herb":4,"lod":207,"ld":"2018-12","lv":19000},{"a":"Freyjugata 30","pn":"550","sv":"Skagafjörður","teg":"Fjölbýli","fnr":"2131548","full":1,"mat":52100,"matN":51950,"bruna":58650,"ar":1990,"fm":106.8,"herb":2,"lod":356,"ld":"2021-11","lv":24000},{"a":"Freyjugata 32","pn":"550","sv":"Skagafjörður","teg":"Fjölbýli","fnr":"2131551","full":1,"mat":24650,"matN":24700,"bruna":33800,"ar":1935,"fm":63.1,"herb":1,"lod":400,"ld":"2026-07","lv":25000},{"a":"Freyjugata 32","pn":"550","sv":"Skagafjörður","teg":"Fjölbýli","fnr":"2131552","full":1,"mat":22400,"matN":22500,"bruna":28500,"ar":1935,"fm":56.4,"herb":2,"lod":400,"ld":"2020-07","lv":12000},{"a":"Freyjugata 32","pn":"550","sv":"Skagafjörður","teg":"Fjölbýli","fnr":"2131550","full":1,"mat":19150,"matN":19350,"bruna":21550,"ar":1935,"fm":42.9,"herb":2,"lod":400,"ld":"2020-07","lv":13000},{"a":"Freyjugata 36","pn":"550","sv":"Skagafjörður","teg":"Einbýli","fnr":"2131555","full":1,"mat":56100,"matN":56850,"bruna":66950,"ar":1932,"fm":147.1,"herb":2,"lod":430,"ld":"2024-04","lv":60000},{"a":"Freyjugata 38","pn":"550","sv":"Skagafjörður","teg":"Einbýli","fnr":"2131557","full":1,"mat":41250,"matN":41400,"bruna":44750,"ar":1942,"fm":89.6,"herb":3,"lod":447,"ld":"2016-09","lv":19000},{"a":"Freyjugata 40","pn":"550","sv":"Skagafjörður","teg":"Einbýli","fnr":"2131558","full":1,"mat":42750,"matN":42950,"bruna":49500,"ar":1943,"fm":96,"herb":2,"lod":380,"ld":"2021-03","lv":31000},{"a":"Freyjugata 42","pn":"550","sv":"Skagafjörður","teg":"Einbýli","fnr":"2131559","full":1,"mat":58000,"matN":58600,"bruna":69950,"ar":1942,"fm":146.8,"herb":4,"lod":350,"ld":"2010-01","lv":15913},{"a":"Freyjugata 44","pn":"550","sv":"Skagafjörður","teg":"Einbýli","fnr":"2131560","full":1,"mat":41600,"matN":41750,"bruna":46250,"ar":1946,"fm":91.3,"herb":3,"lod":416,"ld":"2022-08","lv":30000},{"a":"Freyjugata 46","pn":"550","sv":"Skagafjörður","teg":"Einbýli","fnr":"2131561","full":1,"mat":41600,"matN":41750,"bruna":45250,"ar":1946,"fm":90.7,"herb":3,"lod":459,"ld":"2020-05","lv":17500},{"a":"Freyjugata 5","pn":"550","sv":"Skagafjörður","teg":"Einbýli","fnr":"2131514","full":1,"mat":76550,"matN":76750,"bruna":107550,"ar":1962,"fm":218.9,"herb":4,"lod":320,"ld":"2018-02","lv":25000},{"a":"Freyjugata 50","pn":"550","sv":"Skagafjörður","teg":"Einbýli","fnr":"2131564","full":1,"mat":66400,"matN":66750,"bruna":82500,"ar":1953,"fm":181.5,"herb":5,"lod":568,"ld":"2026-02","lv":78000},{"a":"Furuhlíð 3","pn":"550","sv":"Skagafjörður","teg":"Einbýli","fnr":"2131592","full":1,"mat":101250,"matN":101200,"bruna":129550,"ar":1981,"fm":268.6,"herb":6,"lod":705,"ld":"2026-06","lv":98000},{"a":"Furuhlíð 7","pn":"550","sv":"Skagafjörður","teg":"Einbýli","fnr":"2131596","full":1,"mat":109200,"matN":109050,"bruna":142700,"ar":1979,"fm":309.4,"herb":6,"lod":705,"ld":"2025-08","lv":92000},{"a":"Furuhlíð 8","pn":"550","sv":"Skagafjörður","teg":"Sérbýli","fnr":"2131597","full":1,"mat":78750,"matN":77900,"bruna":97280,"ar":1985,"fm":212.3,"herb":4,"lod":705,"ld":"2021-05","lv":49500},{"a":"Gilstún 1","pn":"550","sv":"Skagafjörður","teg":"Sérbýli","fnr":"2337188","full":1,"mat":90150,"matN":89600,"bruna":103000,"ar":2022,"fm":171.7,"herb":3,"lod":969,"ld":"2022-09","lv":76364},{"a":"Gilstún 10","pn":"550","sv":"Skagafjörður","teg":"Sérbýli","fnr":"2264398","full":1,"mat":68200,"matN":67900,"bruna":67050,"ar":2003,"fm":126.9,"herb":3,"lod":1050,"ld":"2026-04","lv":71900},{"a":"Gilstún 11","pn":"550","sv":"Skagafjörður","teg":"Sérbýli","fnr":"2219783","full":1,"mat":48850,"matN":48750,"bruna":50650,"ar":1994,"fm":81.3,"herb":2,"lod":900,"ld":"2023-05","lv":41500},{"a":"Gilstún 12","pn":"550","sv":"Skagafjörður","teg":"Sérbýli","fnr":"2264399","full":1,"mat":68200,"matN":67900,"bruna":67050,"ar":2003,"fm":126.9,"herb":3,"lod":1050,"ld":"2014-10","lv":26500},{"a":"Gilstún 14","pn":"550","sv":"Skagafjörður","teg":"Sérbýli","fnr":"2257563","full":1,"mat":67850,"matN":67550,"bruna":66650,"ar":2002,"fm":126.9,"herb":3,"lod":1050,"ld":"2018-12","lv":35000},{"a":"Gilstún 16","pn":"550","sv":"Skagafjörður","teg":"Sérbýli","fnr":"2257590","full":1,"mat":67850,"matN":67550,"bruna":66650,"ar":2002,"fm":126.9,"herb":3,"lod":1050,"ld":"2025-07","lv":63000},{"a":"Gilstún 17","pn":"550","sv":"Skagafjörður","teg":"Sérbýli","fnr":"2218761","full":1,"mat":48650,"matN":48550,"bruna":48050,"ar":1994,"fm":81.3,"herb":2,"lod":956,"ld":"2016-06","lv":17000},{"a":"Gilstún 18","pn":"550","sv":"Skagafjörður","teg":"Einbýli","fnr":"2219784","full":1,"mat":63750,"matN":63600,"bruna":68800,"ar":1994,"fm":129,"herb":2,"lod":875,"ld":"2008-07","lv":16000},{"a":"Gilstún 24","pn":"550","sv":"Skagafjörður","teg":"Einbýli","fnr":"2238057","full":1,"mat":78850,"matN":78800,"bruna":89800,"ar":1998,"fm":151.7,"herb":3,"lod":750,"ld":"2006-10","lv":23500},{"a":"Gilstún 26","pn":"550","sv":"Skagafjörður","teg":"Einbýli","fnr":"2285152","full":1,"mat":77700,"matN":77700,"bruna":85900,"ar":2005,"fm":146.7,"herb":4,"lod":750,"ld":"2020-02","lv":45000},{"a":"Gilstún 30","pn":"550","sv":"Skagafjörður","teg":"Einbýli","fnr":"2289470","full":1,"mat":96400,"matN":96150,"bruna":110700,"ar":2006,"fm":202.6,"herb":4,"lod":750,"ld":"2021-09","lv":78000},{"a":"Gilstún 4","pn":"550","sv":"Skagafjörður","teg":"Sérbýli","fnr":"2337189","full":1,"mat":82650,"matN":82200,"bruna":89800,"ar":2017,"fm":160.3,"herb":3,"lod":1019,"ld":"2019-02","lv":55000},{"a":"Gilstún 5","pn":"550","sv":"Skagafjörður","teg":"Sérbýli","fnr":"2255331","full":1,"mat":50950,"matN":50800,"bruna":42800,"ar":2001,"fm":81.3,"herb":2,"lod":900,"ld":"2021-12","lv":24000},{"a":"Gilstún 6","pn":"550","sv":"Skagafjörður","teg":"Einbýli","fnr":"2219780","full":1,"mat":41650,"matN":41700,"bruna":38650,"ar":1994,"fm":64,"herb":1,"lod":1035,"ld":"2015-04","lv":10629},{"a":"Gilstún 7","pn":"550","sv":"Skagafjörður","teg":"Sérbýli","fnr":"2255332","full":1,"mat":50950,"matN":50800,"bruna":42800,"ar":2001,"fm":81.3,"herb":2,"lod":900,"ld":"2020-03","lv":27000},{"a":"Gilstún 9","pn":"550","sv":"Skagafjörður","teg":"Sérbýli","fnr":"2219782","full":1,"mat":61700,"matN":61550,"bruna":66750,"ar":1994,"fm":116.1,"herb":3,"lod":900,"ld":"2019-03","lv":32500},{"a":"Grenihlíð 12","pn":"550","sv":"Skagafjörður","teg":"Sérbýli","fnr":"2131625","full":1,"mat":69850,"matN":69850,"bruna":87750,"ar":1980,"fm":181.5,"herb":3,"lod":256,"ld":"2020-08","lv":35000},{"a":"Grenihlíð 13","pn":"550","sv":"Skagafjörður","teg":"Sérbýli","fnr":"2131626","full":1,"mat":72200,"matN":72250,"bruna":99150,"ar":1988,"fm":186.6,"herb":3,"lod":229,"ld":"2024-02","lv":66000},{"a":"Grenihlíð 14","pn":"550","sv":"Skagafjörður","teg":"Einbýli","fnr":"2131627","full":1,"mat":58450,"matN":58950,"bruna":67900,"ar":1981,"fm":128.7,"herb":2,"lod":180,"ld":"2021-08","lv":37000},{"a":"Grenihlíð 15","pn":"550","sv":"Skagafjörður","teg":"Sérbýli","fnr":"2218069","full":1,"mat":76250,"matN":76300,"bruna":105170,"ar":1994,"fm":193.4,"herb":3,"lod":230,"ld":"2016-10","lv":30000},{"a":"Grenihlíð 17","pn":"550","sv":"Skagafjörður","teg":"Fjölbýli","fnr":"2131629","full":1,"mat":42650,"matN":42600,"bruna":45600,"ar":1993,"fm":76.4,"herb":1,"lod":840,"ld":"2021-05","lv":26500},{"a":"Grenihlíð 19","pn":"550","sv":"Skagafjörður","teg":"Fjölbýli","fnr":"2131631","full":1,"mat":43100,"matN":43050,"bruna":47700,"ar":1993,"fm":76.4,"herb":1,"lod":840,"ld":"2013-12","lv":15500},{"a":"Grenihlíð 2","pn":"550","sv":"Skagafjörður","teg":"Sérbýli","fnr":"2131615","full":1,"mat":72550,"matN":72850,"bruna":88250,"ar":1980,"fm":181.5,"herb":5,"lod":257,"ld":"2021-01","lv":40000},{"a":"Grenihlíð 20","pn":"550","sv":"Skagafjörður","teg":"Sérbýli","fnr":"2131634","full":1,"mat":58800,"matN":59250,"bruna":68050,"ar":1984,"fm":128.7,"herb":2,"lod":180,"ld":"2023-10","lv":45000},{"a":"Grenihlíð 24","pn":"550","sv":"Skagafjörður","teg":"Sérbýli","fnr":"2131636","full":1,"mat":59400,"matN":59800,"bruna":70900,"ar":1989,"fm":128.7,"herb":3,"lod":180,"ld":"2021-05","lv":38000},{"a":"Grenihlíð 26","pn":"550","sv":"Skagafjörður","teg":"Fjölbýli","fnr":"2131637","full":1,"mat":43150,"matN":43250,"bruna":49300,"ar":1989,"fm":79.2,"herb":1,"lod":1241,"ld":"2006-05","lv":7200},{"a":"Grenihlíð 26","pn":"550","sv":"Skagafjörður","teg":"Fjölbýli","fnr":"2131638","full":1,"mat":49500,"matN":49250,"bruna":60100,"ar":1989,"fm":103.8,"herb":2,"lod":1241,"ld":"2022-09","lv":35000},{"a":"Grenihlíð 28","pn":"550","sv":"Skagafjörður","teg":"Fjölbýli","fnr":"2131640","full":1,"mat":49000,"matN":48800,"bruna":59500,"ar":1989,"fm":102.2,"herb":2,"lod":1241,"ld":"2018-08","lv":25400},{"a":"Grenihlíð 3","pn":"550","sv":"Skagafjörður","teg":"Sérbýli","fnr":"2131616","full":1,"mat":77500,"matN":77350,"bruna":108450,"ar":1980,"fm":234,"herb":5,"lod":309,"ld":"2006-11","lv":19100},{"a":"Grenihlíð 32","pn":"550","sv":"Skagafjörður","teg":"Fjölbýli","fnr":"2131643","full":1,"mat":43150,"matN":43250,"bruna":45100,"ar":1989,"fm":79.2,"herb":1,"lod":1241,"ld":"2013-10","lv":12500},{"a":"Grenihlíð 32","pn":"550","sv":"Skagafjörður","teg":"Fjölbýli","fnr":"2131644","full":1,"mat":49500,"matN":49250,"bruna":60150,"ar":1989,"fm":103.8,"herb":2,"lod":1241,"ld":"2016-05","lv":14000},{"a":"Grenihlíð 7","pn":"550","sv":"Skagafjörður","teg":"Sérbýli","fnr":"2131620","full":1,"mat":69000,"matN":68800,"bruna":97550,"ar":1980,"fm":186,"herb":4,"lod":309,"ld":"2022-02","lv":60000},{"a":"Grenihlíð 8","pn":"550","sv":"Skagafjörður","teg":"Sérbýli","fnr":"2131621","full":1,"mat":55150,"matN":55450,"bruna":61650,"ar":1980,"fm":125.6,"herb":2,"lod":174,"ld":"2017-02","lv":22000},{"a":"Grenihlíð 9","pn":"550","sv":"Skagafjörður","teg":"Sérbýli","fnr":"2131622","full":1,"mat":75050,"matN":75150,"bruna":93700,"ar":1981,"fm":187.2,"herb":4,"lod":229,"ld":"2009-06","lv":18300},{"a":"Grundarstígur 1","pn":"550","sv":"Skagafjörður","teg":"Einbýli","fnr":"2131645","full":1,"mat":70900,"matN":70900,"bruna":89100,"ar":1966,"fm":183.2,"herb":4,"lod":690,"ld":"2012-05","lv":28000},{"a":"Grundarstígur 14","pn":"550","sv":"Skagafjörður","teg":"Einbýli","fnr":"2131665","full":1,"mat":72650,"matN":72550,"bruna":93450,"ar":1971,"fm":166.6,"herb":3,"lod":606,"ld":"2023-06","lv":72500},{"a":"Grundarstígur 20","pn":"550","sv":"Skagafjörður","teg":"Einbýli","fnr":"2131672","full":1,"mat":70650,"matN":70200,"bruna":87400,"ar":1971,"fm":170.7,"herb":4,"lod":652,"ld":"2010-09","lv":17200},{"a":"Grundarstígur 24","pn":"550","sv":"Skagafjörður","teg":"Einbýli","fnr":"2131675","full":1,"mat":72900,"matN":72900,"bruna":84550,"ar":1969,"fm":166.6,"herb":5,"lod":630,"ld":"2019-01","lv":40000},{"a":"Grundarstígur 26","pn":"550","sv":"Skagafjörður","teg":"Einbýli","fnr":"2131677","full":1,"mat":78250,"matN":78250,"bruna":93960,"ar":1969,"fm":193.3,"herb":4,"lod":630,"ld":"2025-06","lv":69900},{"a":"Grundarstígur 3","pn":"550","sv":"Skagafjörður","teg":"Einbýli","fnr":"2131648","full":1,"mat":67900,"matN":67900,"bruna":82600,"ar":1969,"fm":166.1,"herb":4,"lod":690,"ld":"2017-08","lv":33000},{"a":"Grundarstígur 6","pn":"550","sv":"Skagafjörður","teg":"Einbýli","fnr":"2131652","full":1,"mat":71550,"matN":71500,"bruna":85900,"ar":1968,"fm":166.6,"herb":4,"lod":606,"ld":"2026-02","lv":70000},{"a":"Grundarstígur 8","pn":"550","sv":"Skagafjörður","teg":"Einbýli","fnr":"2131655","full":1,"mat":73150,"matN":73150,"bruna":85850,"ar":1970,"fm":166.6,"herb":4,"lod":606,"ld":"2024-04","lv":70000},{"a":"Grundarstígur 9","pn":"550","sv":"Skagafjörður","teg":"Einbýli","fnr":"2131657","full":1,"mat":64500,"matN":64600,"bruna":68450,"ar":1968,"fm":137.5,"herb":3,"lod":646,"ld":"2024-11","lv":67000},{"a":"Háahlíð 14","pn":"550","sv":"Skagafjörður","teg":"Einbýli","fnr":"2131702","full":1,"mat":100600,"matN":100350,"bruna":135400,"ar":1977,"fm":282.9,"herb":7,"lod":800,"ld":"2014-04","lv":38000},{"a":"Háahlíð 3","pn":"550","sv":"Skagafjörður","teg":"Einbýli","fnr":"2131686","full":1,"mat":122250,"matN":121900,"bruna":148250,"ar":1981,"fm":274.2,"herb":6,"lod":800,"ld":"2015-09","lv":40000},{"a":"Háahlíð 6","pn":"550","sv":"Skagafjörður","teg":"Einbýli","fnr":"2131691","full":1,"mat":95000,"matN":94650,"bruna":118350,"ar":1977,"fm":261.4,"herb":6,"lod":800,"ld":"2022-10","lv":92000},{"a":"Háahlíð 8","pn":"550","sv":"Skagafjörður","teg":"Einbýli","fnr":"2131694","full":1,"mat":98950,"matN":98300,"bruna":141700,"ar":1979,"fm":299.4,"herb":6,"lod":800,"ld":"2006-05","lv":27500},{"a":"Hásæti 1A","pn":"550","sv":"Skagafjörður","teg":"Sérbýli","fnr":"2257218","full":1,"mat":66800,"matN":66550,"bruna":64850,"ar":2002,"fm":127.9,"herb":2,"lod":1072,"ld":"2017-06","lv":25000},{"a":"Hásæti 2B","pn":"550","sv":"Skagafjörður","teg":"Sérbýli","fnr":"2263561","full":1,"mat":67000,"matN":66750,"bruna":65470,"ar":2003,"fm":127.9,"herb":2,"lod":1007,"ld":"2023-06","lv":56000},{"a":"Hásæti 4B","pn":"550","sv":"Skagafjörður","teg":"Sérbýli","fnr":"2272031","full":1,"mat":67500,"matN":67250,"bruna":63820,"ar":2004,"fm":127.4,"herb":2,"lod":1161,"ld":"2009-06","lv":19500},{"a":"Hásæti 6A","pn":"550","sv":"Skagafjörður","teg":"Sérbýli","fnr":"2275587","full":1,"mat":67300,"matN":67050,"bruna":64200,"ar":2004,"fm":127.4,"herb":2,"lod":1059,"ld":"2023-04","lv":56500},{"a":"Hásæti 6B","pn":"550","sv":"Skagafjörður","teg":"Sérbýli","fnr":"2275589","full":1,"mat":67300,"matN":67050,"bruna":64200,"ar":2004,"fm":127.4,"herb":2,"lod":1059,"ld":"2025-12","lv":56400},{"a":"Hlíðarstígur 4","pn":"550","sv":"Skagafjörður","teg":"Einbýli","fnr":"2131719","full":1,"mat":61000,"matN":60950,"bruna":71350,"ar":1955,"fm":168.3,"herb":4,"lod":645,"ld":"2016-07","lv":22000},{"a":"Hólatún 1","pn":"550","sv":"Skagafjörður","teg":"Einbýli","fnr":"2131723","full":1,"mat":86550,"matN":86650,"bruna":113700,"ar":1989,"fm":183.5,"herb":3,"lod":714,"ld":"2006-06","lv":24500},{"a":"Hólatún 10","pn":"550","sv":"Skagafjörður","teg":"Einbýli","fnr":"2131737","full":1,"mat":84300,"matN":84250,"bruna":93700,"ar":1985,"fm":199.2,"herb":3,"lod":690,"ld":"2007-04","lv":23500},{"a":"Hólatún 12","pn":"550","sv":"Skagafjörður","teg":"Einbýli","fnr":"2131739","full":1,"mat":84900,"matN":84850,"bruna":108950,"ar":1985,"fm":196.5,"herb":4,"lod":690,"ld":"2023-03","lv":80000},{"a":"Hólatún 13","pn":"550","sv":"Skagafjörður","teg":"Einbýli","fnr":"2131740","full":1,"mat":80900,"matN":81000,"bruna":90100,"ar":1988,"fm":174.9,"herb":4,"lod":690,"ld":"2019-09","lv":50000},{"a":"Hólatún 14","pn":"550","sv":"Skagafjörður","teg":"Einbýli","fnr":"2131742","full":1,"mat":75200,"matN":75200,"bruna":82200,"ar":1985,"fm":160.6,"herb":3,"lod":690,"ld":"2013-09","lv":27500},{"a":"Hólatún 15","pn":"550","sv":"Skagafjörður","teg":"Einbýli","fnr":"2131744","full":1,"mat":79650,"matN":79850,"bruna":95100,"ar":1993,"fm":166.7,"herb":3,"lod":690,"ld":"2007-07","lv":26000},{"a":"Hólatún 2","pn":"550","sv":"Skagafjörður","teg":"Einbýli","fnr":"2131725","full":1,"mat":86750,"matN":86450,"bruna":102700,"ar":1986,"fm":207.2,"herb":5,"lod":690,"ld":"2010-05","lv":31000},{"a":"Hólatún 5","pn":"550","sv":"Skagafjörður","teg":"Einbýli","fnr":"2131730","full":1,"mat":93700,"matN":93450,"bruna":114700,"ar":1991,"fm":211,"herb":5,"lod":690,"ld":"2017-05","lv":45400},{"a":"Hólatún 8","pn":"550","sv":"Skagafjörður","teg":"Einbýli","fnr":"2131734","full":1,"mat":79600,"matN":79350,"bruna":86050,"ar":1989,"fm":174.7,"herb":4,"lod":690,"ld":"2025-12","lv":80000},{"a":"Hólavegur 1","pn":"550","sv":"Skagafjörður","teg":"Einbýli","fnr":"2131745","full":1,"mat":43150,"matN":43500,"bruna":44550,"ar":1946,"fm":90,"herb":1,"lod":418,"ld":"2021-04","lv":27200},{"a":"Hólavegur 10A","pn":"550","sv":"Skagafjörður","teg":"Sérbýli","fnr":"2131759","full":1,"mat":33200,"matN":33050,"bruna":41700,"ar":1948,"fm":63.7,"herb":3,"lod":850,"ld":"2017-09","lv":13333},{"a":"Hólavegur 10B","pn":"550","sv":"Skagafjörður","teg":"Sérbýli","fnr":"2131760","full":1,"mat":31700,"matN":31600,"bruna":39400,"ar":1948,"fm":67.9,"herb":3,"lod":850,"ld":"2023-07","lv":25000},{"a":"Hólavegur 11","pn":"550","sv":"Skagafjörður","teg":"Einbýli","fnr":"2131761","full":1,"mat":52700,"matN":52750,"bruna":61600,"ar":1948,"fm":124.7,"herb":3,"lod":412,"ld":"2017-08","lv":28000},{"a":"Hólavegur 12","pn":"550","sv":"Skagafjörður","teg":"Einbýli","fnr":"2131763","full":1,"mat":46700,"matN":46600,"bruna":52750,"ar":1948,"fm":110,"herb":2,"lod":560,"ld":"2026-03","lv":37500},{"a":"Hólavegur 15","pn":"550","sv":"Skagafjörður","teg":"Fjölbýli","fnr":"2131767","full":1,"mat":48050,"matN":47850,"bruna":58000,"ar":1960,"fm":124.5,"herb":2,"lod":525,"ld":"2023-10","lv":42000},{"a":"Hólavegur 15","pn":"550","sv":"Skagafjörður","teg":"Fjölbýli","fnr":"2131766","full":1,"mat":45550,"matN":45300,"bruna":53650,"ar":1960,"fm":107.1,"herb":3,"lod":525,"ld":"2025-10","lv":46000},{"a":"Hólavegur 17","pn":"550","sv":"Skagafjörður","teg":"Sérbýli","fnr":"2131771","full":1,"mat":39650,"matN":39550,"bruna":51050,"ar":1950,"fm":102.6,"herb":4,"lod":462,"ld":"2016-10","lv":17800},{"a":"Hólavegur 17","pn":"550","sv":"Skagafjörður","teg":"Sérbýli","fnr":"2131770","full":1,"mat":44750,"matN":44650,"bruna":57390,"ar":1950,"fm":123.7,"herb":3,"lod":462,"ld":"2017-11","lv":18000},{"a":"Hólavegur 18","pn":"550","sv":"Skagafjörður","teg":"Einbýli","fnr":"2131773","full":1,"mat":61200,"matN":61150,"bruna":77700,"ar":1954,"fm":150,"herb":3,"lod":550,"ld":"2015-09","lv":27000},{"a":"Hólavegur 2","pn":"550","sv":"Skagafjörður","teg":"Einbýli","fnr":"2131746","full":1,"mat":43500,"matN":43950,"bruna":54850,"ar":1945,"fm":94.3,"herb":2,"lod":350,"ld":"2022-11","lv":41000},{"a":"Hólavegur 20","pn":"550","sv":"Skagafjörður","teg":"Einbýli","fnr":"2131777","full":1,"mat":56950,"matN":56750,"bruna":65500,"ar":1955,"fm":137.5,"herb":2,"lod":661,"ld":"2022-07","lv":30000},{"a":"Hólavegur 21","pn":"550","sv":"Skagafjörður","teg":"Einbýli","fnr":"2131779","full":1,"mat":60100,"matN":59950,"bruna":73350,"ar":1960,"fm":146.9,"herb":3,"lod":462,"ld":"2018-02","lv":26000},{"a":"Hólavegur 22","pn":"550","sv":"Skagafjörður","teg":"Fjölbýli","fnr":"2131782","full":1,"mat":48000,"matN":47950,"bruna":60450,"ar":1957,"fm":125.7,"herb":2,"lod":643,"ld":"2007-06","lv":14200},{"a":"Hólavegur 23","pn":"550","sv":"Skagafjörður","teg":"Einbýli","fnr":"2131785","full":1,"mat":56700,"matN":56500,"bruna":68700,"ar":1960,"fm":138.3,"herb":4,"lod":462,"ld":"2010-07","lv":17300},{"a":"Hólavegur 24","pn":"550","sv":"Skagafjörður","teg":"Fjölbýli","fnr":"2131787","full":1,"mat":47700,"matN":47500,"bruna":60050,"ar":1962,"fm":119.5,"herb":3,"lod":615,"ld":"2022-12","lv":41000},{"a":"Hólavegur 26","pn":"550","sv":"Skagafjörður","teg":"Fjölbýli","fnr":"2131792","full":1,"mat":null,"matN":null,"bruna":null,"ar":1958,"fm":98.1,"herb":null,"lod":640,"ld":"2010-04","lv":8000},{"a":"Hólavegur 26","pn":"550","sv":"Skagafjörður","teg":"Einbýli","fnr":"2131791","full":1,"mat":79200,"matN":79150,"bruna":121500,"ar":1958,"fm":231.9,"herb":6,"lod":640,"ld":"2024-06","lv":89000},{"a":"Hólavegur 27","pn":"550","sv":"Skagafjörður","teg":"Einbýli","fnr":"2131794","full":1,"mat":85750,"matN":85900,"bruna":108500,"ar":1958,"fm":265.8,"herb":6,"lod":462,"ld":"2020-06","lv":44500},{"a":"Hólavegur 28","pn":"550","sv":"Skagafjörður","teg":"Fjölbýli","fnr":"2131796","full":1,"mat":53500,"matN":53150,"bruna":65100,"ar":1960,"fm":139,"herb":3,"lod":615,"ld":"2023-05","lv":40000},{"a":"Hólavegur 28","pn":"550","sv":"Skagafjörður","teg":"Fjölbýli","fnr":"2131797","full":1,"mat":53450,"matN":53150,"bruna":65450,"ar":1960,"fm":138.9,"herb":3,"lod":615,"ld":"2021-05","lv":35000},{"a":"Hólavegur 30","pn":"550","sv":"Skagafjörður","teg":"Fjölbýli","fnr":"2131802","full":1,"mat":52050,"matN":51550,"bruna":65700,"ar":1961,"fm":142,"herb":3,"lod":615,"ld":"2020-09","lv":34900},{"a":"Hólavegur 31","pn":"550","sv":"Skagafjörður","teg":"Einbýli","fnr":"2131806","full":1,"mat":70250,"matN":70500,"bruna":69550,"ar":1960,"fm":142.5,"herb":4,"lod":462,"ld":"2026-01","lv":55000},{"a":"Hólavegur 32","pn":"550","sv":"Skagafjörður","teg":"Fjölbýli","fnr":"2131809","full":1,"mat":53350,"matN":53150,"bruna":67630,"ar":1961,"fm":145,"herb":2,"lod":615,"ld":"2013-10","lv":21000},{"a":"Hólavegur 33","pn":"550","sv":"Skagafjörður","teg":"Fjölbýli","fnr":"2131813","full":1,"mat":45200,"matN":45150,"bruna":57450,"ar":1959,"fm":120.8,"herb":5,"lod":462,"ld":"2026-07","lv":45500},{"a":"Hólavegur 34","pn":"550","sv":"Skagafjörður","teg":"Fjölbýli","fnr":"2131815","full":1,"mat":48400,"matN":48000,"bruna":56650,"ar":1966,"fm":116.1,"herb":3,"lod":636,"ld":"2015-04","lv":19000},{"a":"Hólavegur 36","pn":"550","sv":"Skagafjörður","teg":"Fjölbýli","fnr":"2131820","full":1,"mat":60600,"matN":60200,"bruna":73400,"ar":1969,"fm":158.1,"herb":5,"lod":649,"ld":"2022-02","lv":49500},{"a":"Hólavegur 36","pn":"550","sv":"Skagafjörður","teg":"Fjölbýli","fnr":"2131821","full":1,"mat":61250,"matN":61100,"bruna":82250,"ar":1969,"fm":169.4,"herb":6,"lod":649,"ld":"2023-05","lv":47500},{"a":"Hólavegur 37","pn":"550","sv":"Skagafjörður","teg":"Einbýli","fnr":"2131824","full":1,"mat":69650,"matN":69700,"bruna":89750,"ar":1958,"fm":197.3,"herb":3,"lod":462,"ld":"2019-01","lv":14000},{"a":"Hólavegur 38","pn":"550","sv":"Skagafjörður","teg":"Fjölbýli","fnr":"2131825","full":1,"mat":60900,"matN":60550,"bruna":76200,"ar":1962,"fm":165.3,"herb":3,"lod":615,"ld":"2022-08","lv":59000},{"a":"Hólavegur 38","pn":"550","sv":"Skagafjörður","teg":"Fjölbýli","fnr":"2131826","full":1,"mat":50550,"matN":50400,"bruna":62000,"ar":1962,"fm":129.8,"herb":4,"lod":615,"ld":"2015-11","lv":14000},{"a":"Hólavegur 4","pn":"550","sv":"Skagafjörður","teg":"Einbýli","fnr":"2131748","full":1,"mat":57150,"matN":57400,"bruna":72100,"ar":1945,"fm":147.3,"herb":3,"lod":575,"ld":"2025-10","lv":46000},{"a":"Hólavegur 40","pn":"550","sv":"Skagafjörður","teg":"Fjölbýli","fnr":"2131831","full":1,"mat":32600,"matN":32600,"bruna":43880,"ar":1973,"fm":78.5,"herb":2,"lod":646,"ld":"2021-04","lv":24000},{"a":"Hólavegur 40","pn":"550","sv":"Skagafjörður","teg":"Fjölbýli","fnr":"2131829","full":1,"mat":39500,"matN":39100,"bruna":51000,"ar":1973,"fm":110.9,"herb":2,"lod":646,"ld":"2022-08","lv":39700},{"a":"Hólavegur 40","pn":"550","sv":"Skagafjörður","teg":"Fjölbýli","fnr":"2131828","full":1,"mat":39700,"matN":39250,"bruna":52050,"ar":1973,"fm":111,"herb":2,"lod":646,"ld":"2018-07","lv":22500},{"a":"Hólavegur 42","pn":"550","sv":"Skagafjörður","teg":"Fjölbýli","fnr":"2131837","full":1,"mat":33050,"matN":33050,"bruna":42240,"ar":1974,"fm":78.5,"herb":2,"lod":646,"ld":"2016-01","lv":14000},{"a":"Hólavegur 42","pn":"550","sv":"Skagafjörður","teg":"Fjölbýli","fnr":"2131836","full":1,"mat":32700,"matN":32750,"bruna":41440,"ar":1974,"fm":78.5,"herb":2,"lod":646,"ld":"2023-02","lv":33500},{"a":"Hólavegur 42","pn":"550","sv":"Skagafjörður","teg":"Fjölbýli","fnr":"2131839","full":1,"mat":39250,"matN":38900,"bruna":51300,"ar":1974,"fm":111,"herb":2,"lod":646,"ld":"2026-07","lv":38000},{"a":"Hólavegur 42","pn":"550","sv":"Skagafjörður","teg":"Fjölbýli","fnr":"2131838","full":1,"mat":39250,"matN":38900,"bruna":51050,"ar":1974,"fm":111,"herb":2,"lod":646,"ld":"2021-02","lv":29500},{"a":"Hólavegur 5","pn":"550","sv":"Skagafjörður","teg":"Einbýli","fnr":"2131750","full":1,"mat":53550,"matN":53800,"bruna":65600,"ar":1950,"fm":127.8,"herb":3,"lod":408,"ld":"2023-09","lv":40000},{"a":"Hólavegur 6","pn":"550","sv":"Skagafjörður","teg":"Einbýli","fnr":"2131752","full":1,"mat":56950,"matN":57350,"bruna":64750,"ar":1945,"fm":138.3,"herb":4,"lod":565,"ld":"2010-07","lv":17000},{"a":"Hólavegur 7","pn":"550","sv":"Skagafjörður","teg":"Einbýli","fnr":"2131754","full":1,"mat":55050,"matN":55250,"bruna":72100,"ar":1946,"fm":150.7,"herb":3,"lod":406,"ld":"2024-09","lv":50000},{"a":"Hólavegur 8","pn":"550","sv":"Skagafjörður","teg":"Einbýli","fnr":"2131755","full":1,"mat":53850,"matN":54150,"bruna":59860,"ar":1946,"fm":132.5,"herb":3,"lod":585,"ld":"2015-11","lv":19600},{"a":"Hólavegur 9","pn":"550","sv":"Skagafjörður","teg":"Einbýli","fnr":"2131757","full":1,"mat":74000,"matN":74650,"bruna":98250,"ar":1946,"fm":229.8,"herb":7,"lod":440,"ld":"2021-04","lv":56500},{"a":"Hólmagrund 11","pn":"550","sv":"Skagafjörður","teg":"Einbýli","fnr":"2131861","full":1,"mat":80900,"matN":80900,"bruna":116100,"ar":1962,"fm":252.8,"herb":6,"lod":462,"ld":"2022-02","lv":61000},{"a":"Hólmagrund 12","pn":"550","sv":"Skagafjörður","teg":"Einbýli","fnr":"2131862","full":1,"mat":72750,"matN":72350,"bruna":89400,"ar":1964,"fm":187.9,"herb":3,"lod":460,"ld":"2015-12","lv":20000},{"a":"Hólmagrund 13","pn":"550","sv":"Skagafjörður","teg":"Einbýli","fnr":"2131864","full":1,"mat":66600,"matN":66700,"bruna":74900,"ar":1962,"fm":136.9,"herb":3,"lod":462,"ld":"2022-11","lv":56000},{"a":"Hólmagrund 14","pn":"550","sv":"Skagafjörður","teg":"Einbýli","fnr":"2131866","full":1,"mat":62800,"matN":63000,"bruna":66850,"ar":1962,"fm":147,"herb":3,"lod":462,"ld":"2018-11","lv":37000},{"a":"Hólmagrund 22","pn":"550","sv":"Skagafjörður","teg":"Einbýli","fnr":"2131879","full":1,"mat":70400,"matN":70650,"bruna":85000,"ar":1967,"fm":164.1,"herb":4,"lod":462,"ld":"2025-10","lv":74000},{"a":"Hólmagrund 24","pn":"550","sv":"Skagafjörður","teg":"Einbýli","fnr":"2131882","full":1,"mat":65500,"matN":65550,"bruna":77050,"ar":1967,"fm":150.5,"herb":3,"lod":438,"ld":"2021-11","lv":27000},{"a":"Hólmagrund 3","pn":"550","sv":"Skagafjörður","teg":"Einbýli","fnr":"2131847","full":1,"mat":50600,"matN":50500,"bruna":53900,"ar":1961,"fm":112.6,"herb":3,"lod":462,"ld":"2021-02","lv":26000},{"a":"Hólmagrund 4","pn":"550","sv":"Skagafjörður","teg":"Einbýli","fnr":"2131848","full":1,"mat":65200,"matN":65250,"bruna":73350,"ar":1963,"fm":155.8,"herb":3,"lod":462,"ld":"2020-02","lv":36000},{"a":"Hólmagrund 6","pn":"550","sv":"Skagafjörður","teg":"Einbýli","fnr":"2131852","full":1,"mat":65550,"matN":65450,"bruna":75300,"ar":1962,"fm":164.3,"herb":3,"lod":462,"ld":"2024-11","lv":48000},{"a":"Hólmagrund 8","pn":"550","sv":"Skagafjörður","teg":"Einbýli","fnr":"2131855","full":1,"mat":61700,"matN":61550,"bruna":86750,"ar":1964,"fm":150.4,"herb":2,"lod":525,"ld":"2019-09","lv":40000},{"a":"Hvannahlíð 1","pn":"550","sv":"Skagafjörður","teg":"Einbýli","fnr":"2131884","full":1,"mat":88950,"matN":88700,"bruna":113950,"ar":1991,"fm":200.3,"herb":5,"lod":705,"ld":"2020-12","lv":62000},{"a":"Hvannahlíð 2","pn":"550","sv":"Skagafjörður","teg":"Einbýli","fnr":"2131886","full":1,"mat":86600,"matN":86250,"bruna":100000,"ar":1980,"fm":186.4,"herb":5,"lod":705,"ld":"2010-09","lv":28000},{"a":"Hvannahlíð 8","pn":"550","sv":"Skagafjörður","teg":"Einbýli","fnr":"2131896","full":1,"mat":97700,"matN":97150,"bruna":129750,"ar":1981,"fm":263.6,"herb":4,"lod":705,"ld":"2020-09","lv":58000},{"a":"Iðutún 10","pn":"550","sv":"Skagafjörður","teg":"Einbýli","fnr":"2288918","full":1,"mat":86500,"matN":86500,"bruna":91400,"ar":2006,"fm":170,"herb":4,"lod":750,"ld":"2025-12","lv":84000},{"a":"Iðutún 13","pn":"550","sv":"Skagafjörður","teg":"Sérbýli","fnr":"2288805","full":1,"mat":72900,"matN":72550,"bruna":76050,"ar":2006,"fm":141.7,"herb":3,"lod":1187,"ld":"2011-10","lv":26200},{"a":"Iðutún 15","pn":"550","sv":"Skagafjörður","teg":"Sérbýli","fnr":"2288806","full":0,"mat":72900,"matN":72550,"bruna":72850,"ar":2006,"fm":141.7,"herb":3,"lod":1187,"ld":"2006-05","lv":17700},{"a":"Iðutún 16","pn":"550","sv":"Skagafjörður","teg":"Einbýli","fnr":"2309417","full":1,"mat":98600,"matN":98300,"bruna":109830,"ar":2007,"fm":213.6,"herb":5,"lod":858,"ld":"2022-09","lv":92750},{"a":"Jöklatún 1","pn":"550","sv":"Skagafjörður","teg":"Sérbýli","fnr":"2131899","full":1,"mat":59200,"matN":58850,"bruna":69400,"ar":1992,"fm":110.4,"herb":3,"lod":966,"ld":"2017-06","lv":26000},{"a":"Jöklatún 10","pn":"550","sv":"Skagafjörður","teg":"Sérbýli","fnr":"2131905","full":1,"mat":58250,"matN":58350,"bruna":66750,"ar":1990,"fm":108.3,"herb":3,"lod":3840,"ld":"2015-03","lv":23000},{"a":"Jöklatún 12","pn":"550","sv":"Skagafjörður","teg":"Sérbýli","fnr":"2131906","full":1,"mat":52000,"matN":52200,"bruna":58800,"ar":1990,"fm":90.4,"herb":2,"lod":3840,"ld":"2010-11","lv":15500},{"a":"Jöklatún 2","pn":"550","sv":"Skagafjörður","teg":"Sérbýli","fnr":"2131901","full":1,"mat":58250,"matN":58350,"bruna":66750,"ar":1990,"fm":108.3,"herb":3,"lod":3840,"ld":"2022-11","lv":51000},{"a":"Jöklatún 20","pn":"550","sv":"Skagafjörður","teg":"Sérbýli","fnr":"2131910","full":1,"mat":51750,"matN":51950,"bruna":56800,"ar":1990,"fm":90.4,"herb":2,"lod":3840,"ld":"2024-10","lv":47900},{"a":"Jöklatún 22","pn":"550","sv":"Skagafjörður","teg":"Sérbýli","fnr":"2131911","full":1,"mat":51750,"matN":51950,"bruna":56800,"ar":1990,"fm":90.4,"herb":2,"lod":3840,"ld":"2016-06","lv":16100},{"a":"Jöklatún 24","pn":"550","sv":"Skagafjörður","teg":"Sérbýli","fnr":"2131912","full":1,"mat":58250,"matN":58350,"bruna":66750,"ar":1990,"fm":108.3,"herb":3,"lod":3840,"ld":"2011-05","lv":18500},{"a":"Jöklatún 4","pn":"550","sv":"Skagafjörður","teg":"Sérbýli","fnr":"2131902","full":1,"mat":51750,"matN":51950,"bruna":56800,"ar":1990,"fm":90.4,"herb":2,"lod":3840,"ld":"2011-08","lv":14800},{"a":"Jöklatún 6","pn":"550","sv":"Skagafjörður","teg":"Sérbýli","fnr":"2131903","full":1,"mat":51750,"matN":51950,"bruna":56800,"ar":1990,"fm":90.4,"herb":2,"lod":3840,"ld":"2017-05","lv":23600},{"a":"Jöklatún 7","pn":"550","sv":"Skagafjörður","teg":"Sérbýli","fnr":"2131914","full":1,"mat":74450,"matN":74200,"bruna":87400,"ar":1992,"fm":94.9,"herb":2,"lod":966,"ld":"2013-08","lv":17600},{"a":"Jöklatún 8","pn":"550","sv":"Skagafjörður","teg":"Sérbýli","fnr":"2131904","full":1,"mat":58250,"matN":58350,"bruna":66750,"ar":1990,"fm":108.3,"herb":3,"lod":3840,"ld":"2020-07","lv":35000},{"a":"Kambastígur 2A","pn":"550","sv":"Skagafjörður","teg":"Fjölbýli","fnr":"2131917","full":1,"mat":45750,"matN":45700,"bruna":56150,"ar":1927,"fm":137.7,"herb":3,"lod":434,"ld":"2023-02","lv":22000},{"a":"Kambastígur 2B","pn":"550","sv":"Skagafjörður","teg":"Fjölbýli","fnr":"2131918","full":1,"mat":35250,"matN":35450,"bruna":39100,"ar":1927,"fm":110.7,"herb":4,"lod":434,"ld":"2022-07","lv":26000},{"a":"Kambastígur 4","pn":"550","sv":"Skagafjörður","teg":"Einbýli","fnr":"2131919","full":1,"mat":49850,"matN":50100,"bruna":53250,"ar":1981,"fm":97.8,"herb":3,"lod":181,"ld":"2019-08","lv":21700},{"a":"Kambastígur 8","pn":"550","sv":"Skagafjörður","teg":"Einbýli","fnr":"2131921","full":1,"mat":44800,"matN":44400,"bruna":48825,"ar":1925,"fm":161.1,"herb":3,"lod":550,"ld":"2025-05","lv":35000},{"a":"Kleifatún 13","pn":"550","sv":"Skagafjörður","teg":"Sérbýli","fnr":"2309434","full":1,"mat":68350,"matN":68100,"bruna":64750,"ar":2007,"fm":127.4,"herb":3,"lod":1080,"ld":"2015-01","lv":26500},{"a":"Kleifatún 6A","pn":"550","sv":"Skagafjörður","teg":"Sérbýli","fnr":"2337208","full":1,"mat":87800,"matN":87250,"bruna":93900,"ar":2019,"fm":170.3,"herb":3,"lod":825,"ld":"2023-05","lv":85500},{"a":"Kleifatún 6B","pn":"550","sv":"Skagafjörður","teg":"Sérbýli","fnr":"2508532","full":1,"mat":87800,"matN":87250,"bruna":93900,"ar":2019,"fm":170.3,"herb":3,"lod":825,"ld":"2024-11","lv":85500},{"a":"Knarrarstígur 2","pn":"550","sv":"Skagafjörður","teg":"Fjölbýli","fnr":"2131935","full":1,"mat":29200,"matN":29150,"bruna":34500,"ar":1947,"fm":74,"herb":1,"lod":209,"ld":"2021-05","lv":18700},{"a":"Knarrarstígur 4","pn":"550","sv":"Skagafjörður","teg":"Fjölbýli","fnr":"2131937","full":1,"mat":27550,"matN":27600,"bruna":33800,"ar":1947,"fm":64.3,"herb":1,"lod":209,"ld":"2022-04","lv":22500},{"a":"Knarrarstígur 4","pn":"550","sv":"Skagafjörður","teg":"Fjölbýli","fnr":"2131938","full":1,"mat":29750,"matN":29950,"bruna":31050,"ar":1947,"fm":67.6,"herb":2,"lod":209,"ld":"2025-12","lv":37000},{"a":"Kvistahlíð 1","pn":"550","sv":"Skagafjörður","teg":"Sérbýli","fnr":"2131939","full":1,"mat":68900,"matN":68900,"bruna":90250,"ar":1980,"fm":152.2,"herb":3,"lod":403,"ld":"2011-02","lv":24250},{"a":"Kvistahlíð 11","pn":"550","sv":"Skagafjörður","teg":"Sérbýli","fnr":"2131947","full":1,"mat":51050,"matN":50850,"bruna":53000,"ar":1990,"fm":88.4,"herb":2,"lod":952,"ld":"2020-12","lv":27500},{"a":"Kvistahlíð 13","pn":"550","sv":"Skagafjörður","teg":"Sérbýli","fnr":"2131948","full":1,"mat":41500,"matN":41400,"bruna":46250,"ar":1990,"fm":76.4,"herb":1,"lod":963,"ld":"2018-04","lv":19000},{"a":"Kvistahlíð 17","pn":"550","sv":"Skagafjörður","teg":"Sérbýli","fnr":"2131950","full":1,"mat":46250,"matN":46150,"bruna":46250,"ar":1990,"fm":76.4,"herb":1,"lod":884,"ld":"2023-10","lv":32000},{"a":"Kvistahlíð 19","pn":"550","sv":"Skagafjörður","teg":"Sérbýli","fnr":"2131951","full":1,"mat":51250,"matN":51100,"bruna":54000,"ar":1990,"fm":88.4,"herb":2,"lod":884,"ld":"2017-06","lv":22000},{"a":"Kvistahlíð 8","pn":"550","sv":"Skagafjörður","teg":"Einbýli","fnr":"2337216","full":1,"mat":105200,"matN":104950,"bruna":117400,"ar":2017,"fm":212.5,"herb":5,"lod":859,"ld":"2025-06","lv":103000},{"a":"Kvistahlíð 9","pn":"550","sv":"Skagafjörður","teg":"Sérbýli","fnr":"2131946","full":1,"mat":46700,"matN":46600,"bruna":47100,"ar":1990,"fm":76.4,"herb":1,"lod":952,"ld":"2017-05","lv":17000},{"a":"Laugatún 1","pn":"550","sv":"Skagafjörður","teg":"Fjölbýli","fnr":"2131953","full":1,"mat":58050,"matN":57700,"bruna":66600,"ar":1992,"fm":119.7,"herb":4,"lod":750,"ld":"2022-06","lv":45000},{"a":"Laugatún 10","pn":"550","sv":"Skagafjörður","teg":"Sérbýli","fnr":"2131964","full":1,"mat":65500,"matN":65000,"bruna":79450,"ar":1992,"fm":129.5,"herb":4,"lod":1025,"ld":"2019-05","lv":32500},{"a":"Laugatún 11","pn":"550","sv":"Skagafjörður","teg":"Fjölbýli","fnr":"2216410","full":1,"mat":53950,"matN":53700,"bruna":59000,"ar":1994,"fm":104.7,"herb":3,"lod":750,"ld":"2021-03","lv":39500},{"a":"Laugatún 13","pn":"550","sv":"Skagafjörður","teg":"Fjölbýli","fnr":"2323987","full":1,"mat":46600,"matN":46450,"bruna":52000,"ar":2010,"fm":130.3,"herb":3,"lod":1770,"ld":"2018-01","lv":24600},{"a":"Laugatún 13","pn":"550","sv":"Skagafjörður","teg":"Fjölbýli","fnr":"2323985","full":1,"mat":46800,"matN":46600,"bruna":50750,"ar":2010,"fm":129.2,"herb":3,"lod":1770,"ld":"2025-12","lv":31000},{"a":"Laugatún 17","pn":"550","sv":"Skagafjörður","teg":"Fjölbýli","fnr":"2323996","full":1,"mat":46550,"matN":46400,"bruna":52000,"ar":2010,"fm":128.5,"herb":2,"lod":1632,"ld":"2018-05","lv":24600},{"a":"Laugatún 19","pn":"550","sv":"Skagafjörður","teg":"Fjölbýli","fnr":"2323995","full":1,"mat":48800,"matN":48600,"bruna":54500,"ar":2010,"fm":133.8,"herb":4,"lod":1632,"ld":"2025-12","lv":33000},{"a":"Laugatún 5","pn":"550","sv":"Skagafjörður","teg":"Fjölbýli","fnr":"2131958","full":1,"mat":53450,"matN":53200,"bruna":58950,"ar":1992,"fm":104.7,"herb":3,"lod":750,"ld":"2007-08","lv":12500},{"a":"Laugatún 6","pn":"550","sv":"Skagafjörður","teg":"Sérbýli","fnr":"2131960","full":1,"mat":79650,"matN":78850,"bruna":94700,"ar":1992,"fm":178,"herb":7,"lod":1025,"ld":"2026-02","lv":78500},{"a":"Laugatún 7","pn":"550","sv":"Skagafjörður","teg":"Fjölbýli","fnr":"2131963","full":1,"mat":58050,"matN":57700,"bruna":66600,"ar":1992,"fm":119.7,"herb":4,"lod":750,"ld":"2007-04","lv":14300},{"a":"Laugatún 7","pn":"550","sv":"Skagafjörður","teg":"Fjölbýli","fnr":"2131962","full":1,"mat":53450,"matN":53200,"bruna":58950,"ar":1992,"fm":104.7,"herb":3,"lod":750,"ld":"2022-06","lv":33000},{"a":"Laugatún 8","pn":"550","sv":"Skagafjörður","teg":"Sérbýli","fnr":"2131961","full":1,"mat":58650,"matN":58350,"bruna":68600,"ar":1992,"fm":109.5,"herb":3,"lod":1025,"ld":"2016-03","lv":22600},{"a":"Laugatún 9","pn":"550","sv":"Skagafjörður","teg":"Fjölbýli","fnr":"2213301","full":1,"mat":53950,"matN":53700,"bruna":59000,"ar":1994,"fm":104.7,"herb":3,"lod":750,"ld":"2022-06","lv":38000},{"a":"Laugatún 9","pn":"550","sv":"Skagafjörður","teg":"Fjölbýli","fnr":"2213302","full":1,"mat":58600,"matN":58300,"bruna":66700,"ar":1994,"fm":119.7,"herb":4,"lod":750,"ld":"2026-02","lv":55100},{"a":"Lerkihlíð 9","pn":"550","sv":"Skagafjörður","teg":"Einbýli","fnr":"2131972","full":1,"mat":103700,"matN":103350,"bruna":150600,"ar":1982,"fm":301.4,"herb":7,"lod":709,"ld":"2016-08","lv":42300},{"a":"Lindargata 1","pn":"550","sv":"Skagafjörður","teg":"Fjölbýli","fnr":"2131973","full":1,"mat":50080,"matN":53720,"bruna":159200,"ar":1942,"fm":164.5,"herb":null,"lod":293,"ld":"2010-05","lv":13500},{"a":"Lindargata 1","pn":"550","sv":"Skagafjörður","teg":"Fjölbýli","fnr":"2131974","full":1,"mat":null,"matN":null,"bruna":null,"ar":1942,"fm":120.6,"herb":null,"lod":293,"ld":"2011-10","lv":16000},{"a":"Lindargata 11","pn":"550","sv":"Skagafjörður","teg":"Einbýli","fnr":"2131988","full":1,"mat":41950,"matN":42250,"bruna":58900,"ar":1936,"fm":104.9,"herb":3,"lod":300,"ld":"2024-07","lv":46500},{"a":"Lindargata 13","pn":"550","sv":"Skagafjörður","teg":"Einbýli","fnr":"2131990","full":1,"mat":37350,"matN":37650,"bruna":49550,"ar":1871,"fm":92.5,"herb":2,"lod":504,"ld":"2025-12","lv":49000},{"a":"Lindargata 15","pn":"550","sv":"Skagafjörður","teg":"Fjölbýli","fnr":"2131991","full":1,"mat":38800,"matN":38500,"bruna":43700,"ar":1947,"fm":93.8,"herb":3,"lod":638,"ld":"2008-07","lv":9700},{"a":"Lindargata 17","pn":"550","sv":"Skagafjörður","teg":"Einbýli","fnr":"2131993","full":1,"mat":46800,"matN":46900,"bruna":57950,"ar":1945,"fm":117,"herb":4,"lod":598,"ld":"2008-09","lv":16800},{"a":"Lindargata 5","pn":"550","sv":"Skagafjörður","teg":"Fjölbýli","fnr":"2131979","full":1,"mat":21750,"matN":21850,"bruna":25750,"ar":1930,"fm":51.2,"herb":2,"lod":319,"ld":"2022-08","lv":25750},{"a":"Lindargata 5","pn":"550","sv":"Skagafjörður","teg":"Fjölbýli","fnr":"2131977","full":1,"mat":26350,"matN":26650,"bruna":33600,"ar":1930,"fm":68.8,"herb":2,"lod":319,"ld":"2026-03","lv":26500},{"a":"Lindargata 7","pn":"550","sv":"Skagafjörður","teg":"Einbýli","fnr":"2131982","full":1,"mat":55350,"matN":55650,"bruna":63030,"ar":1871,"fm":144.8,"herb":2,"lod":480,"ld":"2020-07","lv":30000},{"a":"Melatún 3A","pn":"550","sv":"Skagafjörður","teg":"Sérbýli","fnr":"2505243","full":0,"mat":88500,"matN":88000,"bruna":100300,"ar":2020,"fm":174.3,"herb":4,"lod":1064,"ld":"2021-08","lv":54000},{"a":"Nestún 24A","pn":"550","sv":"Skagafjörður","teg":"Sérbýli","fnr":"2525279","full":1,"mat":94000,"matN":93350,"bruna":113750,"ar":2024,"fm":178.9,"herb":3,"lod":1151,"ld":"2026-06","lv":123000},{"a":"Nestún 24B","pn":"550","sv":"Skagafjörður","teg":"Sérbýli","fnr":"2529092","full":1,"mat":94000,"matN":93350,"bruna":114250,"ar":null,"fm":178.9,"herb":3,"lod":1151,"ld":"2024-03","lv":115798},{"a":"Raftahlíð 1","pn":"550","sv":"Skagafjörður","teg":"Sérbýli","fnr":"2131994","full":1,"mat":52450,"matN":52350,"bruna":59750,"ar":1978,"fm":112.2,"herb":2,"lod":322,"ld":"2023-05","lv":54000},{"a":"Raftahlíð 12","pn":"550","sv":"Skagafjörður","teg":"Sérbýli","fnr":"2132006","full":1,"mat":66650,"matN":66750,"bruna":84900,"ar":1975,"fm":148.6,"herb":3,"lod":370,"ld":"2007-06","lv":18000},{"a":"Raftahlíð 13","pn":"550","sv":"Skagafjörður","teg":"Sérbýli","fnr":"2132007","full":1,"mat":61050,"matN":60800,"bruna":75700,"ar":1977,"fm":137,"herb":3,"lod":380,"ld":"2021-07","lv":49750},{"a":"Raftahlíð 14","pn":"550","sv":"Skagafjörður","teg":"Sérbýli","fnr":"2132008","full":1,"mat":67100,"matN":67250,"bruna":86800,"ar":1975,"fm":148.6,"herb":4,"lod":370,"ld":"2014-01","lv":28000},{"a":"Raftahlíð 15","pn":"550","sv":"Skagafjörður","teg":"Sérbýli","fnr":"2132009","full":1,"mat":62150,"matN":62050,"bruna":76250,"ar":1976,"fm":137,"herb":3,"lod":378,"ld":"2024-11","lv":62500},{"a":"Raftahlíð 16","pn":"550","sv":"Skagafjörður","teg":"Sérbýli","fnr":"2132010","full":1,"mat":67500,"matN":67700,"bruna":85850,"ar":1975,"fm":148.6,"herb":4,"lod":370,"ld":"2012-08","lv":22000},{"a":"Raftahlíð 19","pn":"550","sv":"Skagafjörður","teg":"Sérbýli","fnr":"2132013","full":1,"mat":62650,"matN":62600,"bruna":78200,"ar":1976,"fm":137,"herb":3,"lod":370,"ld":"2024-01","lv":63000},{"a":"Raftahlíð 2","pn":"550","sv":"Skagafjörður","teg":"Sérbýli","fnr":"2131995","full":1,"mat":64900,"matN":64750,"bruna":80800,"ar":1977,"fm":148.6,"herb":3,"lod":370,"ld":"2026-06","lv":70000},{"a":"Raftahlíð 20","pn":"550","sv":"Skagafjörður","teg":"Sérbýli","fnr":"2132014","full":1,"mat":63200,"matN":63000,"bruna":79000,"ar":1974,"fm":149.3,"herb":4,"lod":370,"ld":"2023-02","lv":63000},{"a":"Raftahlíð 22","pn":"550","sv":"Skagafjörður","teg":"Sérbýli","fnr":"2132016","full":1,"mat":63350,"matN":63150,"bruna":79950,"ar":1975,"fm":148.6,"herb":4,"lod":370,"ld":"2018-12","lv":30000},{"a":"Raftahlíð 23","pn":"550","sv":"Skagafjörður","teg":"Sérbýli","fnr":"2132017","full":1,"mat":64600,"matN":64450,"bruna":79400,"ar":1977,"fm":147.7,"herb":4,"lod":378,"ld":"2020-07","lv":32750},{"a":"Raftahlíð 27","pn":"550","sv":"Skagafjörður","teg":"Sérbýli","fnr":"2132021","full":1,"mat":66500,"matN":66500,"bruna":86200,"ar":1977,"fm":147.7,"herb":4,"lod":378,"ld":"2019-12","lv":35500},{"a":"Raftahlíð 3","pn":"550","sv":"Skagafjörður","teg":"Sérbýli","fnr":"2131996","full":1,"mat":54000,"matN":54000,"bruna":61100,"ar":1978,"fm":112.2,"herb":2,"lod":322,"ld":"2023-07","lv":38500},{"a":"Raftahlíð 30","pn":"550","sv":"Skagafjörður","teg":"Sérbýli","fnr":"2132024","full":1,"mat":63600,"matN":63450,"bruna":84550,"ar":1975,"fm":148.6,"herb":4,"lod":370,"ld":"2020-08","lv":37000},{"a":"Raftahlíð 31","pn":"550","sv":"Skagafjörður","teg":"Sérbýli","fnr":"2132025","full":1,"mat":66700,"matN":66750,"bruna":78700,"ar":1977,"fm":147.7,"herb":4,"lod":378,"ld":"2016-02","lv":27600},{"a":"Raftahlíð 34","pn":"550","sv":"Skagafjörður","teg":"Sérbýli","fnr":"2132028","full":1,"mat":66050,"matN":65900,"bruna":77300,"ar":1975,"fm":148.6,"herb":4,"lod":370,"ld":"2014-11","lv":26000},{"a":"Raftahlíð 36","pn":"550","sv":"Skagafjörður","teg":"Sérbýli","fnr":"2132030","full":1,"mat":65450,"matN":65400,"bruna":79300,"ar":1975,"fm":148.6,"herb":4,"lod":370,"ld":"2006-05","lv":17300},{"a":"Raftahlíð 37","pn":"550","sv":"Skagafjörður","teg":"Sérbýli","fnr":"2132031","full":1,"mat":66750,"matN":66750,"bruna":78250,"ar":1976,"fm":147.7,"herb":4,"lod":378,"ld":"2025-06","lv":62500},{"a":"Raftahlíð 4","pn":"550","sv":"Skagafjörður","teg":"Sérbýli","fnr":"2131997","full":1,"mat":64450,"matN":64300,"bruna":78800,"ar":1976,"fm":148.6,"herb":3,"lod":370,"ld":"2022-04","lv":54900},{"a":"Raftahlíð 46","pn":"550","sv":"Skagafjörður","teg":"Sérbýli","fnr":"2132040","full":1,"mat":80450,"matN":80200,"bruna":113750,"ar":1981,"fm":233.2,"herb":3,"lod":376,"ld":"2010-07","lv":25000},{"a":"Raftahlíð 47","pn":"550","sv":"Skagafjörður","teg":"Sérbýli","fnr":"2132041","full":1,"mat":64150,"matN":64150,"bruna":76450,"ar":1978,"fm":137.9,"herb":3,"lod":370,"ld":"2010-12","lv":18700},{"a":"Raftahlíð 48","pn":"550","sv":"Skagafjörður","teg":"Sérbýli","fnr":"2132042","full":1,"mat":75300,"matN":74850,"bruna":110400,"ar":1981,"fm":233.2,"herb":4,"lod":376,"ld":"2022-08","lv":80000},{"a":"Raftahlíð 49","pn":"550","sv":"Skagafjörður","teg":"Sérbýli","fnr":"2132044","full":1,"mat":62300,"matN":62250,"bruna":82000,"ar":1978,"fm":137.9,"herb":3,"lod":376,"ld":"2026-07","lv":70500},{"a":"Raftahlíð 51","pn":"550","sv":"Skagafjörður","teg":"Sérbýli","fnr":"2132046","full":1,"mat":63400,"matN":63400,"bruna":79450,"ar":1978,"fm":137.9,"herb":3,"lod":370,"ld":"2016-02","lv":26200},{"a":"Raftahlíð 52","pn":"550","sv":"Skagafjörður","teg":"Sérbýli","fnr":"2132047","full":1,"mat":67900,"matN":67950,"bruna":87500,"ar":1979,"fm":168.2,"herb":4,"lod":322,"ld":"2017-09","lv":32000},{"a":"Raftahlíð 54","pn":"550","sv":"Skagafjörður","teg":"Sérbýli","fnr":"2132049","full":1,"mat":66400,"matN":66300,"bruna":91550,"ar":1978,"fm":168.5,"herb":4,"lod":319,"ld":"2011-06","lv":24500},{"a":"Raftahlíð 58","pn":"550","sv":"Skagafjörður","teg":"Sérbýli","fnr":"2132053","full":1,"mat":65750,"matN":65700,"bruna":90450,"ar":1978,"fm":168.5,"herb":4,"lod":319,"ld":"2025-03","lv":65000},{"a":"Raftahlíð 59","pn":"550","sv":"Skagafjörður","teg":"Sérbýli","fnr":"2132054","full":1,"mat":61450,"matN":61250,"bruna":77450,"ar":1977,"fm":137.9,"herb":3,"lod":376,"ld":"2022-09","lv":70000},{"a":"Raftahlíð 60","pn":"550","sv":"Skagafjörður","teg":"Sérbýli","fnr":"2132055","full":1,"mat":66350,"matN":66400,"bruna":97750,"ar":1978,"fm":168,"herb":4,"lod":317,"ld":"2020-04","lv":36000},{"a":"Raftahlíð 65","pn":"550","sv":"Skagafjörður","teg":"Sérbýli","fnr":"2132063","full":1,"mat":67450,"matN":67300,"bruna":87970,"ar":1976,"fm":155.7,"herb":4,"lod":370,"ld":"2015-05","lv":28500},{"a":"Raftahlíð 68","pn":"550","sv":"Skagafjörður","teg":"Sérbýli","fnr":"2132066","full":1,"mat":53000,"matN":53000,"bruna":59250,"ar":1977,"fm":111.4,"herb":2,"lod":315,"ld":"2011-05","lv":16500},{"a":"Raftahlíð 69","pn":"550","sv":"Skagafjörður","teg":"Sérbýli","fnr":"2132067","full":1,"mat":53600,"matN":53550,"bruna":74150,"ar":1976,"fm":112.1,"herb":2,"lod":324,"ld":"2021-10","lv":42000},{"a":"Raftahlíð 70","pn":"550","sv":"Skagafjörður","teg":"Sérbýli","fnr":"2132068","full":1,"mat":52800,"matN":52700,"bruna":60100,"ar":1977,"fm":111.4,"herb":2,"lod":315,"ld":"2021-08","lv":37000},{"a":"Raftahlíð 71","pn":"550","sv":"Skagafjörður","teg":"Sérbýli","fnr":"2132069","full":1,"mat":52000,"matN":51850,"bruna":61050,"ar":1976,"fm":112.1,"herb":2,"lod":324,"ld":"2020-07","lv":27000},{"a":"Raftahlíð 74","pn":"550","sv":"Skagafjörður","teg":"Sérbýli","fnr":"2132072","full":1,"mat":64200,"matN":64050,"bruna":77300,"ar":1976,"fm":148.6,"herb":4,"lod":370,"ld":"2023-03","lv":63000},{"a":"Raftahlíð 75","pn":"550","sv":"Skagafjörður","teg":"Sérbýli","fnr":"2132073","full":1,"mat":54150,"matN":54100,"bruna":62500,"ar":1976,"fm":112.1,"herb":2,"lod":324,"ld":"2014-08","lv":17500},{"a":"Raftahlíð 77","pn":"550","sv":"Skagafjörður","teg":"Sérbýli","fnr":"2132075","full":1,"mat":54150,"matN":54100,"bruna":61950,"ar":1976,"fm":112.1,"herb":2,"lod":324,"ld":"2024-03","lv":52500},{"a":"Raftahlíð 78","pn":"550","sv":"Skagafjörður","teg":"Sérbýli","fnr":"2132076","full":1,"mat":64450,"matN":64300,"bruna":73450,"ar":1976,"fm":148.6,"herb":4,"lod":370,"ld":"2026-06","lv":70000},{"a":"Raftahlíð 79","pn":"550","sv":"Skagafjörður","teg":"Sérbýli","fnr":"2132077","full":1,"mat":54000,"matN":54150,"bruna":77100,"ar":1976,"fm":112.1,"herb":2,"lod":324,"ld":"2022-09","lv":50015},{"a":"Raftahlíð 7A","pn":"550","sv":"Skagafjörður","teg":"Sérbýli","fnr":"2132001","full":1,"mat":41100,"matN":41400,"bruna":42600,"ar":1977,"fm":70.2,"herb":1,"lod":204,"ld":"2012-09","lv":12450},{"a":"Raftahlíð 9","pn":"550","sv":"Skagafjörður","teg":"Einbýli","fnr":"2132003","full":1,"mat":62700,"matN":62650,"bruna":77750,"ar":1977,"fm":137,"herb":3,"lod":380,"ld":"2006-06","lv":18000},{"a":"Ránarstígur 2","pn":"550","sv":"Skagafjörður","teg":"Einbýli","fnr":"2132081","full":1,"mat":40750,"matN":40750,"bruna":44050,"ar":1946,"fm":90,"herb":3,"lod":462,"ld":"2026-05","lv":51000},{"a":"Ránarstígur 3","pn":"550","sv":"Skagafjörður","teg":"Sérbýli","fnr":"2519908","full":1,"mat":73750,"matN":73900,"bruna":77700,"ar":2023,"fm":123.7,"herb":2,"lod":1149,"ld":"2024-11","lv":82500},{"a":"Ránarstígur 4","pn":"550","sv":"Skagafjörður","teg":"Einbýli","fnr":"2132082","full":1,"mat":47400,"matN":47600,"bruna":54800,"ar":1946,"fm":112.8,"herb":3,"lod":446,"ld":"2023-09","lv":40000},{"a":"Ránarstígur 5","pn":"550","sv":"Skagafjörður","teg":"Sérbýli","fnr":"2532437","full":1,"mat":80150,"matN":80150,"bruna":90750,"ar":2023,"fm":140.3,"herb":3,"lod":1149,"ld":"2024-07","lv":90000},{"a":"Ránarstígur 6","pn":"550","sv":"Skagafjörður","teg":"Einbýli","fnr":"2132084","full":1,"mat":43350,"matN":43650,"bruna":41050,"ar":1946,"fm":90,"herb":3,"lod":462,"ld":"2014-08","lv":11985},{"a":"Ránarstígur 8","pn":"550","sv":"Skagafjörður","teg":"Einbýli","fnr":"2132085","full":1,"mat":43200,"matN":43600,"bruna":49000,"ar":1946,"fm":90,"herb":3,"lod":440,"ld":"2014-11","lv":19500},{"a":"Skagfirðingabraut 1","pn":"550","sv":"Skagafjörður","teg":"Fjölbýli","fnr":"2132088","full":1,"mat":36650,"matN":36800,"bruna":43100,"ar":1929,"fm":88.9,"herb":2,"lod":478,"ld":"2024-09","lv":35000},{"a":"Skagfirðingabraut 1","pn":"550","sv":"Skagafjörður","teg":"Fjölbýli","fnr":"2132087","full":1,"mat":28150,"matN":28300,"bruna":28300,"ar":1929,"fm":57.1,"herb":2,"lod":478,"ld":"2023-12","lv":29500},{"a":"Skagfirðingabraut 10","pn":"550","sv":"Skagafjörður","teg":"Einbýli","fnr":"2132108","full":1,"mat":56350,"matN":56050,"bruna":70400,"ar":1926,"fm":143,"herb":5,"lod":460,"ld":"2025-09","lv":54000},{"a":"Skagfirðingabraut 11","pn":"550","sv":"Skagafjörður","teg":"Fjölbýli","fnr":"2132111","full":1,"mat":48650,"matN":48350,"bruna":60250,"ar":1950,"fm":138.6,"herb":2,"lod":710,"ld":"2010-05","lv":14000},{"a":"Skagfirðingabraut 23","pn":"550","sv":"Skagafjörður","teg":"Fjölbýli","fnr":"2132121","full":1,"mat":43650,"matN":43350,"bruna":57600,"ar":1948,"fm":117.4,"herb":5,"lod":480,"ld":"2021-04","lv":30000},{"a":"Skagfirðingabraut 25","pn":"550","sv":"Skagafjörður","teg":"Fjölbýli","fnr":"2132124","full":1,"mat":45150,"matN":44850,"bruna":65350,"ar":1948,"fm":118.1,"herb":2,"lod":486,"ld":"2009-12","lv":10900},{"a":"Skagfirðingabraut 25","pn":"550","sv":"Skagafjörður","teg":"Fjölbýli","fnr":"2132125","full":1,"mat":59150,"matN":58800,"bruna":98540,"ar":1948,"fm":189.8,"herb":3,"lod":486,"ld":"2025-08","lv":56500},{"a":"Skagfirðingabraut 31","pn":"550","sv":"Skagafjörður","teg":"Einbýli","fnr":"2132131","full":1,"mat":72700,"matN":72900,"bruna":101850,"ar":1945,"fm":232.2,"herb":7,"lod":713,"ld":"2021-09","lv":50300},{"a":"Skagfirðingabraut 33","pn":"550","sv":"Skagafjörður","teg":"Fjölbýli","fnr":"2132134","full":1,"mat":49500,"matN":49150,"bruna":63800,"ar":1948,"fm":139.2,"herb":3,"lod":815,"ld":"2015-05","lv":19000},{"a":"Skagfirðingabraut 33","pn":"550","sv":"Skagafjörður","teg":"Fjölbýli","fnr":"2132133","full":1,"mat":48600,"matN":48150,"bruna":62050,"ar":1948,"fm":138.2,"herb":2,"lod":815,"ld":"2021-07","lv":22000},{"a":"Skagfirðingabraut 35","pn":"550","sv":"Skagafjörður","teg":"Fjölbýli","fnr":"2132137","full":1,"mat":29450,"matN":29800,"bruna":43550,"ar":1951,"fm":88.4,"herb":1,"lod":365,"ld":"2024-09","lv":32000},{"a":"Skagfirðingabraut 35","pn":"550","sv":"Skagafjörður","teg":"Fjölbýli","fnr":"2132138","full":1,"mat":44850,"matN":44500,"bruna":73350,"ar":1951,"fm":152.8,"herb":2,"lod":365,"ld":"2021-04","lv":36000},{"a":"Skagfirðingabraut 35","pn":"550","sv":"Skagafjörður","teg":"Fjölbýli","fnr":"2132139","full":1,"mat":44100,"matN":44300,"bruna":84000,"ar":1951,"fm":148.4,"herb":5,"lod":365,"ld":"2013-08","lv":18900},{"a":"Skagfirðingabraut 37","pn":"550","sv":"Skagafjörður","teg":"Fjölbýli","fnr":"2132142","full":1,"mat":63050,"matN":62150,"bruna":82200,"ar":1959,"fm":203.8,"herb":2,"lod":640,"ld":"2010-12","lv":21017},{"a":"Skagfirðingabraut 37","pn":"550","sv":"Skagafjörður","teg":"Fjölbýli","fnr":"2132141","full":1,"mat":43850,"matN":43650,"bruna":51550,"ar":1959,"fm":102.1,"herb":2,"lod":640,"ld":"2016-05","lv":21500},{"a":"Skagfirðingabraut 39","pn":"550","sv":"Skagafjörður","teg":"Fjölbýli","fnr":"2132145","full":1,"mat":56550,"matN":56200,"bruna":76740,"ar":1958,"fm":166.1,"herb":3,"lod":672,"ld":"2026-02","lv":59250},{"a":"Skagfirðingabraut 39","pn":"550","sv":"Skagafjörður","teg":"Fjölbýli","fnr":"2132144","full":1,"mat":47950,"matN":47500,"bruna":57900,"ar":1958,"fm":120.5,"herb":3,"lod":672,"ld":"2026-02","lv":55000},{"a":"Skagfirðingabraut 4","pn":"550","sv":"Skagafjörður","teg":"Einbýli","fnr":"2132092","full":1,"mat":72050,"matN":72100,"bruna":92400,"ar":1956,"fm":204.8,"herb":5,"lod":340,"ld":"2022-10","lv":40000},{"a":"Skagfirðingabraut 41","pn":"550","sv":"Skagafjörður","teg":"Fjölbýli","fnr":"2132147","full":1,"mat":45050,"matN":44600,"bruna":54200,"ar":1958,"fm":115.5,"herb":3,"lod":672,"ld":"2015-06","lv":17800},{"a":"Skagfirðingabraut 43","pn":"550","sv":"Skagafjörður","teg":"Fjölbýli","fnr":"2132150","full":1,"mat":57550,"matN":57150,"bruna":73530,"ar":1957,"fm":158.6,"herb":3,"lod":672,"ld":"2021-04","lv":43500},{"a":"Skagfirðingabraut 45","pn":"550","sv":"Skagafjörður","teg":"Fjölbýli","fnr":"2132154","full":1,"mat":55650,"matN":55350,"bruna":76050,"ar":1964,"fm":150.1,"herb":3,"lod":820,"ld":"2022-06","lv":45800},{"a":"Skagfirðingabraut 49","pn":"550","sv":"Skagafjörður","teg":"Fjölbýli","fnr":"2132158","full":1,"mat":58800,"matN":58400,"bruna":79340,"ar":1970,"fm":149.5,"herb":4,"lod":849,"ld":"2010-03","lv":16468},{"a":"Skagfirðingabraut 49","pn":"550","sv":"Skagafjörður","teg":"Fjölbýli","fnr":"2132157","full":1,"mat":42150,"matN":41900,"bruna":48100,"ar":1970,"fm":87.1,"herb":1,"lod":849,"ld":"2022-05","lv":28000},{"a":"Skagfirðingabraut 5","pn":"550","sv":"Skagafjörður","teg":"Fjölbýli","fnr":"2132093","full":1,"mat":26550,"matN":26650,"bruna":35000,"ar":1929,"fm":73.3,"herb":2,"lod":245,"ld":"2006-07","lv":2800},{"a":"Skagfirðingabraut 6","pn":"550","sv":"Skagafjörður","teg":"Fjölbýli","fnr":"2132097","full":1,"mat":37050,"matN":37100,"bruna":51500,"ar":1948,"fm":118.4,"herb":2,"lod":646,"ld":"2019-10","lv":25500},{"a":"Skagfirðingabraut 7","pn":"550","sv":"Skagafjörður","teg":"Einbýli","fnr":"2132101","full":1,"mat":67900,"matN":67500,"bruna":82500,"ar":1930,"fm":162.3,"herb":4,"lod":433,"ld":"2020-06","lv":37500},{"a":"Skagfirðingabraut 8","pn":"550","sv":"Skagafjörður","teg":"Einbýli","fnr":"2132102","full":1,"mat":73800,"matN":73400,"bruna":103500,"ar":1930,"fm":244.5,"herb":6,"lod":495,"ld":"2022-05","lv":66000},{"a":"Skagfirðingabraut 9","pn":"550","sv":"Skagafjörður","teg":"Einbýli","fnr":"2132104","full":1,"mat":51300,"matN":51200,"bruna":65450,"ar":1928,"fm":136.9,"herb":5,"lod":461,"ld":"2024-08","lv":42500},{"a":"Skógargata 13","pn":"550","sv":"Skagafjörður","teg":"Einbýli","fnr":"2132189","full":1,"mat":61500,"matN":61750,"bruna":80300,"ar":1904,"fm":141.9,"herb":3,"lod":377,"ld":"2007-06","lv":13000},{"a":"Skógargata 17B","pn":"550","sv":"Skagafjörður","teg":"Einbýli","fnr":"2132194","full":1,"mat":46150,"matN":46300,"bruna":56500,"ar":1915,"fm":87.6,"herb":4,"lod":336,"ld":"2009-12","lv":4468},{"a":"Skógargata 2","pn":"550","sv":"Skagafjörður","teg":"Fjölbýli","fnr":"2132173","full":1,"mat":44000,"matN":44150,"bruna":61900,"ar":1990,"fm":106.8,"herb":3,"lod":677,"ld":"2026-03","lv":38750},{"a":"Skógargata 24","pn":"550","sv":"Skagafjörður","teg":"Einbýli","fnr":"2132206","full":1,"mat":43350,"matN":43800,"bruna":46730,"ar":1915,"fm":105.7,"herb":3,"lod":755,"ld":"2026-06","lv":32000},{"a":"Skógargata 3B","pn":"550","sv":"Skagafjörður","teg":"Sérbýli","fnr":"2132176","full":1,"mat":42700,"matN":42700,"bruna":58600,"ar":1907,"fm":151,"herb":5,"lod":188,"ld":"2016-04","lv":13500},{"a":"Skógargata 5","pn":"550","sv":"Skagafjörður","teg":"Einbýli","fnr":"2132177","full":1,"mat":32950,"matN":33250,"bruna":35700,"ar":1898,"fm":94.4,"herb":3,"lod":268,"ld":"2022-10","lv":28000},{"a":"Skógargata 6","pn":"550","sv":"Skagafjörður","teg":"Fjölbýli","fnr":"2132179","full":1,"mat":32300,"matN":32250,"bruna":36350,"ar":1947,"fm":73.4,"herb":3,"lod":324,"ld":"2019-03","lv":1500},{"a":"Skógargata 6","pn":"550","sv":"Skagafjörður","teg":"Fjölbýli","fnr":"2132180","full":1,"mat":38550,"matN":38450,"bruna":49050,"ar":1947,"fm":101.9,"herb":3,"lod":324,"ld":"2025-08","lv":22000},{"a":"Skógargata 6B","pn":"550","sv":"Skagafjörður","teg":"Einbýli","fnr":"2132181","full":1,"mat":34350,"matN":34900,"bruna":40950,"ar":1942,"fm":70.1,"herb":2,"lod":338,"ld":"2025-06","lv":34000},{"a":"Skógargata 8","pn":"550","sv":"Skagafjörður","teg":"Einbýli","fnr":"2132183","full":1,"mat":49900,"matN":49950,"bruna":65560,"ar":1927,"fm":154.7,"herb":4,"lod":596,"ld":"2015-10","lv":14000},{"a":"Skólastígur 1","pn":"550","sv":"Skagafjörður","teg":"Fjölbýli","fnr":"2132212","full":1,"mat":41450,"matN":41100,"bruna":49100,"ar":1959,"fm":103.2,"herb":2,"lod":422,"ld":"2018-12","lv":19500},{"a":"Skólastígur 1","pn":"550","sv":"Skagafjörður","teg":"Fjölbýli","fnr":"2132213","full":1,"mat":50550,"matN":50100,"bruna":66950,"ar":1959,"fm":147.9,"herb":4,"lod":422,"ld":"2025-09","lv":57000},{"a":"Smáragrund 11","pn":"550","sv":"Skagafjörður","teg":"Einbýli","fnr":"2132235","full":1,"mat":69500,"matN":69350,"bruna":81850,"ar":1969,"fm":159.8,"herb":3,"lod":632,"ld":"2021-04","lv":45000},{"a":"Smáragrund 12","pn":"550","sv":"Skagafjörður","teg":"Einbýli","fnr":"2132237","full":1,"mat":69350,"matN":69350,"bruna":75300,"ar":1966,"fm":163.8,"herb":4,"lod":659,"ld":"2022-03","lv":59000},{"a":"Smáragrund 13","pn":"550","sv":"Skagafjörður","teg":"Einbýli","fnr":"2132239","full":1,"mat":71950,"matN":72000,"bruna":86750,"ar":1966,"fm":163.5,"herb":4,"lod":633,"ld":"2006-05","lv":13500},{"a":"Smáragrund 16","pn":"550","sv":"Skagafjörður","teg":"Einbýli","fnr":"2132245","full":1,"mat":74200,"matN":74100,"bruna":89450,"ar":1966,"fm":178.5,"herb":5,"lod":666,"ld":"2007-05","lv":18000},{"a":"Smáragrund 19","pn":"550","sv":"Skagafjörður","teg":"Einbýli","fnr":"2132251","full":1,"mat":68000,"matN":68100,"bruna":81500,"ar":1965,"fm":151,"herb":3,"lod":600,"ld":"2025-03","lv":60500},{"a":"Smáragrund 20","pn":"550","sv":"Skagafjörður","teg":"Einbýli","fnr":"2132253","full":1,"mat":75250,"matN":75450,"bruna":88400,"ar":1966,"fm":170.7,"herb":4,"lod":660,"ld":"2024-08","lv":57500},{"a":"Smáragrund 21","pn":"550","sv":"Skagafjörður","teg":"Einbýli","fnr":"2132255","full":1,"mat":69100,"matN":69200,"bruna":78950,"ar":1968,"fm":159.4,"herb":3,"lod":630,"ld":"2013-03","lv":23000},{"a":"Smáragrund 5","pn":"550","sv":"Skagafjörður","teg":"Fjölbýli","fnr":"2132223","full":1,"mat":47200,"matN":47000,"bruna":68200,"ar":1959,"fm":137.5,"herb":4,"lod":674,"ld":"2012-08","lv":16200},{"a":"Smáragrund 5","pn":"550","sv":"Skagafjörður","teg":"Fjölbýli","fnr":"2132222","full":1,"mat":55450,"matN":54850,"bruna":69450,"ar":1959,"fm":158.1,"herb":4,"lod":674,"ld":"2020-02","lv":36000},{"a":"Smáragrund 6A","pn":"550","sv":"Skagafjörður","teg":"Fjölbýli","fnr":"2132225","full":1,"mat":44450,"matN":44150,"bruna":55200,"ar":1959,"fm":106.3,"herb":3,"lod":660,"ld":"2021-04","lv":32300},{"a":"Smáragrund 7","pn":"550","sv":"Skagafjörður","teg":"Einbýli","fnr":"2132227","full":1,"mat":73350,"matN":73300,"bruna":90150,"ar":1963,"fm":194.1,"herb":4,"lod":672,"ld":"2015-09","lv":32500},{"a":"Smáragrund 8","pn":"550","sv":"Skagafjörður","teg":"Einbýli","fnr":"2132229","full":1,"mat":73350,"matN":73300,"bruna":88750,"ar":1962,"fm":203.4,"herb":4,"lod":675,"ld":"2012-09","lv":24000},{"a":"Smáragrund 9","pn":"550","sv":"Skagafjörður","teg":"Einbýli","fnr":"2132231","full":1,"mat":71950,"matN":71900,"bruna":80400,"ar":1968,"fm":165.4,"herb":3,"lod":632,"ld":"2009-06","lv":20500},{"a":"Suðurgata 11B","pn":"550","sv":"Skagafjörður","teg":"Einbýli","fnr":"2132274","full":1,"mat":61000,"matN":60950,"bruna":69050,"ar":1929,"fm":118.2,"herb":4,"lod":247,"ld":"2024-12","lv":60000},{"a":"Suðurgata 12","pn":"550","sv":"Skagafjörður","teg":"Einbýli","fnr":"2273311","full":1,"mat":77200,"matN":77300,"bruna":71250,"ar":2004,"fm":147.1,"herb":3,"lod":699,"ld":"2026-02","lv":74900},{"a":"Suðurgata 13","pn":"550","sv":"Skagafjörður","teg":"Einbýli","fnr":"2132276","full":1,"mat":64500,"matN":64300,"bruna":88100,"ar":1933,"fm":197.6,"herb":4,"lod":420,"ld":"2013-12","lv":22000},{"a":"Suðurgata 18B","pn":"550","sv":"Skagafjörður","teg":"Einbýli","fnr":"2132285","full":1,"mat":45450,"matN":45550,"bruna":54100,"ar":1901,"fm":112.7,"herb":4,"lod":553,"ld":"2016-02","lv":14000},{"a":"Suðurgata 2","pn":"550","sv":"Skagafjörður","teg":"Einbýli","fnr":"2132260","full":1,"mat":65950,"matN":66050,"bruna":87250,"ar":1908,"fm":191.7,"herb":6,"lod":375,"ld":"2015-06","lv":19319},{"a":"Suðurgata 22","pn":"550","sv":"Skagafjörður","teg":"Einbýli","fnr":"2132289","full":1,"mat":26750,"matN":26950,"bruna":26100,"ar":1920,"fm":66.2,"herb":2,"lod":928,"ld":"2022-05","lv":19500},{"a":"Suðurgata 6","pn":"550","sv":"Skagafjörður","teg":"Einbýli","fnr":"2132265","full":1,"mat":43750,"matN":43900,"bruna":76700,"ar":1914,"fm":202.3,"herb":4,"lod":441,"ld":"2007-03","lv":15500},{"a":"Suðurgata 7","pn":"550","sv":"Skagafjörður","teg":"Einbýli","fnr":"2132266","full":1,"mat":68250,"matN":68500,"bruna":96900,"ar":1936,"fm":201.4,"herb":5,"lod":450,"ld":"2021-02","lv":40500},{"a":"Sæmundargata 11","pn":"550","sv":"Skagafjörður","teg":"Fjölbýli","fnr":"2132330","full":1,"mat":37250,"matN":37150,"bruna":42300,"ar":1962,"fm":79.7,"herb":2,"lod":508,"ld":"2019-10","lv":19500},{"a":"Sæmundargata 11","pn":"550","sv":"Skagafjörður","teg":"Fjölbýli","fnr":"2132331","full":1,"mat":38850,"matN":39050,"bruna":43840,"ar":1962,"fm":88.2,"herb":4,"lod":508,"ld":"2019-06","lv":25700},{"a":"Sæmundargata 13","pn":"550","sv":"Skagafjörður","teg":"Einbýli","fnr":"2132333","full":1,"mat":45100,"matN":45550,"bruna":65850,"ar":1892,"fm":169.9,"herb":4,"lod":451,"ld":"2024-07","lv":41267},{"a":"Sæmundargata 15","pn":"550","sv":"Skagafjörður","teg":"Einbýli","fnr":"2132334","full":1,"mat":81550,"matN":81350,"bruna":106000,"ar":1981,"fm":177.3,"herb":6,"lod":618,"ld":"2019-06","lv":41500},{"a":"Sæmundargata 2A","pn":"550","sv":"Skagafjörður","teg":"Fjölbýli","fnr":"2519492","full":1,"mat":42900,"matN":42900,"bruna":56150,"ar":1946,"fm":81.2,"herb":2,"lod":3394,"ld":"2022-06","lv":46000},{"a":"Sæmundargata 2A","pn":"550","sv":"Skagafjörður","teg":"Fjölbýli","fnr":"2131566","full":1,"mat":38400,"matN":38350,"bruna":49100,"ar":1946,"fm":67.3,"herb":1,"lod":3394,"ld":"2024-10","lv":42000},{"a":"Sæmundargata 2A","pn":"550","sv":"Skagafjörður","teg":"Fjölbýli","fnr":"2519499","full":1,"mat":43450,"matN":43350,"bruna":57800,"ar":1946,"fm":80.9,"herb":2,"lod":3394,"ld":"2025-07","lv":53900},{"a":"Sæmundargata 2A","pn":"550","sv":"Skagafjörður","teg":"Fjölbýli","fnr":"2519498","full":1,"mat":41200,"matN":41100,"bruna":55900,"ar":1946,"fm":74,"herb":2,"lod":3394,"ld":"2024-10","lv":48000},{"a":"Sæmundargata 2A","pn":"550","sv":"Skagafjörður","teg":"Fjölbýli","fnr":"2519491","full":1,"mat":41450,"matN":41500,"bruna":55050,"ar":1946,"fm":78,"herb":2,"lod":3394,"ld":"2022-07","lv":44600},{"a":"Sæmundargata 2A","pn":"550","sv":"Skagafjörður","teg":"Fjölbýli","fnr":"2519496","full":1,"mat":53650,"matN":53450,"bruna":74600,"ar":1946,"fm":108.6,"herb":3,"lod":3394,"ld":"2022-07","lv":56000},{"a":"Sæmundargata 2A","pn":"550","sv":"Skagafjörður","teg":"Fjölbýli","fnr":"2519497","full":1,"mat":39350,"matN":39250,"bruna":51800,"ar":1946,"fm":68.8,"herb":1,"lod":3394,"ld":"2022-07","lv":39000},{"a":"Sæmundargata 2A","pn":"550","sv":"Skagafjörður","teg":"Fjölbýli","fnr":"2519501","full":1,"mat":30750,"matN":30750,"bruna":37200,"ar":1946,"fm":48,"herb":1,"lod":3394,"ld":"2023-05","lv":32000},{"a":"Sæmundargata 2A","pn":"550","sv":"Skagafjörður","teg":"Fjölbýli","fnr":"2519494","full":1,"mat":30350,"matN":30400,"bruna":34850,"ar":1946,"fm":48,"herb":1,"lod":3394,"ld":"2023-05","lv":30900},{"a":"Sæmundargata 2A","pn":"550","sv":"Skagafjörður","teg":"Fjölbýli","fnr":"2519502","full":1,"mat":45850,"matN":45750,"bruna":59750,"ar":1946,"fm":87.2,"herb":2,"lod":3394,"ld":"2023-05","lv":49900},{"a":"Sæmundargata 2A","pn":"550","sv":"Skagafjörður","teg":"Fjölbýli","fnr":"2519500","full":1,"mat":45250,"matN":45150,"bruna":58950,"ar":1946,"fm":85.5,"herb":2,"lod":3394,"ld":"2025-06","lv":54000},{"a":"Sæmundargata 2A","pn":"550","sv":"Skagafjörður","teg":"Fjölbýli","fnr":"2519495","full":1,"mat":45200,"matN":45150,"bruna":57100,"ar":1946,"fm":87,"herb":2,"lod":3394,"ld":"2024-05","lv":49000},{"a":"Sæmundargata 2A","pn":"550","sv":"Skagafjörður","teg":"Fjölbýli","fnr":"2519493","full":1,"mat":45050,"matN":45000,"bruna":57100,"ar":1946,"fm":87.2,"herb":2,"lod":3394,"ld":"2023-09","lv":47000},{"a":"Sæmundargata 3","pn":"550","sv":"Skagafjörður","teg":"Fjölbýli","fnr":"2132306","full":1,"mat":41400,"matN":41400,"bruna":56200,"ar":1959,"fm":123.3,"herb":2,"lod":330,"ld":"2013-04","lv":11500},{"a":"Sæmundargata 5","pn":"550","sv":"Skagafjörður","teg":"Fjölbýli","fnr":"2132315","full":1,"mat":18750,"matN":19050,"bruna":23850,"ar":1954,"fm":42.2,"herb":null,"lod":760,"ld":"2026-01","lv":22000},{"a":"Sæmundargata 5","pn":"550","sv":"Skagafjörður","teg":"Fjölbýli","fnr":"2132314","full":1,"mat":22650,"matN":22850,"bruna":30000,"ar":1954,"fm":54.7,"herb":1,"lod":760,"ld":"2021-09","lv":13000},{"a":"Sæmundargata 5","pn":"550","sv":"Skagafjörður","teg":"Fjölbýli","fnr":"2132310","full":1,"mat":22850,"matN":23050,"bruna":28900,"ar":1954,"fm":54.7,"herb":1,"lod":760,"ld":"2022-03","lv":22000},{"a":"Sæmundargata 5","pn":"550","sv":"Skagafjörður","teg":"Fjölbýli","fnr":"2132311","full":1,"mat":19200,"matN":19400,"bruna":24100,"ar":1954,"fm":42.2,"herb":null,"lod":760,"ld":"2017-11","lv":10500},{"a":"Sæmundargata 9","pn":"550","sv":"Skagafjörður","teg":"Fjölbýli","fnr":"2132326","full":1,"mat":46150,"matN":46200,"bruna":52130,"ar":1925,"fm":127.2,"herb":5,"lod":486,"ld":"2010-10","lv":13000},{"a":"Sævarstígur 2","pn":"550","sv":"Skagafjörður","teg":"Fjölbýli","fnr":"2132341","full":1,"mat":29000,"matN":29200,"bruna":38700,"ar":1931,"fm":78.2,"herb":2,"lod":115,"ld":"2023-07","lv":21500},{"a":"Víðigrund 1","pn":"550","sv":"Skagafjörður","teg":"Einbýli","fnr":"2132345","full":1,"mat":73750,"matN":73500,"bruna":99700,"ar":1961,"fm":207.8,"herb":5,"lod":660,"ld":"2013-04","lv":27550},{"a":"Víðigrund 11","pn":"550","sv":"Skagafjörður","teg":"Einbýli","fnr":"2132382","full":1,"mat":78000,"matN":78000,"bruna":101900,"ar":1965,"fm":213,"herb":4,"lod":660,"ld":"2006-10","lv":20000},{"a":"Víðigrund 13","pn":"550","sv":"Skagafjörður","teg":"Einbýli","fnr":"2132383","full":1,"mat":77950,"matN":77750,"bruna":101800,"ar":1965,"fm":216.7,"herb":6,"lod":960,"ld":"2024-01","lv":78000},{"a":"Víðigrund 14","pn":"550","sv":"Skagafjörður","teg":"Fjölbýli","fnr":"2132390","full":1,"mat":28900,"matN":28950,"bruna":36850,"ar":1975,"fm":65.9,"herb":1,"lod":2270,"ld":"2023-06","lv":23500},{"a":"Víðigrund 14","pn":"550","sv":"Skagafjörður","teg":"Fjölbýli","fnr":"2132388","full":1,"mat":35350,"matN":35300,"bruna":45200,"ar":1975,"fm":86.7,"herb":2,"lod":2270,"ld":"2013-11","lv":13420},{"a":"Víðigrund 14","pn":"550","sv":"Skagafjörður","teg":"Fjölbýli","fnr":"2132384","full":1,"mat":28400,"matN":28400,"bruna":32300,"ar":1975,"fm":62.1,"herb":1,"lod":2270,"ld":"2007-05","lv":8500},{"a":"Víðigrund 14","pn":"550","sv":"Skagafjörður","teg":"Fjölbýli","fnr":"2132387","full":1,"mat":29350,"matN":29400,"bruna":36250,"ar":1975,"fm":66.6,"herb":1,"lod":2270,"ld":"2017-01","lv":11000},{"a":"Víðigrund 14","pn":"550","sv":"Skagafjörður","teg":"Fjölbýli","fnr":"2132385","full":1,"mat":28600,"matN":28600,"bruna":32450,"ar":1975,"fm":62.7,"herb":1,"lod":2270,"ld":"2024-12","lv":27000},{"a":"Víðigrund 14","pn":"550","sv":"Skagafjörður","teg":"Fjölbýli","fnr":"2132391","full":1,"mat":35050,"matN":35050,"bruna":44800,"ar":1975,"fm":87.5,"herb":2,"lod":2270,"ld":"2023-09","lv":30000},{"a":"Víðigrund 16","pn":"550","sv":"Skagafjörður","teg":"Fjölbýli","fnr":"2132395","full":1,"mat":42400,"matN":42350,"bruna":61200,"ar":1975,"fm":113.8,"herb":3,"lod":2270,"ld":"2006-09","lv":11000},{"a":"Víðigrund 16","pn":"550","sv":"Skagafjörður","teg":"Fjölbýli","fnr":"2132392","full":1,"mat":28350,"matN":28400,"bruna":33200,"ar":1975,"fm":62.5,"herb":1,"lod":2270,"ld":"2007-11","lv":7560},{"a":"Víðigrund 16","pn":"550","sv":"Skagafjörður","teg":"Fjölbýli","fnr":"2132396","full":1,"mat":42200,"matN":42200,"bruna":61400,"ar":1975,"fm":115.1,"herb":3,"lod":2270,"ld":"2020-01","lv":20000},{"a":"Víðigrund 16","pn":"550","sv":"Skagafjörður","teg":"Fjölbýli","fnr":"2132393","full":1,"mat":28100,"matN":28150,"bruna":33050,"ar":1975,"fm":61.6,"herb":1,"lod":2270,"ld":"2020-12","lv":14000},{"a":"Víðigrund 16","pn":"550","sv":"Skagafjörður","teg":"Fjölbýli","fnr":"2132394","full":1,"mat":42850,"matN":42800,"bruna":61650,"ar":1975,"fm":115.9,"herb":3,"lod":2270,"ld":"2023-03","lv":37000},{"a":"Víðigrund 16","pn":"550","sv":"Skagafjörður","teg":"Fjölbýli","fnr":"2132397","full":1,"mat":42000,"matN":42000,"bruna":61450,"ar":1975,"fm":114.6,"herb":3,"lod":2270,"ld":"2026-01","lv":38900},{"a":"Víðigrund 2","pn":"550","sv":"Skagafjörður","teg":"Fjölbýli","fnr":"2132354","full":1,"mat":32500,"matN":32550,"bruna":41300,"ar":1971,"fm":81.8,"herb":2,"lod":2175,"ld":"2019-07","lv":18800},{"a":"Víðigrund 2","pn":"550","sv":"Skagafjörður","teg":"Fjölbýli","fnr":"2132352","full":1,"mat":32950,"matN":32950,"bruna":41400,"ar":1971,"fm":82,"herb":2,"lod":2175,"ld":"2017-04","lv":15000},{"a":"Víðigrund 2","pn":"550","sv":"Skagafjörður","teg":"Fjölbýli","fnr":"2132347","full":1,"mat":28700,"matN":28750,"bruna":31450,"ar":1971,"fm":66,"herb":2,"lod":2175,"ld":"2011-02","lv":7300},{"a":"Víðigrund 2","pn":"550","sv":"Skagafjörður","teg":"Fjölbýli","fnr":"2132350","full":1,"mat":33300,"matN":33250,"bruna":41250,"ar":1971,"fm":81.7,"herb":2,"lod":2175,"ld":"2017-09","lv":16200},{"a":"Víðigrund 2","pn":"550","sv":"Skagafjörður","teg":"Fjölbýli","fnr":"2132351","full":1,"mat":39100,"matN":39100,"bruna":49200,"ar":1971,"fm":98.9,"herb":3,"lod":2175,"ld":"2024-02","lv":38000},{"a":"Víðigrund 2","pn":"550","sv":"Skagafjörður","teg":"Fjölbýli","fnr":"2132353","full":1,"mat":37050,"matN":37100,"bruna":49300,"ar":1971,"fm":99,"herb":3,"lod":2175,"ld":"2023-01","lv":38500},{"a":"Víðigrund 22","pn":"550","sv":"Skagafjörður","teg":"Fjölbýli","fnr":"2132402","full":1,"mat":35800,"matN":35800,"bruna":46300,"ar":1978,"fm":87.2,"herb":2,"lod":1981,"ld":"2020-06","lv":20500},{"a":"Víðigrund 22","pn":"550","sv":"Skagafjörður","teg":"Fjölbýli","fnr":"2132405","full":1,"mat":35350,"matN":35400,"bruna":46300,"ar":1978,"fm":87.2,"herb":2,"lod":1981,"ld":"2022-07","lv":28900},{"a":"Víðigrund 22","pn":"550","sv":"Skagafjörður","teg":"Fjölbýli","fnr":"2132401","full":1,"mat":29650,"matN":29750,"bruna":37600,"ar":1978,"fm":66.5,"herb":1,"lod":1981,"ld":"2026-05","lv":31750},{"a":"Víðigrund 22","pn":"550","sv":"Skagafjörður","teg":"Fjölbýli","fnr":"2132403","full":1,"mat":34800,"matN":34850,"bruna":45950,"ar":1978,"fm":85.2,"herb":2,"lod":1981,"ld":"2023-06","lv":27500},{"a":"Víðigrund 22","pn":"550","sv":"Skagafjörður","teg":"Fjölbýli","fnr":"2132400","full":1,"mat":35300,"matN":35300,"bruna":46000,"ar":1978,"fm":85.5,"herb":2,"lod":1981,"ld":"2018-11","lv":19300},{"a":"Víðigrund 24","pn":"550","sv":"Skagafjörður","teg":"Fjölbýli","fnr":"2132411","full":1,"mat":42600,"matN":42650,"bruna":62900,"ar":1978,"fm":114.6,"herb":4,"lod":1981,"ld":"2024-01","lv":38000},{"a":"Víðigrund 24","pn":"550","sv":"Skagafjörður","teg":"Fjölbýli","fnr":"2132408","full":1,"mat":42750,"matN":42750,"bruna":62700,"ar":1978,"fm":113.2,"herb":4,"lod":1981,"ld":"2024-03","lv":38000},{"a":"Víðigrund 24","pn":"550","sv":"Skagafjörður","teg":"Fjölbýli","fnr":"2132409","full":1,"mat":43250,"matN":43250,"bruna":63200,"ar":1978,"fm":115.4,"herb":4,"lod":1981,"ld":"2025-06","lv":38000},{"a":"Víðigrund 24","pn":"550","sv":"Skagafjörður","teg":"Fjölbýli","fnr":"2132410","full":1,"mat":42400,"matN":42450,"bruna":62950,"ar":1978,"fm":114.1,"herb":4,"lod":1981,"ld":"2016-02","lv":13000},{"a":"Víðigrund 26","pn":"550","sv":"Skagafjörður","teg":"Fjölbýli","fnr":"2132412","full":1,"mat":29050,"matN":29100,"bruna":36250,"ar":1979,"fm":63.6,"herb":1,"lod":3462,"ld":"2023-01","lv":24000},{"a":"Víðigrund 26","pn":"550","sv":"Skagafjörður","teg":"Fjölbýli","fnr":"2132416","full":1,"mat":43100,"matN":43050,"bruna":62200,"ar":1979,"fm":114.6,"herb":3,"lod":3462,"ld":"2021-04","lv":28000},{"a":"Víðigrund 26","pn":"550","sv":"Skagafjörður","teg":"Fjölbýli","fnr":"2132414","full":1,"mat":43700,"matN":43650,"bruna":62600,"ar":1979,"fm":115.4,"herb":3,"lod":3462,"ld":"2022-09","lv":36250},{"a":"Víðigrund 26","pn":"550","sv":"Skagafjörður","teg":"Fjölbýli","fnr":"2132417","full":1,"mat":42850,"matN":42850,"bruna":61950,"ar":1979,"fm":114.1,"herb":3,"lod":3462,"ld":"2024-09","lv":37700},{"a":"Víðigrund 28","pn":"550","sv":"Skagafjörður","teg":"Fjölbýli","fnr":"2132421","full":1,"mat":29950,"matN":30050,"bruna":36000,"ar":1980,"fm":66.5,"herb":1,"lod":3462,"ld":"2025-03","lv":25000},{"a":"Víðigrund 28","pn":"550","sv":"Skagafjörður","teg":"Fjölbýli","fnr":"2132424","full":1,"mat":29800,"matN":29900,"bruna":36450,"ar":1980,"fm":67.5,"herb":1,"lod":3462,"ld":"2006-09","lv":7800},{"a":"Víðigrund 28","pn":"550","sv":"Skagafjörður","teg":"Fjölbýli","fnr":"2132419","full":1,"mat":29250,"matN":29250,"bruna":34250,"ar":1980,"fm":62.8,"herb":1,"lod":3462,"ld":"2024-09","lv":24600},{"a":"Víðigrund 28","pn":"550","sv":"Skagafjörður","teg":"Fjölbýli","fnr":"2132423","full":1,"mat":35150,"matN":35200,"bruna":45950,"ar":1980,"fm":85.2,"herb":2,"lod":3462,"ld":"2009-09","lv":10500},{"a":"Víðigrund 28","pn":"550","sv":"Skagafjörður","teg":"Fjölbýli","fnr":"2132425","full":1,"mat":35700,"matN":35750,"bruna":46900,"ar":1980,"fm":87.2,"herb":2,"lod":3462,"ld":"2019-12","lv":18000},{"a":"Víðigrund 28","pn":"550","sv":"Skagafjörður","teg":"Fjölbýli","fnr":"2132420","full":1,"mat":35650,"matN":35650,"bruna":46100,"ar":1980,"fm":85.5,"herb":2,"lod":3462,"ld":"2013-11","lv":11000},{"a":"Víðigrund 28","pn":"550","sv":"Skagafjörður","teg":"Fjölbýli","fnr":"2132418","full":1,"mat":29000,"matN":29050,"bruna":33950,"ar":1980,"fm":62.2,"herb":1,"lod":3462,"ld":"2025-05","lv":26500},{"a":"Víðigrund 4","pn":"550","sv":"Skagafjörður","teg":"Fjölbýli","fnr":"2132359","full":1,"mat":32950,"matN":32950,"bruna":42700,"ar":1971,"fm":81.7,"herb":2,"lod":2175,"ld":"2006-08","lv":8200},{"a":"Víðigrund 4","pn":"550","sv":"Skagafjörður","teg":"Fjölbýli","fnr":"2132356","full":1,"mat":28700,"matN":28750,"bruna":31600,"ar":1971,"fm":66,"herb":2,"lod":2175,"ld":"2006-12","lv":7500},{"a":"Víðigrund 4","pn":"550","sv":"Skagafjörður","teg":"Fjölbýli","fnr":"2132360","full":1,"mat":37550,"matN":37500,"bruna":48950,"ar":1971,"fm":99.2,"herb":3,"lod":2175,"ld":"2021-09","lv":25000},{"a":"Víðigrund 4","pn":"550","sv":"Skagafjörður","teg":"Fjölbýli","fnr":"2132362","full":1,"mat":37100,"matN":37150,"bruna":50150,"ar":1971,"fm":99,"herb":3,"lod":2175,"ld":"2019-03","lv":21000},{"a":"Víðigrund 6","pn":"550","sv":"Skagafjörður","teg":"Fjölbýli","fnr":"2132372","full":1,"mat":39200,"matN":39100,"bruna":57950,"ar":1972,"fm":103,"herb":3,"lod":2310,"ld":"2022-07","lv":23000},{"a":"Víðigrund 6","pn":"550","sv":"Skagafjörður","teg":"Fjölbýli","fnr":"2132368","full":1,"mat":26750,"matN":26750,"bruna":31350,"ar":1972,"fm":56.7,"herb":1,"lod":2310,"ld":"2024-05","lv":21500},{"a":"Víðigrund 6","pn":"550","sv":"Skagafjörður","teg":"Fjölbýli","fnr":"2132371","full":1,"mat":34600,"matN":34550,"bruna":50950,"ar":1972,"fm":85.5,"herb":2,"lod":2310,"ld":"2022-10","lv":27300},{"a":"Víðigrund 6","pn":"550","sv":"Skagafjörður","teg":"Fjölbýli","fnr":"2132369","full":1,"mat":35050,"matN":34950,"bruna":48400,"ar":1972,"fm":85.5,"herb":2,"lod":2310,"ld":"2021-10","lv":16000},{"a":"Víðigrund 6","pn":"550","sv":"Skagafjörður","teg":"Fjölbýli","fnr":"2132367","full":1,"mat":26600,"matN":26550,"bruna":31450,"ar":1972,"fm":55.9,"herb":1,"lod":2310,"ld":"2024-10","lv":26000},{"a":"Víðigrund 7","pn":"550","sv":"Skagafjörður","teg":"Einbýli","fnr":"2132379","full":1,"mat":72550,"matN":72550,"bruna":90100,"ar":1967,"fm":189.2,"herb":5,"lod":660,"ld":"2017-03","lv":33000},{"a":"Víðigrund 8","pn":"550","sv":"Skagafjörður","teg":"Fjölbýli","fnr":"2132375","full":1,"mat":39500,"matN":39450,"bruna":56200,"ar":1972,"fm":103,"herb":3,"lod":2310,"ld":"2010-11","lv":13400},{"a":"Víðigrund 8","pn":"550","sv":"Skagafjörður","teg":"Fjölbýli","fnr":"2132377","full":1,"mat":39200,"matN":39100,"bruna":57050,"ar":1972,"fm":103,"herb":3,"lod":2310,"ld":"2023-06","lv":34000},{"a":"Víðigrund 8","pn":"550","sv":"Skagafjörður","teg":"Fjölbýli","fnr":"2132378","full":1,"mat":34600,"matN":34550,"bruna":47650,"ar":1972,"fm":85.5,"herb":2,"lod":2310,"ld":"2015-09","lv":11600},{"a":"Víðigrund 8","pn":"550","sv":"Skagafjörður","teg":"Fjölbýli","fnr":"2132376","full":1,"mat":34900,"matN":34850,"bruna":46900,"ar":1972,"fm":85.5,"herb":2,"lod":2310,"ld":"2026-03","lv":35000},{"a":"Víðigrund 9","pn":"550","sv":"Skagafjörður","teg":"Einbýli","fnr":"2132381","full":1,"mat":72500,"matN":72550,"bruna":93450,"ar":1965,"fm":189.2,"herb":4,"lod":660,"ld":"2018-07","lv":41000},{"a":"Víðihlíð 1","pn":"550","sv":"Skagafjörður","teg":"Einbýli","fnr":"2132426","full":1,"mat":65000,"matN":64900,"bruna":70700,"ar":1975,"fm":129.8,"herb":4,"lod":1011,"ld":"2007-03","lv":17000},{"a":"Víðihlíð 13","pn":"550","sv":"Skagafjörður","teg":"Einbýli","fnr":"2132442","full":1,"mat":82200,"matN":82150,"bruna":98900,"ar":1976,"fm":189.3,"herb":4,"lod":833,"ld":"2011-06","lv":26000},{"a":"Víðihlíð 17","pn":"550","sv":"Skagafjörður","teg":"Einbýli","fnr":"2132446","full":1,"mat":77900,"matN":78000,"bruna":86500,"ar":1976,"fm":169,"herb":3,"lod":825,"ld":"2019-10","lv":45800},{"a":"Víðihlíð 19","pn":"550","sv":"Skagafjörður","teg":"Einbýli","fnr":"2132448","full":1,"mat":78050,"matN":77700,"bruna":93950,"ar":1974,"fm":183,"herb":3,"lod":864,"ld":"2020-02","lv":47000},{"a":"Víðihlíð 2","pn":"550","sv":"Skagafjörður","teg":"Einbýli","fnr":"2132427","full":1,"mat":98900,"matN":98550,"bruna":134700,"ar":1975,"fm":291.3,"herb":3,"lod":1100,"ld":"2025-06","lv":113000},{"a":"Víðihlíð 21","pn":"550","sv":"Skagafjörður","teg":"Einbýli","fnr":"2132450","full":1,"mat":71350,"matN":71250,"bruna":73340,"ar":1975,"fm":156.8,"herb":4,"lod":864,"ld":"2025-05","lv":68000},{"a":"Víðihlíð 27","pn":"550","sv":"Skagafjörður","teg":"Einbýli","fnr":"2132456","full":1,"mat":84150,"matN":83950,"bruna":96200,"ar":1980,"fm":193.1,"herb":3,"lod":833,"ld":"2017-01","lv":37500},{"a":"Víðihlíð 4","pn":"550","sv":"Skagafjörður","teg":"Einbýli","fnr":"2132430","full":1,"mat":99400,"matN":99050,"bruna":139000,"ar":1974,"fm":293.9,"herb":5,"lod":819,"ld":"2015-08","lv":32000},{"a":"Víðihlíð 5","pn":"550","sv":"Skagafjörður","teg":"Einbýli","fnr":"2132431","full":1,"mat":78850,"matN":78700,"bruna":91700,"ar":1974,"fm":182.5,"herb":5,"lod":1028,"ld":"2021-04","lv":60000},{"a":"Víðihlíð 6","pn":"550","sv":"Skagafjörður","teg":"Einbýli","fnr":"2132433","full":1,"mat":98050,"matN":97950,"bruna":127050,"ar":1982,"fm":256.1,"herb":6,"lod":819,"ld":"2024-05","lv":82000},{"a":"Víðihlíð 8","pn":"550","sv":"Skagafjörður","teg":"Einbýli","fnr":"2132436","full":1,"mat":94950,"matN":94900,"bruna":122150,"ar":1980,"fm":249.4,"herb":6,"lod":819,"ld":"2019-05","lv":44000},{"a":"Víðimýri 10","pn":"550","sv":"Skagafjörður","teg":"Fjölbýli","fnr":"2132495","full":1,"mat":50150,"matN":50300,"bruna":79640,"ar":1986,"fm":149,"herb":3,"lod":2006,"ld":"2026-04","lv":42500},{"a":"Víðimýri 8","pn":"550","sv":"Skagafjörður","teg":"Fjölbýli","fnr":"2132482","full":1,"mat":31450,"matN":31550,"bruna":36200,"ar":1986,"fm":69.3,"herb":1,"lod":2006,"ld":"2022-11","lv":18300},{"a":"Ægisstígur 1","pn":"550","sv":"Skagafjörður","teg":"Einbýli","fnr":"2132496","full":1,"mat":65700,"matN":65650,"bruna":89300,"ar":1950,"fm":193.5,"herb":8,"lod":440,"ld":"2024-12","lv":62000},{"a":"Ægisstígur 2","pn":"550","sv":"Skagafjörður","teg":"Fjölbýli","fnr":"2132498","full":1,"mat":27400,"matN":27450,"bruna":26750,"ar":1947,"fm":54.1,"herb":1,"lod":620,"ld":"2017-07","lv":9000},{"a":"Ægisstígur 3","pn":"550","sv":"Skagafjörður","teg":"Einbýli","fnr":"2132500","full":1,"mat":74650,"matN":74700,"bruna":97350,"ar":1958,"fm":213.7,"herb":6,"lod":440,"ld":"2013-10","lv":23500},{"a":"Ægisstígur 4","pn":"550","sv":"Skagafjörður","teg":"Einbýli","fnr":"2132502","full":1,"mat":78350,"matN":78450,"bruna":87650,"ar":1947,"fm":174,"herb":4,"lod":620,"ld":"2014-04","lv":26000},{"a":"Ægisstígur 5","pn":"550","sv":"Skagafjörður","teg":"Einbýli","fnr":"2132504","full":1,"mat":52000,"matN":51650,"bruna":64600,"ar":1959,"fm":138.6,"herb":3,"lod":440,"ld":"2025-05","lv":40000},{"a":"Ægisstígur 6","pn":"550","sv":"Skagafjörður","teg":"Einbýli","fnr":"2132506","full":1,"mat":60000,"matN":60100,"bruna":69750,"ar":1948,"fm":158.1,"herb":3,"lod":483,"ld":"2007-06","lv":17200},{"a":"Öldustígur 1","pn":"550","sv":"Skagafjörður","teg":"Fjölbýli","fnr":"2132511","full":1,"mat":55000,"matN":54800,"bruna":64600,"ar":1959,"fm":151.7,"herb":5,"lod":704,"ld":"2019-04","lv":24000},{"a":"Öldustígur 10","pn":"550","sv":"Skagafjörður","teg":"Sérbýli","fnr":"2132525","full":1,"mat":46950,"matN":46700,"bruna":50870,"ar":1951,"fm":124.6,"herb":3,"lod":376,"ld":"2007-07","lv":14700},{"a":"Öldustígur 13","pn":"550","sv":"Skagafjörður","teg":"Einbýli","fnr":"2132530","full":1,"mat":56500,"matN":56700,"bruna":70300,"ar":1955,"fm":151.6,"herb":3,"lod":420,"ld":"2017-05","lv":30000},{"a":"Öldustígur 15","pn":"550","sv":"Skagafjörður","teg":"Fjölbýli","fnr":"2132536","full":1,"mat":41100,"matN":41050,"bruna":46100,"ar":1959,"fm":100.7,"herb":2,"lod":535,"ld":"2017-03","lv":13500},{"a":"Öldustígur 15","pn":"550","sv":"Skagafjörður","teg":"Fjölbýli","fnr":"2132535","full":1,"mat":47050,"matN":46850,"bruna":52450,"ar":1959,"fm":122.5,"herb":2,"lod":535,"ld":"2018-04","lv":20500},{"a":"Öldustígur 16","pn":"550","sv":"Skagafjörður","teg":"Sérbýli","fnr":"2132538","full":1,"mat":24350,"matN":24400,"bruna":50550,"ar":1951,"fm":117.4,"herb":1,"lod":449,"ld":"2008-05","lv":11000},{"a":"Öldustígur 17","pn":"550","sv":"Skagafjörður","teg":"Einbýli","fnr":"2132540","full":1,"mat":66700,"matN":66900,"bruna":73900,"ar":1957,"fm":165.7,"herb":3,"lod":608,"ld":"2019-06","lv":35500},{"a":"Öldustígur 2","pn":"550","sv":"Skagafjörður","teg":"Sérbýli","fnr":"2132513","full":1,"mat":38650,"matN":38500,"bruna":42850,"ar":1951,"fm":94.8,"herb":3,"lod":190,"ld":"2023-04","lv":45000},{"a":"Öldustígur 3","pn":"550","sv":"Skagafjörður","teg":"Fjölbýli","fnr":"2132515","full":1,"mat":45000,"matN":44850,"bruna":52650,"ar":1959,"fm":115.3,"herb":3,"lod":775,"ld":"2024-11","lv":35000},{"a":"Öldustígur 4","pn":"550","sv":"Skagafjörður","teg":"Sérbýli","fnr":"2132516","full":1,"mat":57800,"matN":57400,"bruna":78800,"ar":1951,"fm":168,"herb":4,"lod":360,"ld":"2025-09","lv":52000},{"a":"Öldustígur 5","pn":"550","sv":"Skagafjörður","teg":"Einbýli","fnr":"2132518","full":1,"mat":79400,"matN":79150,"bruna":104250,"ar":1962,"fm":231.2,"herb":4,"lod":728,"ld":"2016-04","lv":30000},{"a":"Öldustígur 6","pn":"550","sv":"Skagafjörður","teg":"Sérbýli","fnr":"2132519","full":1,"mat":50800,"matN":50700,"bruna":63300,"ar":1951,"fm":139.5,"herb":2,"lod":354,"ld":"2022-03","lv":38000},{"a":"Öldustígur 7","pn":"550","sv":"Skagafjörður","teg":"Fjölbýli","fnr":"2132520","full":1,"mat":52350,"matN":51950,"bruna":63200,"ar":1969,"fm":125.2,"herb":3,"lod":666,"ld":"2007-06","lv":13500}]