[{"a":"Bakki 3","pn":"765","sv":"Múlaþing","teg":"Einbýli","fnr":"2179535","full":1,"mat":25100,"matN":24400,"bruna":47700,"ar":1947,"fm":124.2,"herb":3,"lod":600,"ld":"2007-06","lv":5000},{"a":"Borgarland 11","pn":"765","sv":"Múlaþing","teg":"Sérbýli","fnr":"2179459","full":1,"mat":25200,"matN":24450,"bruna":41900,"ar":1984,"fm":74.8,"herb":2,"lod":675,"ld":"2016-02","lv":9800},{"a":"Borgarland 13","pn":"765","sv":"Múlaþing","teg":"Sérbýli","fnr":"2179286","full":1,"mat":25850,"matN":25100,"bruna":40800,"ar":1984,"fm":74.8,"herb":2,"lod":675,"ld":"2015-07","lv":9200},{"a":"Borgarland 14","pn":"765","sv":"Múlaþing","teg":"Einbýli","fnr":"2179539","full":1,"mat":44250,"matN":43050,"bruna":87850,"ar":1987,"fm":153.2,"herb":4,"lod":1125,"ld":"2026-06","lv":54000},{"a":"Borgarland 15","pn":"765","sv":"Múlaþing","teg":"Einbýli","fnr":"2179507","full":1,"mat":34500,"matN":33550,"bruna":61750,"ar":1981,"fm":115.2,"herb":4,"lod":906,"ld":"2025-03","lv":21255},{"a":"Borgarland 20B","pn":"765","sv":"Múlaþing","teg":"Sérbýli","fnr":"2179288","full":1,"mat":28950,"matN":28050,"bruna":49250,"ar":1992,"fm":87.8,"herb":3,"lod":398,"ld":"2018-04","lv":13400},{"a":"Borgarland 21","pn":"765","sv":"Múlaþing","teg":"Einbýli","fnr":"2179510","full":1,"mat":38650,"matN":37450,"bruna":60050,"ar":1977,"fm":146.8,"herb":5,"lod":800,"ld":"2012-11","lv":8500},{"a":"Borgarland 22A","pn":"765","sv":"Múlaþing","teg":"Einbýli","fnr":"2223734","full":1,"mat":32050,"matN":31050,"bruna":55300,"ar":1995,"fm":98.2,"herb":3,"lod":424,"ld":"2015-05","lv":9000},{"a":"Borgarland 22B","pn":"765","sv":"Múlaþing","teg":"Sérbýli","fnr":"2223735","full":1,"mat":31800,"matN":30700,"bruna":55700,"ar":1995,"fm":98.2,"herb":3,"lod":650,"ld":"2017-07","lv":14500},{"a":"Borgarland 24","pn":"765","sv":"Múlaþing","teg":"Einbýli","fnr":"2179407","full":1,"mat":34150,"matN":33150,"bruna":55950,"ar":1987,"fm":106.7,"herb":3,"lod":800,"ld":"2008-09","lv":5500},{"a":"Borgarland 28","pn":"765","sv":"Múlaþing","teg":"Einbýli","fnr":"2179346","full":1,"mat":42200,"matN":41050,"bruna":77320,"ar":1987,"fm":147.3,"herb":3,"lod":775,"ld":"2009-11","lv":11332},{"a":"Borgarland 3","pn":"765","sv":"Múlaþing","teg":"Einbýli","fnr":"2179381","full":1,"mat":55450,"matN":54200,"bruna":113150,"ar":1977,"fm":255.1,"herb":4,"lod":1350,"ld":"2023-03","lv":54000},{"a":"Borgarland 32A","pn":"765","sv":"Múlaþing","teg":"Sérbýli","fnr":"2179289","full":1,"mat":24450,"matN":23750,"bruna":39250,"ar":1990,"fm":67.5,"herb":2,"lod":429,"ld":"2024-06","lv":26000},{"a":"Borgarland 32B","pn":"765","sv":"Múlaþing","teg":"Sérbýli","fnr":"2179290","full":1,"mat":23850,"matN":23100,"bruna":37450,"ar":1990,"fm":67.5,"herb":2,"lod":325,"ld":"2015-09","lv":6900},{"a":"Borgarland 34","pn":"765","sv":"Múlaþing","teg":"Einbýli","fnr":"2179378","full":1,"mat":36650,"matN":35650,"bruna":63500,"ar":1985,"fm":116,"herb":4,"lod":965,"ld":"2007-05","lv":8500},{"a":"Borgarland 38","pn":"765","sv":"Múlaþing","teg":"Einbýli","fnr":"2179291","full":1,"mat":31750,"matN":30800,"bruna":58850,"ar":1990,"fm":109.6,"herb":3,"lod":434,"ld":"2018-02","lv":15500},{"a":"Borgarland 40","pn":"765","sv":"Múlaþing","teg":"Einbýli","fnr":"2179292","full":1,"mat":31750,"matN":30800,"bruna":59100,"ar":1990,"fm":109.6,"herb":3,"lod":434,"ld":"2022-07","lv":24000},{"a":"Borgarland 42","pn":"765","sv":"Múlaþing","teg":"Einbýli","fnr":"2179293","full":1,"mat":31900,"matN":30900,"bruna":58850,"ar":1990,"fm":109.6,"herb":3,"lod":465,"ld":"2018-11","lv":15500},{"a":"Borgarland 44","pn":"765","sv":"Múlaþing","teg":"Einbýli","fnr":"2179294","full":1,"mat":32100,"matN":31100,"bruna":58850,"ar":1990,"fm":109.6,"herb":3,"lod":558,"ld":"2007-12","lv":5500},{"a":"Borgarland 46A","pn":"765","sv":"Múlaþing","teg":"Sérbýli","fnr":"2513590","full":1,"mat":37450,"matN":36450,"bruna":62750,"ar":2024,"fm":101.9,"herb":3,"lod":1099,"ld":"2026-05","lv":52500},{"a":"Brekka 1","pn":"765","sv":"Múlaþing","teg":"Einbýli","fnr":"2179534","full":1,"mat":24550,"matN":23850,"bruna":41700,"ar":1980,"fm":73,"herb":2,"lod":500,"ld":"2006-12","lv":4200},{"a":"Brekka 12","pn":"765","sv":"Múlaþing","teg":"Einbýli","fnr":"2179457","full":1,"mat":26050,"matN":25500,"bruna":38150,"ar":1930,"fm":81.8,"herb":2,"lod":826,"ld":"2026-01","lv":30000},{"a":"Brekka 16","pn":"765","sv":"Múlaþing","teg":"Fjölbýli","fnr":"2231322","full":0,"mat":17900,"matN":18650,"bruna":31850,"ar":1952,"fm":114.2,"herb":3,"lod":800,"ld":"2008-03","lv":3521},{"a":"Brekka 16","pn":"765","sv":"Múlaþing","teg":"Fjölbýli","fnr":"2231318","full":0,"mat":12800,"matN":13350,"bruna":18250,"ar":1952,"fm":62.8,"herb":2,"lod":800,"ld":"2017-04","lv":4961},{"a":"Brekka 16","pn":"765","sv":"Múlaþing","teg":"Fjölbýli","fnr":"2231319","full":1,"mat":12000,"matN":12800,"bruna":23900,"ar":1952,"fm":61.4,"herb":2,"lod":800,"ld":"2020-01","lv":3000},{"a":"Brekka 3","pn":"765","sv":"Múlaþing","teg":"Einbýli","fnr":"2179295","full":1,"mat":24400,"matN":23700,"bruna":41700,"ar":1980,"fm":73,"herb":2,"lod":463,"ld":"2015-05","lv":7500},{"a":"Brekka 4","pn":"765","sv":"Múlaþing","teg":"Einbýli","fnr":"2179547","full":1,"mat":40500,"matN":39400,"bruna":79850,"ar":1973,"fm":161.6,"herb":5,"lod":712,"ld":"2019-04","lv":24000},{"a":"Brekka 5","pn":"765","sv":"Múlaþing","teg":"Einbýli","fnr":"2179367","full":1,"mat":35100,"matN":34100,"bruna":66600,"ar":1977,"fm":114.4,"herb":3,"lod":900,"ld":"2018-06","lv":17700},{"a":"Brekka 8","pn":"765","sv":"Múlaþing","teg":"Einbýli","fnr":"2179366","full":1,"mat":30300,"matN":29500,"bruna":53150,"ar":1928,"fm":137.6,"herb":4,"lod":1295,"ld":"2026-05","lv":28000},{"a":"Búland 10","pn":"765","sv":"Múlaþing","teg":"Einbýli","fnr":"2179552","full":1,"mat":41550,"matN":40350,"bruna":78170,"ar":1966,"fm":159.9,"herb":2,"lod":1000,"ld":"2023-01","lv":36000},{"a":"Búland 14","pn":"765","sv":"Múlaþing","teg":"Einbýli","fnr":"2179455","full":1,"mat":33700,"matN":32800,"bruna":62100,"ar":1965,"fm":113,"herb":3,"lod":700,"ld":"2009-10","lv":7000},{"a":"Búland 16","pn":"765","sv":"Múlaþing","teg":"Einbýli","fnr":"2179516","full":1,"mat":41100,"matN":39950,"bruna":73400,"ar":1968,"fm":112.6,"herb":3,"lod":600,"ld":"2026-01","lv":56000},{"a":"Búland 8","pn":"765","sv":"Múlaþing","teg":"Einbýli","fnr":"2179466","full":1,"mat":36650,"matN":35550,"bruna":70470,"ar":1965,"fm":141.1,"herb":3,"lod":700,"ld":"2015-07","lv":7500},{"a":"Eyjaland 3","pn":"765","sv":"Múlaþing","teg":"Einbýli","fnr":"2179351","full":1,"mat":30700,"matN":29850,"bruna":52640,"ar":1945,"fm":129.1,"herb":3,"lod":1000,"ld":"2010-06","lv":1950},{"a":"Hammersminni 1","pn":"765","sv":"Múlaþing","teg":"Einbýli","fnr":"2179433","full":1,"mat":44950,"matN":43800,"bruna":74700,"ar":1968,"fm":147.9,"herb":3,"lod":700,"ld":"2023-01","lv":34000},{"a":"Hammersminni 14","pn":"765","sv":"Múlaþing","teg":"Einbýli","fnr":"2179401","full":1,"mat":44350,"matN":43150,"bruna":86800,"ar":1976,"fm":166.2,"herb":3,"lod":1064,"ld":"2011-01","lv":9000},{"a":"Hammersminni 16","pn":"765","sv":"Múlaþing","teg":"Einbýli","fnr":"2179403","full":1,"mat":49800,"matN":48250,"bruna":107200,"ar":1976,"fm":230.6,"herb":6,"lod":1064,"ld":"2008-07","lv":20000},{"a":"Hammersminni 18","pn":"765","sv":"Múlaþing","teg":"Einbýli","fnr":"2179392","full":1,"mat":42500,"matN":41500,"bruna":95520,"ar":1933,"fm":222.6,"herb":5,"lod":1614,"ld":"2019-03","lv":11000},{"a":"Hammersminni 3","pn":"765","sv":"Múlaþing","teg":"Einbýli","fnr":"2179369","full":1,"mat":34650,"matN":33550,"bruna":67050,"ar":1948,"fm":168.8,"herb":5,"lod":700,"ld":"2021-05","lv":21000},{"a":"Hammersminni 6","pn":"765","sv":"Múlaþing","teg":"Einbýli","fnr":"2179395","full":1,"mat":36700,"matN":35550,"bruna":60200,"ar":1984,"fm":124.3,"herb":4,"lod":1100,"ld":"2026-03","lv":34500},{"a":"Hlíð 3","pn":"765","sv":"Múlaþing","teg":"Einbýli","fnr":"2179410","full":1,"mat":29950,"matN":29200,"bruna":40600,"ar":1930,"fm":94.1,"herb":2,"lod":400,"ld":"2022-08","lv":4000},{"a":"Hraun 3","pn":"765","sv":"Múlaþing","teg":"Einbýli","fnr":"2179374","full":1,"mat":43450,"matN":42300,"bruna":106050,"ar":1968,"fm":181.7,"herb":4,"lod":600,"ld":"2015-05","lv":18000},{"a":"Kambur 10","pn":"765","sv":"Múlaþing","teg":"Fjölbýli","fnr":"2179448","full":1,"mat":58450,"matN":56300,"bruna":162700,"ar":1958,"fm":254.4,"herb":5,"lod":750,"ld":"2007-08","lv":20000},{"a":"Kambur 8","pn":"765","sv":"Múlaþing","teg":"Einbýli","fnr":"2179435","full":1,"mat":41750,"matN":40600,"bruna":64850,"ar":1974,"fm":166.7,"herb":4,"lod":900,"ld":"2026-06","lv":57000},{"a":"Markarland 10A","pn":"765","sv":"Múlaþing","teg":"Sérbýli","fnr":"2514368","full":0,"mat":18500,"matN":18150,"bruna":null,"ar":null,"fm":323.9,"herb":2,"lod":1250,"ld":"2026-02","lv":14000},{"a":"Markarland 11","pn":"765","sv":"Múlaþing","teg":"Einbýli","fnr":"2179528","full":1,"mat":30300,"matN":29650,"bruna":45840,"ar":1969,"fm":99.2,"herb":3,"lod":700,"ld":"2012-08","lv":6777},{"a":"Markarland 15","pn":"765","sv":"Múlaþing","teg":"Einbýli","fnr":"2179526","full":1,"mat":37850,"matN":36650,"bruna":75710,"ar":1968,"fm":148.2,"herb":4,"lod":600,"ld":"2019-04","lv":21000},{"a":"Markarland 5","pn":"765","sv":"Múlaþing","teg":"Einbýli","fnr":"2179504","full":1,"mat":41800,"matN":40650,"bruna":73850,"ar":1979,"fm":158,"herb":3,"lod":819,"ld":"2021-07","lv":34000},{"a":"Markarland 6A","pn":"765","sv":"Múlaþing","teg":"Einbýli","fnr":"2179306","full":1,"mat":26800,"matN":25950,"bruna":44850,"ar":1991,"fm":74,"herb":2,"lod":456,"ld":"2015-06","lv":9800},{"a":"Markarland 6B","pn":"765","sv":"Múlaþing","teg":"Einbýli","fnr":"2179307","full":1,"mat":26250,"matN":25400,"bruna":43000,"ar":1991,"fm":74,"herb":2,"lod":469,"ld":"2024-05","lv":26000},{"a":"Markarland 8A","pn":"765","sv":"Múlaþing","teg":"Einbýli","fnr":"2216699","full":1,"mat":26700,"matN":25900,"bruna":44050,"ar":1992,"fm":74,"herb":3,"lod":486,"ld":"2025-11","lv":26000},{"a":"Markarland 8b","pn":"765","sv":"Múlaþing","teg":"Einbýli","fnr":"2216703","full":1,"mat":30350,"matN":29400,"bruna":53200,"ar":1992,"fm":89,"herb":3,"lod":531,"ld":"2012-10","lv":7300},{"a":"Melar","pn":"765","sv":"Múlaþing","teg":"Einbýli","fnr":"2179460","full":1,"mat":26600,"matN":25800,"bruna":43100,"ar":1965,"fm":89.2,"herb":2,"lod":700,"ld":"2021-04","lv":15000},{"a":"Steinar 11","pn":"765","sv":"Múlaþing","teg":"Einbýli","fnr":"2179380","full":1,"mat":43300,"matN":41850,"bruna":96550,"ar":1977,"fm":185,"herb":7,"lod":1120,"ld":"2008-07","lv":5000},{"a":"Steinar 12","pn":"765","sv":"Múlaþing","teg":"Sérbýli","fnr":"2179318","full":1,"mat":32100,"matN":31000,"bruna":56550,"ar":1987,"fm":105,"herb":3,"lod":1110,"ld":"2020-11","lv":25500},{"a":"Steinar 13","pn":"765","sv":"Múlaþing","teg":"Einbýli","fnr":"2179485","full":1,"mat":53350,"matN":51900,"bruna":111150,"ar":1975,"fm":212,"herb":7,"lod":900,"ld":"2016-05","lv":13000},{"a":"Steinar 14","pn":"765","sv":"Múlaþing","teg":"Einbýli","fnr":"2179319","full":1,"mat":27500,"matN":26700,"bruna":45900,"ar":1987,"fm":83,"herb":2,"lod":1110,"ld":"2011-04","lv":6900},{"a":"Steinar 15","pn":"765","sv":"Múlaþing","teg":"Einbýli","fnr":"2179464","full":1,"mat":48500,"matN":46700,"bruna":115550,"ar":1980,"fm":267.4,"herb":4,"lod":1100,"ld":"2021-12","lv":46700},{"a":"Steinar 4","pn":"765","sv":"Múlaþing","teg":"Einbýli","fnr":"2179372","full":1,"mat":31000,"matN":30100,"bruna":54300,"ar":1980,"fm":106.8,"herb":2,"lod":500,"ld":"2024-06","lv":28000},{"a":"Steinar 5","pn":"765","sv":"Múlaþing","teg":"Einbýli","fnr":"2179413","full":1,"mat":34950,"matN":34000,"bruna":76250,"ar":1954,"fm":148.8,"herb":5,"lod":800,"ld":"2007-11","lv":6600},{"a":"Steinar 6","pn":"765","sv":"Múlaþing","teg":"Einbýli","fnr":"2179316","full":1,"mat":24550,"matN":23850,"bruna":41700,"ar":1980,"fm":73,"herb":2,"lod":500,"ld":"2021-01","lv":18000},{"a":"Varða 12","pn":"765","sv":"Múlaþing","teg":"Einbýli","fnr":"2179420","full":1,"mat":41200,"matN":40000,"bruna":76550,"ar":1971,"fm":154,"herb":3,"lod":775,"ld":"2010-02","lv":12000},{"a":"Varða 13","pn":"765","sv":"Múlaþing","teg":"Einbýli","fnr":"2179487","full":1,"mat":33900,"matN":32800,"bruna":64950,"ar":1973,"fm":125,"herb":6,"lod":650,"ld":"2009-10","lv":10599},{"a":"Varða 17","pn":"765","sv":"Múlaþing","teg":"Einbýli","fnr":"2179338","full":1,"mat":44550,"matN":43250,"bruna":87050,"ar":1973,"fm":172.2,"herb":5,"lod":700,"ld":"2015-07","lv":13500},{"a":"Varða 19","pn":"765","sv":"Múlaþing","teg":"Einbýli","fnr":"2179479","full":1,"mat":45700,"matN":44450,"bruna":91100,"ar":1973,"fm":173.3,"herb":5,"lod":700,"ld":"2014-10","lv":16000},{"a":"Víkurland 4","pn":"765","sv":"Múlaþing","teg":"Einbýli","fnr":"2179532","full":1,"mat":31850,"matN":30750,"bruna":73050,"ar":1955,"fm":144.4,"herb":6,"lod":1000,"ld":"2025-04","lv":36000},{"a":"Víkurland 7","pn":"765","sv":"Múlaþing","teg":"Einbýli","fnr":"2179426","full":1,"mat":28550,"matN":27850,"bruna":51500,"ar":1930,"fm":128.4,"herb":2,"lod":1162,"ld":"2025-04","lv":23500},{"a":"Vogaland 9","pn":"765","sv":"Múlaþing","teg":"Einbýli","fnr":"2179431","full":1,"mat":31150,"matN":30250,"bruna":47000,"ar":1953,"fm":130.2,"herb":2,"lod":800,"ld":"2019-12","lv":20000}]