[{"a":"Bláengi 1","pn":"816","sv":"Sveitarfélagið Ölfus","teg":"Sérbýli","mat":80450,"matN":78250,"bruna":88000,"ar":2017,"fm":158.8,"herb":3,"lod":2570,"ld":"2022-09","lv":78900},{"a":"Bláengi 1A","pn":"816","sv":"Sveitarfélagið Ölfus","teg":"Sérbýli","mat":80450,"matN":78250,"bruna":88000,"ar":2017,"fm":158.8,"herb":3,"lod":2570,"ld":"2021-10","lv":67900},{"a":"Bláengi 3A","pn":"816","sv":"Sveitarfélagið Ölfus","teg":"Sérbýli","mat":81650,"matN":79450,"bruna":91700,"ar":2020,"fm":158.8,"herb":3,"lod":2554,"ld":"2020-08","lv":58000},{"a":"Bláengi 3B","pn":"816","sv":"Sveitarfélagið Ölfus","teg":"Sérbýli","mat":81650,"matN":79450,"bruna":91700,"ar":2020,"fm":158.8,"herb":3,"lod":2554,"ld":"2020-08","lv":55800},{"a":"Bláengi 5","pn":"816","sv":"Sveitarfélagið Ölfus","teg":"Sérbýli","mat":88500,"matN":86050,"bruna":105950,"ar":null,"fm":175.1,"herb":3,"lod":2527,"ld":"2023-05","lv":65000},{"a":"Bláengi 5A","pn":"816","sv":"Sveitarfélagið Ölfus","teg":"Sérbýli","mat":86500,"matN":84100,"bruna":106300,"ar":2023,"fm":175.1,"herb":3,"lod":2527,"ld":"2024-06","lv":55000},{"a":"Borgargerði 2","pn":"816","sv":"Sveitarfélagið Ölfus","teg":"Einbýli","mat":85250,"matN":83400,"bruna":91100,"ar":1999,"fm":175.1,"herb":3,"lod":7240,"ld":"2025-12","lv":70000},{"a":"Brúarhvammur 2","pn":"816","sv":"Sveitarfélagið Ölfus","teg":"Einbýli","mat":108850,"matN":107900,"bruna":133750,"ar":1968,"fm":254.7,"herb":7,"lod":3169,"ld":"2023-06","lv":90000},{"a":"Dimmustaðir 3","pn":"816","sv":"Sveitarfélagið Ölfus","teg":"Einbýli","mat":100600,"matN":98300,"bruna":113000,"ar":2022,"fm":191.6,"herb":2,"lod":6365,"ld":"2024-10","lv":95000},{"a":"Dimmustaðir 4","pn":"816","sv":"Sveitarfélagið Ölfus","teg":"Einbýli","mat":100550,"matN":98250,"bruna":111800,"ar":null,"fm":191.6,"herb":3,"lod":6085,"ld":"2021-11","lv":59500},{"a":"Gilhagi lóð 1","pn":"816","sv":"Sveitarfélagið Ölfus","teg":"Einbýli","mat":88650,"matN":86500,"bruna":87050,"ar":2009,"fm":296.8,"herb":3,"lod":3800,"ld":"2025-02","lv":74900},{"a":"Gljúfurárholt land 7","pn":"816","sv":"Sveitarfélagið Ölfus","teg":"Einbýli","mat":83750,"matN":81550,"bruna":87250,"ar":1964,"fm":168.7,"herb":5,"lod":2952,"ld":"2019-04","lv":35000},{"a":"Grásteinn I","pn":"816","sv":"Sveitarfélagið Ölfus","teg":"Einbýli","mat":87350,"matN":85550,"bruna":105600,"ar":2017,"fm":161.3,"herb":2,"lod":2115,"ld":"2025-10","lv":115000},{"a":"Grásteinn III","pn":"816","sv":"Sveitarfélagið Ölfus","teg":"Einbýli","mat":102700,"matN":100300,"bruna":129600,"ar":1995,"fm":218.7,"herb":3,"lod":6097,"ld":"2017-05","lv":55000},{"a":"Hellugljúfur 2","pn":"816","sv":"Sveitarfélagið Ölfus","teg":"Einbýli","mat":114100,"matN":111050,"bruna":125350,"ar":2006,"fm":259.9,"herb":4,"lod":5871,"ld":"2019-08","lv":67000},{"a":"Hlíðarás","pn":"816","sv":"Sveitarfélagið Ölfus","teg":"Einbýli","mat":115700,"matN":113100,"bruna":165900,"ar":2014,"fm":279.4,"herb":4,"lod":10000,"ld":"2020-12","lv":64800},{"a":"Klettagljúfur 10","pn":"816","sv":"Sveitarfélagið Ölfus","teg":"Einbýli","mat":84150,"matN":82400,"bruna":90750,"ar":2006,"fm":205,"herb":3,"lod":6336,"ld":"2020-12","lv":56500},{"a":"Klettagljúfur 12","pn":"816","sv":"Sveitarfélagið Ölfus","teg":"Einbýli","mat":127200,"matN":123750,"bruna":173700,"ar":2014,"fm":301.3,"herb":5,"lod":5967,"ld":"2015-09","lv":28000},{"a":"Klettagljúfur 15","pn":"816","sv":"Sveitarfélagið Ölfus","teg":"Einbýli","mat":109950,"matN":107400,"bruna":105250,"ar":2006,"fm":205.7,"herb":5,"lod":6139,"ld":"2020-09","lv":41000},{"a":"Klettagljúfur 17","pn":"816","sv":"Sveitarfélagið Ölfus","teg":"Einbýli","mat":119850,"matN":116500,"bruna":123350,"ar":2006,"fm":292.1,"herb":3,"lod":6028,"ld":"2025-10","lv":90000},{"a":"Klettagljúfur 4","pn":"816","sv":"Sveitarfélagið Ölfus","teg":"Einbýli","mat":102200,"matN":99400,"bruna":115800,"ar":2006,"fm":261.5,"herb":5,"lod":6031,"ld":"2018-04","lv":42000},{"a":"Kvistás","pn":"816","sv":"Sveitarfélagið Ölfus","teg":"Einbýli","mat":87050,"matN":85050,"bruna":107600,"ar":1983,"fm":213.1,"herb":3,"lod":2142,"ld":"2017-09","lv":57000},{"a":"Lindarbær","pn":"816","sv":"Sveitarfélagið Ölfus","teg":"Einbýli","mat":76550,"matN":74900,"bruna":73850,"ar":1994,"fm":149.9,"herb":4,"lod":16873,"ld":"2020-02","lv":42000},{"a":"Lindarbær B","pn":"816","sv":"Sveitarfélagið Ölfus","teg":"Einbýli","mat":82550,"matN":80500,"bruna":116450,"ar":1971,"fm":201.9,"herb":4,"lod":4168,"ld":"2024-12","lv":89400},{"a":"Ljúfilundur","pn":"816","sv":"Sveitarfélagið Ölfus","teg":"Einbýli","mat":66050,"matN":64500,"bruna":65450,"ar":1979,"fm":135.8,"herb":4,"lod":5000,"ld":"2025-07","lv":70500},{"a":"Lækjarhvammur","pn":"816","sv":"Sveitarfélagið Ölfus","teg":"Einbýli","mat":134450,"matN":133300,"bruna":142950,"ar":2008,"fm":271.8,"herb":5,"lod":1990,"ld":"2025-05","lv":224500},{"a":"Lækur 1","pn":"816","sv":"Sveitarfélagið Ölfus","teg":"Einbýli","mat":83900,"matN":82200,"bruna":92400,"ar":2001,"fm":143.2,"herb":2,"lod":2908,"ld":"2025-09","lv":78900},{"a":"Lækur lóð","pn":"816","sv":"Sveitarfélagið Ölfus","teg":"Einbýli","mat":75572,"matN":73934,"bruna":93980,"ar":1956,"fm":232.3,"herb":7,"lod":4378,"ld":"2018-10","lv":42000},{"a":"Mýrarsel 1","pn":"816","sv":"Sveitarfélagið Ölfus","teg":"Einbýli","mat":95400,"matN":93150,"bruna":100450,"ar":2007,"fm":196.7,"herb":4,"lod":10442,"ld":"2008-03","lv":38000},{"a":"Rein","pn":"816","sv":"Sveitarfélagið Ölfus","teg":"Einbýli","mat":58400,"matN":57000,"bruna":62920,"ar":1978,"fm":137.7,"herb":3,"lod":20000,"ld":"2013-11","lv":20400},{"a":"Seylar","pn":"816","sv":"Sveitarfélagið Ölfus","teg":"Einbýli","mat":111900,"matN":108800,"bruna":175850,"ar":1981,"fm":304.5,"herb":8,"lod":1800,"ld":"2021-05","lv":78000},{"a":"Silfurberg","pn":"816","sv":"Sveitarfélagið Ölfus","teg":"Einbýli","mat":44000,"matN":43200,"bruna":37300,"ar":1993,"fm":65.8,"herb":3,"lod":800,"ld":"2018-11","lv":29000},{"a":"Spóavegur 14","pn":"816","sv":"Sveitarfélagið Ölfus","teg":"Einbýli","mat":80900,"matN":78750,"bruna":91950,"ar":1987,"fm":180.5,"herb":4,"lod":8100,"ld":"2023-04","lv":64000},{"a":"Stóragerði lóð 3","pn":"816","sv":"Sveitarfélagið Ölfus","teg":"Einbýli","mat":83200,"matN":81600,"bruna":75100,"ar":2005,"fm":100,"herb":2,"lod":25948,"ld":"2012-04","lv":16000},{"a":"Stóri-Saurbær 3","pn":"816","sv":"Sveitarfélagið Ölfus","teg":"Einbýli","mat":59950,"matN":58550,"bruna":36990,"ar":1979,"fm":838.7,"herb":4,"lod":45361,"ld":"2018-10","lv":20000},{"a":"Straumar","pn":"816","sv":"Sveitarfélagið Ölfus","teg":"Einbýli","mat":75800,"matN":74150,"bruna":94750,"ar":1971,"fm":174.1,"herb":4,"lod":10000,"ld":"2015-06","lv":40000},{"a":"Víðigerði","pn":"816","sv":"Sveitarfélagið Ölfus","teg":"Einbýli","mat":85050,"matN":83200,"bruna":79450,"ar":2002,"fm":164.8,"herb":3,"lod":6,"ld":"2017-10","lv":50000},{"a":"Ytri-Þurá","pn":"816","sv":"Sveitarfélagið Ölfus","teg":"Einbýli","mat":37400,"matN":36850,"bruna":46450,"ar":1936,"fm":81,"herb":2,"lod":700,"ld":"2021-04","lv":23900}]