{"labels": {"samthykkt": "Samþykkt", "jakvaett": "Jákvæð afgreiðsla", "synjad": "Synjað", "neikvaett": "Neikvæð afgreiðsla", "frestad": "Frestað", "visad_fra": "Vísað frá", "afturkallad": "Afturkallað", "afgreitt": "Afgreitt", "annad": "Annað"}, "severity": {"samthykkt": 2, "jakvaett": 2, "synjad": -1, "neikvaett": -1, "frestad": 0, "visad_fra": -1, "afturkallad": 0, "afgreitt": 1, "annad": 0}, "meetings": {"1152": {"url": "https://reykjavik.is/sites/default/files/2022-02/afgrei%C3%B0slufundur%2022.%20febr%C3%BAar%202022.pdf", "date": "2022-02-22"}, "1163": {"url": "https://reykjavik.is/sites/default/files/2022-05/afgrei%C3%B0slufundur%2017%20ma%C3%AD%202022.pdf", "date": "2022-05-17"}, "1165": {"url": "https://reykjavik.is/sites/default/files/2022-06/afgrei%C3%B0slufundur%2031.%20ma%C3%AD%202022.pdf", "date": "2022-05-31"}, "1166": {"url": "https://reykjavik.is/sites/default/files/2022-06/Afgrei%C3%B0slufundur%207.%20j%C3%BAn%C3%AD%202022.pdf", "date": "2022-06-07"}, "1170": {"url": "https://reykjavik.is/sites/default/files/2022-07/afgrei%C3%B0slufundur%205.%20j%C3%BAl%C3%AD%202022_0.pdf", "date": "2022-07-05"}, "1173": {"url": "https://reykjavik.is/sites/default/files/2022-07/afgrei%C3%B0slufundur%2026.%20j%C3%BAl%C3%AD%202022.pdf", "date": "2022-07-26"}, "1178": {"url": "https://reykjavik.is/sites/default/files/2023-03/Fundarger%C3%B0%20BYGG%206%20september%2022.pdf", "date": "2022-09-06"}, "1180": {"url": "https://reykjavik.is/sites/default/files/2022-09/afgrei%C3%B0slufundur%20byggingarfulltr%C3%BAa%2020.%20september%202022_0.pdf", "date": "2022-09-20"}, "1183": {"url": "https://reykjavik.is/sites/default/files/2022-10/afgrei%C3%B0slufundur%20byggingarfulltr%C3%BAa%2011.%20okt%C3%B3ber%202022.pdf", "date": "2022-10-11"}, "1184": {"url": "https://reykjavik.is/sites/default/files/2022-10/Afgrei%C3%B0slufundur%20byggingarfulltr%C3%BAa%2018.%20okt%C3%B3ber%202022.pdf", "date": "2022-10-18"}, "1185": {"url": "https://reykjavik.is/sites/default/files/2022-10/afgrei%C3%B0slufundur%20byggingarfulltr%C3%BAa%2025.%20okt%C3%B3ber%202022.pdf", "date": "2022-10-25"}, "1186": {"url": "https://reykjavik.is/sites/default/files/2022-11/afgrei%C3%B0slufundur%20byggingarfulltr%C3%BAa%201.%20n%C3%B3vember%202022.pdf", "date": "2022-11-01"}, "1187": {"url": "https://reykjavik.is/sites/default/files/2022-11/afgrei%C3%B0slufundur%20byggingarfulltr%C3%BAa%208.%20n%C3%B3vember%202022.pdf", "date": "2022-11-08"}, "1189": {"url": "https://reykjavik.is/sites/default/files/2023-03/Fundarger%C3%B0%20BYGG%2022.%20n%C3%B3vember%2022_0.pdf", "date": "2022-11-22"}, "1190": {"url": "https://reykjavik.is/sites/default/files/2022-11/afgrei%C3%B0slufundur%20byggingarfulltr%C3%BAa%2029.%20n%C3%B3vember%202022.pdf", "date": "2022-11-29"}, "1191": {"url": "https://reykjavik.is/sites/default/files/2022-12/Afgrei%C3%B0slufundur%20byggingarfulltr%C3%BAa%206.%20desember%202022.pdf", "date": "2022-12-06"}, "1192": {"url": "https://reykjavik.is/sites/default/files/2022-12/Afgrei%C3%B0slufundur%20byggingarfulltr%C3%BAa%2013.%20desember%202022_0.pdf", "date": "2022-12-13"}, "1193": {"url": "https://reykjavik.is/sites/default/files/2023-01/Afgrei%C3%B0slufundur%20byggingarfulltr%C3%BAa%2010.%20jan%C3%BAar%202023.pdf", "date": "2023-01-10"}, "1195": {"url": "https://reykjavik.is/sites/default/files/2023-01/Afgrei%C3%B0slufundur%20byggingarfulltr%C3%BAa%2024.%20jan%C3%BAar%202023_0.pdf", "date": "2023-01-24"}, "1198": {"url": "https://reykjavik.is/sites/default/files/2023-02/Afgrei%C3%B0slufundur%20byggingarfulltr%C3%BAa%2014.%20febr%C3%BAar%202023.pdf", "date": "2023-02-14"}, "1199": {"url": "https://reykjavik.is/sites/default/files/2023-02/Afgrei%C3%B0slufundur%20byggingarfulltr%C3%BAa%2021.%20febr%C3%BAar%202023.pdf", "date": "2023-02-21"}, "1200": {"url": "https://reykjavik.is/sites/default/files/2023-03/Afgrei%C3%B0slufundur%20byggingarfulltr%C3%BAa%207.%20mars%202023.pdf", "date": "2023-03-07"}, "1202": {"url": "https://reykjavik.is/sites/default/files/2023-03/Afgrei%C3%B0slufundur%20byggingarfulltr%C3%BAa%2021.%20mars%202023.pdf", "date": "2023-03-21"}, "1205": {"url": "https://reykjavik.is/sites/default/files/2023-04/Afgrei%C3%B0slufundur%20byggingarfulltr%C3%BAa%2018.%20apr%C3%ADl%202023.pdf", "date": "2023-04-18"}, "1209": {"url": "https://reykjavik.is/sites/default/files/2023-05/afgrei%C3%B0slufundur%20byggingarfulltr%C3%BAa%2016.%20ma%C3%AD%202023.pdf", "date": "2023-05-16"}, "1214": {"url": "https://reykjavik.is/sites/default/files/2023-06/afgrei%C3%B0slufundur%20byggingarfulltr%C3%BAa%2020.%20j%C3%BAn%C3%AD%202023.pdf", "date": "2023-06-20"}, "1216": {"url": "https://reykjavik.is/sites/default/files/2023-07/afgrei%C3%B0slufundur%20byggingarfulltr%C3%BAa%204.%20j%C3%BAl%C3%AD%202023.pdf", "date": "2023-07-04"}, "1217": {"url": "https://reykjavik.is/sites/default/files/2025-08/afgreidslufundur-byggingarfulltrua-29.-juli-2025.pdf", "date": "2025-07-29"}, "1221": {"url": "https://reykjavik.is/sites/default/files/2023-08/afgreidslufundur-byggingarfulltrua-8.-agust-2023_0.pdf", "date": "2023-08-08"}, "1223": {"url": "https://reykjavik.is/sites/default/files/2023-08/afgreidslufundur-byggingarfulltrua-22.-agust-2023.pdf", "date": "2023-08-22"}, "1224": {"url": "https://reykjavik.is/sites/default/files/2023-08/afgreidslufundur-byggingarfulltrua-29.-agust-2023_0.pdf", "date": "2023-08-29"}, "1230": {"url": "https://reykjavik.is/sites/default/files/2025-11/afgreidslufundur-byggingarfulltrua-4.-november-2025.pdf", "date": "2025-11-04"}, "1232": {"url": "https://reykjavik.is/sites/default/files/2025-11/afgreidslufundur-byggingarfulltrua-18.-november-2025_0.pdf", "date": "2025-11-18"}, "1106": {"url": "https://reykjavik.is/sites/default/files/afgreidslufundur_9._mars_2021.pdf", "date": "2021-03-09"}, "1235": {"url": "https://reykjavik.is/sites/default/files/2025-12/afgreidslufundur_byggingarfulltrua_9._desember_2025.pdf", "date": "2025-12-09"}, "1107": {"url": "https://reykjavik.is/sites/default/files/afgreidslufundur_16._mars_2021.pdf", "date": "2021-03-16"}, "1237": {"url": "https://reykjavik.is/sites/default/files/2026-01/afgreidslufundur-byggingarfulltrua-22.-desember-2025.pdf", "date": "2025-12-22"}, "1110": {"url": "https://reykjavik.is/sites/default/files/afgreidslufundur_13._april_2021.pdf", "date": "2021-04-13"}, "1242": {"url": "https://reykjavik.is/sites/default/files/2026-02/afgreidslufundur-byggingarfulltrua-3.-februar-2026.pdf", "date": "2026-02-03"}, "1245": {"url": "https://reykjavik.is/sites/default/files/2026-02/Afgrei%C3%B0slufundur%20byggingarfulltr%C3%BAa%2024.%20febr%C3%BAar%202026.pdf", "date": "2026-02-24"}, "1246": {"url": "https://reykjavik.is/sites/default/files/2026-03/Afgrei%C3%B0slufundur%20byggingarfulltr%C3%BAa%203.%20mars%202026.pdf", "date": "2026-03-03"}, "1247": {"url": "https://reykjavik.is/sites/default/files/2026-03/Fundarger%C3%B0%20byggingarfulltr%C3%BAa%2010.%20mars%202026.pdf", "date": "2026-03-10"}, "1248": {"url": "https://reykjavik.is/sites/default/files/2026-03/Afgrei%C3%B0slufundur_byggingarfulltr%C3%BAa_17._mars_2026_%281%29_0.pdf", "date": "2026-03-17"}, "1255": {"url": "https://reykjavik.is/sites/default/files/2026-05/Afgrei%C3%B0slufundur%20byggingarfulltr%C3%BAa%2005.%20ma%C3%AD%202026.pdf", "date": "2026-05-05"}, "1256": {"url": "https://reykjavik.is/sites/default/files/2026-05/Afgrei%C3%B0slufundur%20byggingarfulltr%C3%BAa%2012.%20ma%C3%AD%202026.pdf", "date": "2026-05-12"}, "1129": {"url": "https://reykjavik.is/sites/default/files/afgreidslufundur_31._agust_2021.pdf", "date": "2021-08-31"}, "1130": {"url": "https://reykjavik.is/sites/default/files/afgreidslufundur_7._september_2021.pdf", "date": "2021-09-07"}, "1259": {"url": "https://reykjavik.is/sites/default/files/2026-06/Afgrei%C3%B0sla%20byggingarfulltr%C3%BAa%20%C3%BEri%C3%B0judaginn%2002.%20j%C3%BAn%C3%AD%202026%20nr.%201259_1.pdf", "date": "2026-06-02"}, "1260": {"url": "https://reykjavik.is/sites/default/files/2026-06/Fundarger%C3%B0%20afgrei%C3%B0slufundar%20byggingarfulltr%C3%BAa%209.%20j%C3%BAn%C3%AD%202026_0.pdf", "date": "2026-06-09"}, "1133": {"url": "https://reykjavik.is/sites/default/files/afgreidslufundur_28._september_2021.pdf", "date": "2021-09-28"}, "1134": {"url": "https://reykjavik.is/sites/default/files/afgreidslufundur_5._oktober_2021.pdf", "date": "2021-10-05"}, "1263": {"url": "https://reykjavik.is/sites/default/files/2026-07/Fundarger%C3%B0%20Byggingarfulltr%C3%BAi%20RVK%20Scriban%20-%20Jan%C3%BAar%202025%20%284%29.pdf", "date": "2026-06-30"}, "1136": {"url": "https://reykjavik.is/sites/default/files/afgreidslufundur_19._oktober_2021.pdf", "date": "2021-10-19"}, "1137": {"url": "https://reykjavik.is/sites/default/files/afgreidslufundur_26._oktober_2021.pdf", "date": "2021-10-26"}, "1138": {"url": "https://reykjavik.is/sites/default/files/afgreidslufundur_2._november_2021_1.pdf", "date": "2021-11-02"}, "1139": {"url": "https://reykjavik.is/sites/default/files/afgreidslufundur_9._november_2021_-_leidrett_0.pdf", "date": "2021-11-09"}, "1143": {"url": "https://reykjavik.is/sites/default/files/afgreidslufundur_7._desember_2021.pdf", "date": "2021-12-07"}, "1145": {"url": "https://reykjavik.is/sites/default/files/afgreidslufundur_21._desember_2021_-_leidrett.pdf", "date": "2021-12-21"}}, "addrs": {"almannadalur 27": {"addr": "Almannadalur 27", "cases": [{"caseNo": "USK25100036", "latestCode": "samthykkt", "latestDate": "2026-06-30", "n": 5, "desc": "byggja svalir á austurgafl hesthúss, mhl. 02, á lóð nr. 27 við Almannadal. Umsókn fylgir starfsábyrgðartrygging og yfirlit breytinga", "events": [{"date": "2026-06-30", "code": "samthykkt", "fund": 1263}, {"date": "2026-05-12", "code": "frestad", "fund": 1256}, {"date": "2026-04-14", "code": "frestad", "fund": null}, {"date": "2026-03-03", "code": "frestad", "fund": 1246}, {"date": "2025-11-04", "code": "frestad", "fund": 1230}]}]}, "elliðavatnsblettur 10": {"addr": "Elliðavatnsblettur 10 (81.---.89)", "cases": [{"caseNo": "USK26050463", "latestCode": "samthykkt", "latestDate": "2026-06-09", "n": 2, "desc": "rífa sumarhús, mhl. 01, á lóð nr. 10 við Elliðavatnsblett. Niðurrif fasteignanr. F2057662, merkt sumarbústaður, 40 ferm", "events": [{"date": "2026-06-09", "code": "samthykkt", "fund": 1260}, {"date": "2026-06-02", "code": "frestad", "fund": 1259}]}, {"caseNo": "BN061867", "latestCode": "frestad", "latestDate": "2022-12-06", "n": 1, "desc": "leyfi til niðurrifs á sumarbústað á L113479, hús á lóð nr. 10 við Elliðavatnsblett", "fnr": "113479", "events": [{"date": "2022-12-06", "code": "frestad", "fund": 1191}]}]}, "elliðavatnsblettur 12": {"addr": "Elliðavatnsblettur 12 (81.---.87)", "cases": [{"caseNo": "USK26050467", "latestCode": "samthykkt", "latestDate": "2026-06-09", "n": 2, "desc": "rífa bílskúr á lóð nr. 12 við Elliðavatnsblett. Niðurrif: xx ferm", "events": [{"date": "2026-06-09", "code": "samthykkt", "fund": 1260}, {"date": "2026-06-02", "code": "frestad", "fund": 1259}]}, {"caseNo": "BN061868", "latestCode": "frestad", "latestDate": "2022-12-06", "n": 1, "desc": "leyfi til niðurrifs á sumarbústað á L113477, hús á lóð nr. 12 við Elliðavatnsblett", "fnr": "113477", "events": [{"date": "2022-12-06", "code": "frestad", "fund": 1191}]}]}, "elliðavatnsblettur 18": {"addr": "Elliðavatnsblettur 18 (81.---.81)", "cases": [{"caseNo": "USK26050464", "latestCode": "samthykkt", "latestDate": "2026-06-09", "n": 2, "desc": "rífa sumarhús, mhl. 01 á lóð nr. 12 við Elliðavatnsblett. Niðurrif: Fasteignanr. F2057648, merkt sumarbústaður, 52 ferm", "events": [{"date": "2026-06-09", "code": "samthykkt", "fund": 1260}, {"date": "2026-06-02", "code": "frestad", "fund": 1259}]}, {"caseNo": "BN061870", "latestCode": "frestad", "latestDate": "2022-12-06", "n": 1, "desc": "leyfi til niðurrifs á sumarbústað á L113471, hús á lóð nr. 18 við Elliðavatnsblett", "fnr": "113471", "events": [{"date": "2022-12-06", "code": "frestad", "fund": 1191}]}]}, "elliðavatnsblettur 19": {"addr": "Elliðavatnsblettur 19", "cases": [{"caseNo": "USK26050465", "latestCode": "samthykkt", "latestDate": "2026-06-09", "n": 2, "desc": "rífa geymslu, mhl. 01 á lóð nr. 12 við Elliðavatnsblett. Niðurrif: Fasteignanr. F2057646, merkt geymsla, 14 ferm", "events": [{"date": "2026-06-09", "code": "samthykkt", "fund": 1260}, {"date": "2026-06-02", "code": "frestad", "fund": 1259}]}]}, "elliðavatnsblettur 26": {"addr": "Elliðavatnsblettur 26", "cases": [{"caseNo": "USK26050466", "latestCode": "samthykkt", "latestDate": "2026-06-09", "n": 2, "desc": "rífa sumarbústað, mhl. 01 á lóð nr. 26 við Elliðavatnsblett. Niðurrif: Fasteignanr. F2057633, merkt sumarbústaður, 30 ferm", "events": [{"date": "2026-06-09", "code": "samthykkt", "fund": 1260}, {"date": "2026-06-02", "code": "frestad", "fund": 1259}]}]}, "elliðavatnsblettur 6": {"addr": "Elliðavatnsblettur 6 (81.---.93)", "cases": [{"caseNo": "USK26050462", "latestCode": "samthykkt", "latestDate": "2026-06-09", "n": 2, "desc": "rífa sumarbústað, mhl. 01 á lóð nr. 6 við Elliðavatnsblett. Niðurrif: Fasteignanr. F2057666, merkt sumarbústaður, 40 ferm", "events": [{"date": "2026-06-09", "code": "samthykkt", "fund": 1260}, {"date": "2026-06-02", "code": "frestad", "fund": 1259}]}, {"caseNo": "BN061829", "latestCode": "frestad", "latestDate": "2022-12-06", "n": 1, "desc": "leyfi til niðurrifs á sumarbústað á L113483, hús á lóð nr. 6 við Elliðavatnsblett", "fnr": "113483", "events": [{"date": "2022-12-06", "code": "frestad", "fund": 1191}]}]}, "hólmsheiðarvegur 151": {"addr": "Hólmsheiðarvegur 151", "cases": [{"caseNo": "USK25110054", "latestCode": "samthykkt", "latestDate": "2026-05-05", "n": 4, "desc": "byggja geymslu, stálgrindarhús klætt samlokueiningum sem verður mhl. 09 á lóð nr. 151 við Hólmasheiðaveg", "sizeM2": 1000.0, "sizeM3": 7.0, "events": [{"date": "2026-05-05", "code": "samthykkt", "fund": 1255}, {"date": "2026-04-28", "code": "frestad", "fund": null}, {"date": "2026-04-21", "code": "frestad", "fund": null}, {"date": "2025-12-09", "code": "frestad", "fund": 1235}]}, {"caseNo": "USK25060267", "latestCode": "samthykkt", "latestDate": "2026-02-24", "n": 5, "desc": "leyfi til þess að breyta innra skipulagi þannig að starfsmannaaðstaða er stækkuð, milliloft er stækkað, skrifstofum bætt við og gluggar gerðir á á ?-h", "sizeM2": 69.5, "sizeM3": 127.4, "events": [{"date": "2026-02-24", "code": "samthykkt", "fund": 1245}, {"date": "2026-02-03", "code": "frestad", "fund": 1242}, {"date": "2025-12-22", "code": "frestad", "fund": 1237}, {"date": "2025-11-18", "code": "frestad", "fund": 1232}, {"date": "2025-07-29", "code": "frestad", "fund": 1217}]}, {"caseNo": "USK24120112", "latestCode": "frestad", "latestDate": "2025-01-14", "n": 3, "desc": "breyta erindi USK23100231 vegna lokaúttektar sem snýr að því að færa inntak í húsi nr. 151 við Hólmsheiðarveg", "events": [{"date": "2025-01-14", "code": "frestad", "fund": 1190}, {"date": "2025-01-07", "code": "frestad", "fund": 1189}, {"date": "2024-01-21", "code": "samthykkt", "fund": 1191}]}, {"caseNo": "USK23100231", "latestCode": "samthykkt", "latestDate": "2023-12-12", "n": 4, "desc": "byggja stálgrindarskemmu, klædda PIR samlokueiningum á lóð nr. 151 við Hólmsheiðarveg", "sizeM2": 640.0, "events": [{"date": "2023-12-12", "code": "samthykkt", "fund": 1139}, {"date": "2023-11-28", "code": "frestad", "fund": 1137}, {"date": "2023-11-21", "code": "frestad", "fund": 1136}, {"date": "2023-10-31", "code": "frestad", "fund": 1133}]}]}, "hólmsheiðarvegur 139": {"addr": "Hólmsheiðarvegur 139", "cases": [{"caseNo": "USK26030152", "latestCode": "samthykkt", "latestDate": "2026-03-17", "n": 2, "desc": "stöðuleyfi fyrir frístundahús í smíðum sem ætlað er til flutnings á lóð nr. 139 við Hólmsheiðarveg", "events": [{"date": "2026-03-17", "code": "samthykkt", "fund": 1248}, {"date": "2026-03-10", "code": "frestad", "fund": 1247}]}]}, "elliðavatnsblettur 21": {"addr": "Elliðavatnsblettur 21", "cases": [{"caseNo": "USK25080131", "latestCode": "frestad", "latestDate": "2025-09-23", "n": 1, "desc": "leyfi til þess að byggja rishæð samhliða endurbótum og viðhaldi á sumarhúsi á lóð nr. 21 við Elliðavatnsblett", "events": [{"date": "2025-09-23", "code": "frestad", "fund": 1224}]}]}, "b gata 19": {"addr": "B gata 19", "cases": [{"caseNo": "USK25020256", "latestCode": "frestad", "latestDate": "2025-09-02", "n": 3, "desc": "breyta erindi BN032714 vegna lokaúttektar, þannig að eignarhlutar eru sameinaðir og innra skipulagi, gluggum og hurðum er breytt á hesthúsi við B götu", "events": [{"date": "2025-09-02", "code": "frestad", "fund": 1221}, {"date": "2025-06-03", "code": "frestad", "fund": 1209}, {"date": "2025-03-11", "code": "frestad", "fund": 1198}]}]}, "almannadalur 9": {"addr": "Almannadalur 9", "cases": [{"caseNo": "USK25010148", "latestCode": "samthykkt", "latestDate": "2025-05-06", "n": 3, "desc": "leyfi til þess að breyta erindi BN060970 með því að hækka gólf í stíum í hesthúsi á lóð nr. 9 við Almannadal", "events": [{"date": "2025-05-06", "code": "samthykkt", "fund": 1205}, {"date": "2025-04-08", "code": "frestad", "fund": 1202}, {"date": "2025-01-28", "code": "frestad", "fund": 1192}]}, {"caseNo": "BN060970", "latestCode": "frestad", "latestDate": "2022-07-05", "n": 3, "desc": "byggja hesthús, fjögur rými í einni lengju á tveimur hæðum, kaffistofa og stoðrými á efri hæð í húsi nr. 9 á lóð nr. 9-15 við Almannadal", "fnr": "209395", "sizeM2": 547.2, "events": [{"date": "2022-07-05", "code": "frestad", "fund": 1170}, {"date": "2022-06-07", "code": "frestad", "fund": 1166}, {"date": "2022-05-17", "code": "frestad", "fund": 1163}]}]}, "hólmsheiðarvegur 141": {"addr": "Hólmsheiðarvegur 141", "cases": [{"caseNo": "USK24110181", "latestCode": "frestad", "latestDate": "2025-05-06", "n": 4, "desc": "leyfi fyrir áður gerðum mannvirkjum sem eru þrjár geymslur / flugskýli mhl. 02,03 og 04 á lóð 141 við Hólmsheiðarveg. Erindi fylgir gátlisti hönnuðar.", "events": [{"date": "2025-05-06", "code": "frestad", "fund": 1205}, {"date": "2025-01-14", "code": "frestad", "fund": 1190}, {"date": "2025-01-07", "code": "frestad", "fund": 1189}, {"date": "2024-11-26", "code": "frestad", "fund": 1185}]}]}, "b gata 5": {"addr": "B gata 5", "cases": [{"caseNo": "USK25020257", "latestCode": "frestad", "latestDate": "2025-04-08", "n": 2, "desc": "leyfi fyrir áður gerðum breytingum á hest- og fjárhúsi á lóð nr. 5 við Surtlugötu", "events": [{"date": "2025-04-08", "code": "frestad", "fund": 1202}, {"date": "2025-03-11", "code": "frestad", "fund": 1198}]}]}, "hrossnes 10": {"addr": "Hrossnes 10-16", "cases": [{"caseNo": "USK24100358", "latestCode": "samthykkt", "latestDate": "2025-03-25", "n": 6, "desc": "byggja hesthús á tveimur hæðum á mhl. 01 á lóð nr. 10-16 við Hrossnes. Stærð 393,6 ferm og 1072,90 rúmm. Erindinu fylgir umsögn skipulagsfulltrúa dags", "sizeM2": 393.6, "events": [{"date": "2025-03-25", "code": "samthykkt", "fund": 1200}, {"date": "2025-03-11", "code": "frestad", "fund": 1198}, {"date": "2025-02-04", "code": "frestad", "fund": 1193}, {"date": "2025-01-28", "code": "frestad", "fund": 1192}, {"date": "2024-12-03", "code": "frestad", "fund": 1186}, {"date": "2024-11-19", "code": "frestad", "fund": 1184}]}]}, "vegbrekkur 99": {"addr": "Vegbrekkur 99", "cases": [{"caseNo": "USK25010351", "latestCode": "samthykkt", "latestDate": "2025-02-18", "n": 1, "desc": "rífa geymsluskúr, mhl. 02, merkt 0101 á lóð nr. 99 við Vegbrekku", "events": [{"date": "2025-02-18", "code": "samthykkt", "fund": 1195}]}]}, "b gata 10": {"addr": "B gata 10", "cases": [{"caseNo": "USK23090318", "latestCode": "frestad", "latestDate": "2024-07-02", "n": 1, "desc": "að fá þegar byggt hesthús samþykkt á lóð nr. 10 við Surtlugötu", "events": [{"date": "2024-07-02", "code": "frestad", "fund": 1165}]}]}, "almannadalur 23": {"addr": "Almannadalur 23", "cases": [{"caseNo": "USK24030186", "latestCode": "frestad", "latestDate": "2024-03-26", "n": 1, "desc": "breyta stofnerindi BN036041 með því að setja svalir á mhl. 04 á báða gafla húss nr. 23 við Almannadal. Gjald kr. 15.400", "events": [{"date": "2024-03-26", "code": "frestad", "fund": 1152}]}]}, "a gata 1": {"addr": "A gata 1", "cases": [{"caseNo": "USK23090318", "latestCode": "frestad", "latestDate": "2023-12-12", "n": 4, "desc": "leyfi fyrir áður gerðu hesthúsi á lóð nr. 10 við Surtlugötu. Gjald kr. 14.500. Afgreiðsla:", "sizeM2": 547.2, "events": [{"date": "2023-12-12", "code": "frestad", "fund": 1139}, {"date": "2023-12-05", "code": "frestad", "fund": 1138}, {"date": "2023-11-28", "code": "frestad", "fund": 1137}, {"date": "2023-11-07", "code": "frestad", "fund": 1134}]}]}, "b gata 11": {"addr": "B gata 11", "cases": [{"caseNo": "USK23090025", "latestCode": "samthykkt", "latestDate": "2023-12-05", "n": 3, "desc": "byggja hesthús á lóð nr.11 við Surtlugötu", "events": [{"date": "2023-12-05", "code": "samthykkt", "fund": 1138}, {"date": "2023-11-28", "code": "frestad", "fund": 1137}, {"date": "2023-10-03", "code": "frestad", "fund": 1129}]}]}, "vegbrekkur 9": {"addr": "Vegbrekkur 9-15", "cases": [{"caseNo": "USK23050025", "latestCode": "samthykkt", "latestDate": "2023-10-31", "n": 5, "desc": "byggja hesthús á lóðarhluta nr. 13 á lóð nr. 9-15 við Vegbrekku. Stærð: 495,2 ferm., 1,334.5 rúmm. Erindi fylgir hæðarblað dags. febrúar 2008 og mælib", "sizeM2": 495.2, "events": [{"date": "2023-10-31", "code": "samthykkt", "fund": 1133}, {"date": "2023-10-10", "code": "frestad", "fund": 1130}, {"date": "2023-08-22", "code": "frestad", "fund": 1223}, {"date": "2023-07-04", "code": "frestad", "fund": 1216}, {"date": "2023-06-20", "code": "frestad", "fund": 1214}]}]}, "elliðavatnsblettur 35": {"addr": "Elliðavatnsblettur 35", "cases": [{"caseNo": "USK23070063", "latestCode": "samthykkt", "latestDate": "2023-08-22", "n": 1, "desc": "leyfi til þess að fjarlægja og farga brunarústum sumarbústaðar, mhl.01, og tilheyrandi bátaskýli, mhl.02 á lóð nr. 35 við Elliðavatnsblett", "events": [{"date": "2023-08-22", "code": "samthykkt", "fund": 1223}]}]}, "almannadalur 25": {"addr": "Almannadalur 25-29", "cases": [{"caseNo": "BN061398", "latestCode": "samthykkt", "latestDate": "2022-11-08", "n": 6, "desc": "byggja hesthús á tveimur hæðum, steinsteypt burðarvirki með timbur þaki, skipt upp í tvær notkunareiningar, notkunareining 03-0101 eru 8 stíur ásamt h", "fnr": "208504", "sizeM2": 423.2, "events": [{"date": "2022-11-08", "code": "samthykkt", "fund": 1187}, {"date": "2022-11-01", "code": "frestad", "fund": 1186}, {"date": "2022-10-25", "code": "frestad", "fund": 1185}, {"date": "2022-10-11", "code": "frestad", "fund": 1183}, {"date": "2022-09-20", "code": "frestad", "fund": 1180}, {"date": "2022-09-06", "code": "frestad", "fund": 1178}]}]}, "mjódalsvegur 16": {"addr": "Mjódalsvegur 16", "cases": [{"caseNo": "USK23020091", "latestCode": "samthykkt", "latestDate": "2023-02-21", "n": 1, "desc": "reisa hitaveitugeymi, matshluta nr. 07 á lóð nr. 16 við Mjódalsveg", "sizeM2": 857.2, "events": [{"date": "2023-02-21", "code": "samthykkt", "fund": 1199}]}]}, "elliðavatnsblettur 13": {"addr": "Elliðavatnsblettur 13 (81.---.86)", "cases": [{"caseNo": "BN061869", "latestCode": "frestad", "latestDate": "2022-12-06", "n": 1, "desc": "leyfi til niðurrifs á sumarbústað á L113476, hús á lóð nr. 13 við Elliðavatnsblett", "fnr": "113476", "events": [{"date": "2022-12-06", "code": "frestad", "fund": 1191}]}]}, "almannadalur 17": {"addr": "Almannadalur 17-23", "cases": [{"caseNo": "BN061285", "latestCode": "frestad", "latestDate": "2022-07-26", "n": 1, "desc": "koma fyrir svölum á vestur og austur göflum hesthússins nr. 23 á lóð nr. 17 og 23 við Almannadal. Gjald kr. 12.600", "fnr": "208505", "events": [{"date": "2022-07-26", "code": "frestad", "fund": 1173}]}, {"caseNo": "BN058912", "latestCode": "frestad", "latestDate": "2021-12-21", "n": 5, "desc": "breyta erindi, BN036042, þannig að svalir eru lengdar á suðurgafli á hesthúsi nr. 19 á lóð nr. 17-21 í Almannadal. Útskrift úr gerðabók embættisafgrei", "fnr": "208505", "events": [{"date": "2021-12-21", "code": "frestad", "fund": 1145}, {"date": "2021-12-07", "code": "frestad", "fund": 1143}, {"date": "2021-04-13", "code": "frestad", "fund": 1110}, {"date": "2021-03-16", "code": "frestad", "fund": 1107}, {"date": "2021-03-09", "code": "frestad", "fund": 1106}]}, {"caseNo": "BN060112", "latestCode": "samthykkt", "latestDate": "2021-11-09", "n": 2, "desc": "breyta erindi, BN036042, vegna lokaúttektar, á hesthúsi nr. 19 á lóð nr. 17-23 í Almannadal. Gjald kr. 12.100", "fnr": "208505", "events": [{"date": "2021-11-09", "code": "samthykkt", "fund": 1139}, {"date": "2021-10-26", "code": "frestad", "fund": 1137}]}, {"caseNo": "BN059914", "latestCode": "samthykkt", "latestDate": "2021-09-28", "n": 1, "desc": "breyta erindi, BN036042, þannig að innra skipulagi rýma 0102 og 0202 er breytt, í hesthúsi nr. 19 á lóðinni nr. 17-23 við Almannadal. Gjald kr. 12.100", "fnr": "208505", "events": [{"date": "2021-09-28", "code": "samthykkt", "fund": 1133}]}]}, "vegbrekkur 43": {"addr": "Vegbrekkur 43", "cases": [{"caseNo": "BN060345", "latestCode": "frestad", "latestDate": "2021-12-21", "n": 1, "desc": "leyfi fyrir varaaflstöð, rofa - og spennahús og olíuskilju við hús á lóð nr. 43 við Vegbrekkur", "fnr": "197582", "events": [{"date": "2021-12-21", "code": "frestad", "fund": 1145}]}]}}}