{"updated":"2026-07-16T08:01:43.916Z","n":24,"nFasteignir":23,"source":"Sýslumenn — opinberar uppboðsauglýsingar (island.is)","sourceUrl":"https://island.is/nauthungarsolur","note":"auctionType segir stöðu (byrjun/framhald/sölu lokið). Uppboðsauglýsingar eru opinberar skv. lögum um nauðungarsölu.","rows":[{"e":"Sýslumaðurinn á höfuðborgarsvæðinu","st":"Hlíðasmári 1","teg":"Sölu lokið","flokkur":"Fasteign","a":"Kirkjustræti 2, Reykjavík","id":"2002741","d":"2025-04-08","kl":"11:00"},{"e":"Sýslumaðurinn á Suðurnesjum","st":"Keflavík","teg":"Sölu lokið","flokkur":"Fasteign","a":"Faxagrund 20, Reykjanesbær","id":"2247278","d":"2026-01-13","kl":"13:20"},{"e":"Sýslumaðurinn á Suðurnesjum","st":"Keflavík","teg":"Sölu lokið","flokkur":"Fasteign","a":"Tunguvegur 8, Reykjanesbær","id":"2258896","d":"2026-01-13","kl":"10:30"},{"e":"Sýslumaðurinn á höfuðborgarsvæðinu","st":"Hlíðasmári 1","teg":"Sölu lokið","flokkur":"Fasteign","a":"Hringbraut 25, Hafnarfjörður","id":"2076063","d":"2026-02-09","kl":"10:30"},{"e":"Sýslumaðurinn á Vesturlandi","st":"Stykkishólmur","teg":"Sölu lokið","flokkur":"Fasteign","a":"Borgarvík 24, Borgarbyggð","id":"2111157","d":"2026-02-17","kl":"13:45"},{"e":"Sýslumaðurinn á höfuðborgarsvæðinu","st":"Hlíðasmári 1","teg":"Sölu lokið","flokkur":"Fasteign","a":"Lautasmári 18, Kópavogur, 50 % ehl.","id":"2225471","d":"2026-05-04","kl":"10:30"},{"e":"Sýslumaðurinn á Vesturlandi","st":"Stykkishólmur","teg":"Sölu lokið","flokkur":"Fasteign","a":"Skólastígur 3, Hvalfjarðarsveit","id":"2524307","d":"2026-05-04","kl":"14:00"},{"e":"Sýslumaðurinn á Suðurnesjum","st":"Keflavík","teg":"Sölu lokið","flokkur":"Fasteign","a":"Heiðarvegur 22, Reykjanesbær","id":"2089043","d":"2026-05-12","kl":"09:00"},{"e":"Sýslumaðurinn í Vestmannaeyjum","st":"Vestmannaeyjar","teg":"Sölu lokið","flokkur":"Fasteign","a":"Strandvegur 65B, Vestmannaeyjar","id":"2184787","d":"2026-06-03","kl":"13:30"},{"e":"Sýslumaðurinn á Norðurlandi eystra","st":"Akureyri","teg":"Sölu lokið","flokkur":"Fasteign","a":"Laugarbrekka 19, Norðurþing","id":"2153122","d":"2026-06-10","kl":"09:30"},{"e":"Sýslumaðurinn á Vesturlandi","st":"Stykkishólmur","teg":"Sölu lokið","flokkur":"Fasteign","a":"Skógarlundur 42, Akranes","id":"2521112","d":"2026-06-22","kl":"10:30"},{"e":"Sýslumaðurinn á Norðurlandi eystra","st":"Akureyri","teg":"Sölu lokið","flokkur":"Fasteign","a":"Skarðshlíð 40, Akureyri","id":"2150411","d":"2026-06-23","kl":"11:00"},{"e":"Sýslumaðurinn á höfuðborgarsvæðinu","st":"Hlíðasmári 1","teg":"Sölu lokið","flokkur":"Fasteign","a":"Hafnarbraut 11, Kópavogur","id":"2318684","d":"2026-06-29","kl":"11:30"},{"e":"Sýslumaðurinn á höfuðborgarsvæðinu","st":"Hlíðasmári 1","teg":"Sölu lokið","flokkur":"Fasteign","a":"Sólvallagata 27, Reykjavík","id":"2002374","d":"2026-06-30","kl":"11:00"},{"e":"Sýslumaðurinn á höfuðborgarsvæðinu","st":"Hlíðasmári 1","teg":"Sölu lokið","flokkur":"Fasteign","a":"Hraunbær 146, Reykjavík, 69% ehl.","id":"2045161","d":"2026-07-01","kl":"10:00"},{"e":"Sýslumaðurinn á höfuðborgarsvæðinu","st":"Hlíðasmári 1","teg":"Sölu lokið","flokkur":"Fasteign","a":"Langafit 18, Garðabær","id":"2071128","d":"2026-07-01","kl":"13:30"},{"e":"Sýslumaðurinn á höfuðborgarsvæðinu","st":"Hlíðasmári 1","teg":"Sölu lokið","flokkur":"Fasteign","a":"Urriðaholtsstræti 22B, Garðabær","id":"2501632","d":"2026-07-01","kl":"14:30"},{"e":"Sýslumaðurinn á Vesturlandi","st":"Stykkishólmur","teg":"Sölu lokið","flokkur":"Fasteign","a":"Brekkubraut 17, Akranes","id":"2100323","d":"2026-07-02","kl":"11:30"},{"e":"Sýslumaðurinn á Vesturlandi","st":"Stykkishólmur","teg":"Sölu lokið","flokkur":"Fasteign","a":"Sandabraut 11, Akranes","id":"2101683","d":"2026-07-02","kl":"13:30"},{"e":"Sýslumaðurinn á Vesturlandi","st":"Akranes","teg":"Sölu lokið","flokkur":"Skip","a":"AUSTRI, SH, Snæfellsness- og Hnappadalssýsla, (FARÞEGABÁTUR)","id":"6275","d":"2026-07-02","kl":"14:30"},{"e":"Sýslumaðurinn á Austurlandi","st":"Eskifjörður","teg":"Framhald uppboðs","flokkur":"Fasteign","a":"Hafrafell , Múlaþing","id":"2173261","d":"2026-07-22","kl":"10:15"},{"e":"Sýslumaðurinn á Austurlandi","st":"Eskifjörður","teg":"Framhald uppboðs","flokkur":"Fasteign","a":"Hafrafell 2, Múlaþing","id":"2351136","d":"2026-07-22","kl":"10:00"},{"e":"Sýslumaðurinn á Austurlandi","st":"Eskifjörður","teg":"Framhald uppboðs","flokkur":"Fasteign","a":"Möðrudalur Baðstofa , Múlaþing","id":"2258452","d":"2026-07-22","kl":"12:00"},{"e":"Sýslumaðurinn á Austurlandi","st":"Eskifjörður","teg":"Framhald uppboðs","flokkur":"Fasteign","a":"Möðrudalur Fjallakaffi, Múlaþing","id":"2172755","d":"2026-07-22","kl":"11:45"}]}