{"varmadalur 4":[64.19291,-21.67511,"Kjalarn.-dreifb."],"skrauthólar 3":[64.23224,-21.80473,"Kjalarn.-dreifb."],"lykkja 1":[64.24,-21.85239,"Kjalarn.-dreifb."],"koparslétta 3":[64.19637,-21.69561,"Esjumelar"],"koparslétta 9":[64.19747,-21.69772,"Esjumelar"],"arnarhóll 1":[64.20545,-21.69672,"Kjalarn.-dreifb."],"silfurslétta 5a":[64.19462,-21.69188,"Esjumelar"],"koparslétta 5a":[64.19682,-21.69641,"Esjumelar"],"koparslétta 12":[64.19719,-21.69491,"Esjumelar"],"koparslétta 14":[64.19749,-21.69558,"Esjumelar"],"silfurslétta 1":[64.19497,-21.6939,"Esjumelar"],"gullslétta 8":[64.19669,-21.69798,"Esjumelar"],"gullslétta 12":[64.19726,-21.69944,"Esjumelar"],"koparslétta 6":[64.19634,-21.69301,"Esjumelar"],"koparslétta 10":[64.19685,-21.69413,"Esjumelar"],"brautarholt 2":[64.24161,-21.87261,"Kjalarn.-dreifb."],"koparslétta 13":[64.19808,-21.69917,"Esjumelar"],"víðinesvegur 30":[64.17852,-21.7509,"Álfsnes"],"esjuberg 2":[64.21796,-21.77354,"Kjalarn.-dreifb."],"hofsbraut 52":[64.24264,-21.85338,"Kjalarn.-dreifb."],"hofsbraut 54":[64.24288,-21.85439,"Kjalarn.-dreifb."],"hofsbraut 66":[64.24197,-21.85358,"Kjalarn.-dreifb."],"silfurslétta 9":[64.19403,-21.69039,"Esjumelar"],"gullslétta 3":[64.19598,-21.69904,"Esjumelar"],"gullslétta 5":[64.19663,-21.70033,"Esjumelar"],"gullslétta 7":[64.197,-21.70111,"Esjumelar"],"leiruvegur 2b":[64.19142,-21.69205,"Álfsnes"],"hofsbraut 56":[64.24291,-21.85541,"Kjalarn.-dreifb."],"hofsbraut 58":[64.24255,-21.8558,"Kjalarn.-dreifb."],"hofsbraut 62":[64.24228,-21.8541,"Kjalarn.-dreifb."],"hofsbraut 70":[64.24214,-21.8552,"Kjalarn.-dreifb."],"hofsbraut 72":[64.24227,-21.85604,"Kjalarn.-dreifb."],"mógilsárvegur 37a":[64.20716,-21.69842,"Kjalarn.-dreifb."],"mógilsárvegur 37b":[64.20686,-21.6989,"Kjalarn.-dreifb."],"brautarholt 1":[64.24094,-21.87475,"Kjalarn.-dreifb."],"brautarholt 3":[64.2421,-21.87571,"Kjalarn.-dreifb."],"silfurslétta 3":[64.19473,-21.6928,"Esjumelar"],"varmadalsvegur 31":[64.19525,-21.66597,"Kjalarn.-dreifb."],"mógilsárvegur 37":[64.20737,-21.69775,"Kjalarn.-dreifb."],"lykkja 2a":[64.24082,-21.85309,"Kjalarn.-dreifb."],"víðinesvegur 2":[64.2004,-21.71304,"Álfsnes"],"vellir 2":[64.20872,-21.65842,"Kjalarn.-dreifb."],"lykkja 2b":[64.24109,-21.8544,"Kjalarn.-dreifb."],"koparslétta 11a":[64.19784,-21.69835,"Esjumelar"],"gullslétta 4":[64.19602,-21.69643,"Esjumelar"],"varmadalur 1":[64.19255,-21.67778,"Kjalarn.-dreifb."],"vellir 3":[64.20471,-21.66761,"Kjalarn.-dreifb."],"varmadalur 2":[64.19282,-21.67668,"Kjalarn.-dreifb."],"brautarholt 11":[64.24193,-21.88529,"Kjalarn.-dreifb."],"brautarholt 5":[64.24205,-21.87965,"Kjalarn.-dreifb."],"leiruvegur 7":[64.18432,-21.70647,"Álfsnes"],"leiruvegur 2a":[64.19088,-21.69313,"Álfsnes"],"koparslétta 2":[64.19572,-21.69573,"Esjumelar"],"vesturlandsvegur 103":[64.1934,-21.6985,"Álfsnes"],"gullslétta 6":[64.19635,-21.69715,"Esjumelar"],"lækjarmelur 10":[64.19699,-21.69896,"Esjumelar"],"gullslétta 14":[64.19756,-21.70004,"Esjumelar"],"koparslétta 4":[64.19634,-21.693,"Esjumelar"],"koparslétta 11c":[64.19768,-21.69863,"Esjumelar"],"hofsbraut 60":[64.24242,-21.85499,"Kjalarn.-dreifb."],"hofsbraut 68":[64.242,-21.8543,"Kjalarn.-dreifb."],"lykkja 4":[64.2413,-21.8534,"Kjalarn.-dreifb."],"leiruvegur 4":[64.1898,-21.69434,"Álfsnes"],"víðinesvegur 33":[64.17786,-21.74563,"Álfsnes"],"varmadalsvegur 81":[64.19573,-21.66353,"Kjalarn.-dreifb."],"skarðsvegur 26":[64.22276,-21.5506,"Kjalarn.-dreifb."],"skarðsvegur 21":[64.22312,-21.55339,"Kjalarn.-dreifb."],"skarðsvegur 20":[64.22181,-21.55242,"Kjalarn.-dreifb."],"skarðsvegur 15":[64.22155,-21.5552,"Kjalarn.-dreifb."],"skarðsvegur 9":[64.21991,-21.55722,"Kjalarn.-dreifb."],"skarðsvegur 11":[64.2207,-21.55646,"Kjalarn.-dreifb."],"skarðsvegur 7":[64.21913,-21.55757,"Kjalarn.-dreifb."],"skarðsvegur 24":[64.22247,-21.55127,"Kjalarn.-dreifb."],"skarðsvegur 1":[64.21747,-21.5583,"Kjalarn.-dreifb."],"skarðsvegur 17":[64.22195,-21.55486,"Kjalarn.-dreifb."],"skarðsvegur 3":[64.21803,-21.55829,"Kjalarn.-dreifb."],"skarðsvegur 16":[64.22105,-21.55365,"Kjalarn.-dreifb."],"skarðsvegur 14":[64.22052,-21.55474,"Kjalarn.-dreifb."],"skarðsvegur 8":[64.21779,-21.55682,"Kjalarn.-dreifb."],"skarðsvegur 4":[64.21664,-21.55677,"Kjalarn.-dreifb."],"skarðsvegur 12":[64.21972,-21.55485,"Kjalarn.-dreifb."],"skarðsvegur 10a":[64.21912,-21.55531,"Kjalarn.-dreifb."],"skarðsvegur 10":[64.21869,-21.5557,"Kjalarn.-dreifb."],"dalsmynni 1":[64.27366,-21.84144,"Kjalarn.-dreifb."],"vellir 1a":[64.20917,-21.67596,"Kjalarn.-dreifb."],"mógilsárvegur 1":[64.20922,-21.71236,"Kjalarn.-dreifb."],"vellir 2a":[64.20919,-21.67547,"Kjalarn.-dreifb."],"vellir 3a":[64.20941,-21.66901,"Kjalarn.-dreifb."],"vellir 4a":[64.20957,-21.66404,"Kjalarn.-dreifb."],"vellir 1b":[64.20938,-21.66502,"Kjalarn.-dreifb."],"vellir 5c":[64.20512,-21.6534,"Kjalarn.-dreifb."],"vellir 2b":[64.21035,-21.65417,"Kjalarn.-dreifb."],"vellir 5b":[64.20939,-21.65177,"Kjalarn.-dreifb."],"vellir 5a":[64.21006,-21.65157,"Kjalarn.-dreifb."],"vellir 2d":[64.20492,-21.65915,"Kjalarn.-dreifb."],"vellir 2c":[64.2093,-21.65638,"Kjalarn.-dreifb."],"leiruvegur 14":[64.18414,-21.71086,"Álfsnes"],"leiruvegur 11":[64.18359,-21.71011,"Álfsnes"],"leiruvegur 8":[64.18925,-21.69688,"Álfsnes"],"leiruvegur 3":[64.1881,-21.69204,"Álfsnes"],"leiruvegur 13":[64.18361,-21.70912,"Álfsnes"],"esjuberg 3":[64.21697,-21.77433,"Kjalarn.-dreifb."],"vesturlandsvegur 200":[64.20783,-21.73683,"Kjalarn.-dreifb."],"tindar 1b":[64.21292,-21.78669,"Kjalarn.-dreifb."],"tindar 2":[64.21467,-21.78595,"Kjalarn.-dreifb."],"tindar 3":[64.21268,-21.78525,"Kjalarn.-dreifb."],"tindar 1a":[64.21323,-21.78639,"Kjalarn.-dreifb."],"norðurgrafarvegur 4":[64.19516,-21.69127,"Esjumelar"],"norðurgrafarvegur 2":[64.19516,-21.6925,"Esjumelar"],"skrauthólar 6":[64.23153,-21.81443,"Kjalarn.-dreifb."],"mógilsárvegur 23a":[64.2084,-21.71139,"Kjalarn.-dreifb."],"mógilsárvegur 1a":[64.2078,-21.70637,"Kjalarn.-dreifb."],"vesturlandsvegur 101":[64.19277,-21.69671,"Álfsnes"],"smábýli 2":[64.22701,-21.8016,"Kjalarn.-dreifb."],"smábýli 17":[64.21028,-21.77394,"Kjalarn.-dreifb."],"smábýli 8":[64.22246,-21.79612,"Kjalarn.-dreifb."],"smábýli 18":[64.20976,-21.77159,"Kjalarn.-dreifb."],"smábýli 15":[64.21203,-21.77528,"Kjalarn.-dreifb."],"smábýli 7":[64.22298,-21.79717,"Kjalarn.-dreifb."],"smábýli 11":[64.22101,-21.79164,"Kjalarn.-dreifb."],"smábýli 5":[64.22388,-21.79975,"Kjalarn.-dreifb."],"vesturlandsvegur 99":[64.19208,-21.69472,"Álfsnes"],"vesturlandsvegur 105":[64.19295,-21.69968,"Álfsnes"],"leiruvegur 6":[64.18861,-21.69543,"Álfsnes"],"skrauthólar 5":[64.23089,-21.81239,"Kjalarn.-dreifb."],"víðinesvegur 26":[64.18248,-21.75269,"Álfsnes"],"víðinesvegur 5":[64.18783,-21.72113,"Álfsnes"],"melavellir 2":[64.26839,-21.85538,"Kjalarn.-dreifb."],"tindastaðir 1":[64.29646,-21.76025,"Kjalarn.-dreifb."],"norðurgrafarvegur 3a":[64.19625,-21.68958,"Esjumelar"],"bronsslétta 5":[64.19763,-21.69129,"Esjumelar"],"bronsslétta 3":[64.19725,-21.69067,"Esjumelar"],"bronsslétta 1":[64.19689,-21.69006,"Esjumelar"],"járnslétta 8":[64.19796,-21.69338,"Esjumelar"],"norðurgrafarvegur 1":[64.19625,-21.69049,"Esjumelar"],"járnslétta 8a":[64.19831,-21.6932,"Esjumelar"],"norðurgrafarvegur 3":[64.19655,-21.6895,"Esjumelar"],"gullslétta 10d":[64.1971,-21.69866,"Esjumelar"],"gullslétta 10f":[64.19719,-21.69844,"Esjumelar"],"gullslétta 10g":[64.19709,-21.69825,"Esjumelar"],"gullslétta 10j":[64.19701,-21.69847,"Esjumelar"],"gullslétta 10k":[64.19696,-21.69859,"Esjumelar"],"gullslétta 10b":[64.19703,-21.69886,"Esjumelar"],"varmadalur 3":[64.1936,-21.68223,"Kjalarn.-dreifb."],"leiruvegur 10":[64.18696,-21.69983,"Álfsnes"],"varmadalur 5":[64.19329,-21.67281,"Kjalarn.-dreifb."],"koparslétta 11b":[64.19775,-21.69848,"Esjumelar"],"víðinesvegur 22":[64.18237,-21.76277,"Álfsnes"],"bjóla 1":[64.24015,-21.84765,"Kjalarn.-dreifb."],"málmslétta 3":[64.19543,-21.68793,"Esjumelar"],"norðurgrafarvegur 6":[64.19573,-21.68938,"Esjumelar"],"málmslétta 5":[64.19573,-21.68726,"Esjumelar"],"norðurgrafarvegur 8":[64.19605,-21.68835,"Esjumelar"],"málmslétta 1":[64.19522,-21.68908,"Esjumelar"],"smábýli 10":[64.22282,-21.79152,"Kjalarn.-dreifb."],"koparslétta 22":[64.1988,-21.69832,"Esjumelar"],"skrauthólar 2":[64.23224,-21.8061,"Kjalarn.-dreifb."],"koparslétta 16":[64.19785,-21.69635,"Esjumelar"],"gullslétta 18":[64.19842,-21.70017,"Esjumelar"],"tindar 1":[64.21387,-21.78682,"Kjalarn.-dreifb."],"skarðsvegur 13":[64.22108,-21.55606,"Kjalarn.-dreifb."],"skarðsvegur 5":[64.21857,-21.55766,"Kjalarn.-dreifb."],"skarðsvegur 19":[64.22275,-21.55426,"Kjalarn.-dreifb."],"silfurlétta 1b":[64.19509,-21.69486,"Esjumelar"],"skarðsvegur 22":[64.22213,-21.55182,"Kjalarn.-dreifb."],"skarðsvegur 18":[64.22142,-21.55303,"Kjalarn.-dreifb."],"árvellir 2":[64.22017,-21.78578,"Kjalarn.-dreifb."],"vesturlandsvegur 201":[64.20826,-21.74825,"Kjalarn.-dreifb."],"silfurslétta 7":[64.19425,-21.69113,"Esjumelar"],"gullslétta 16":[64.19802,-21.70087,"Esjumelar"],"hofsbraut 64":[64.24216,-21.85331,"Kjalarn.-dreifb."],"leiruvegur 12":[64.18508,-21.70645,"Álfsnes"],"járnslétta 2":[64.19664,-21.69133,"Esjumelar"],"járnslétta 4":[64.19706,-21.69212,"Esjumelar"],"járnslétta 6":[64.19745,-21.69267,"Esjumelar"],"silfurslétta 5":[64.19449,-21.69198,"Esjumelar"],"leiruvegur 1":[64.18848,-21.69291,"Álfsnes"],"leiruvegur 2":[64.18946,-21.69266,"Álfsnes"],"mógilsárvegur 27":[64.20925,-21.7013,"Kjalarn.-dreifb."],"víðinesvegur 21":[64.18904,-21.75201,"Álfsnes"],"kalkslétta 1":[64.19907,-21.69368,"Esjumelar"],"bjóla 2":[64.24035,-21.848,"Kjalarn.-dreifb."],"saltvík 2":[64.21844,-21.80259,"Kjalarn.-dreifb."],"silfurslétta 11":[64.19383,-21.68951,"Esjumelar"],"silfurslétta 2":[64.19378,-21.69249,"Esjumelar"],"gullslétta 12a":[64.19732,-21.70009,"Esjumelar"],"gullslétta 8a":[64.19668,-21.69865,"Esjumelar"],"brautarholt 8":[64.2464,-21.87864,"Kjalarn.-dreifb."],"brautarholt kjal. 9":[64.2421,-21.88375,"Kjalarn.-dreifb."],"gullslétta 14a":[64.19735,-21.70013,"Esjumelar"],"gullslétta 6a":[64.19608,-21.69729,"Esjumelar"],"bronsslétta 7":[64.19812,-21.69182,"Esjumelar"],"saltvík 1":[64.20935,-21.81983,"Kjalarn.-dreifb."],"smábýli 12":[64.21839,-21.79272,"Kjalarn.-dreifb."],"brautarholt 10":[64.24371,-21.87891,"Kjalarn.-dreifb."],"móanes 1":[64.20317,-21.76286,"Kjalarn.-dreifb."],"saltvík 3":[64.22036,-21.81051,"Kjalarn.-dreifb."],"víðinesvegur 4":[64.19651,-21.71337,"Álfsnes"],"koparslétta 13a":[64.19807,-21.69845,"Esjumelar"],"koparslétta 9a":[64.19743,-21.697,"Esjumelar"],"koparslétta 18":[64.19821,-21.69708,"Esjumelar"],"koparslétta 7a":[64.19741,-21.69695,"Esjumelar"],"koparslétta 20":[64.19856,-21.69773,"Esjumelar"],"koparslétta 14a":[64.19743,-21.69649,"Esjumelar"],"koparslétta 16a":[64.19745,-21.69654,"Esjumelar"],"koparslétta 18a":[64.19807,-21.69793,"Esjumelar"],"koparslétta 20a":[64.19809,-21.69797,"Esjumelar"],"koparslétta 5":[64.19668,-21.69615,"Esjumelar"],"koparslétta 5x":[64.19679,-21.69556,"Esjumelar"],"koparslétta 3a":[64.19677,-21.69551,"Esjumelar"],"koparslétta 12a":[64.19681,-21.69509,"Esjumelar"],"koparslétta 4a":[64.19554,-21.69434,"Esjumelar"],"koparslétta 10a":[64.19679,-21.69505,"Esjumelar"],"koparslétta 6a":[64.19568,-21.69289,"Esjumelar"],"koparslétta 2a":[64.19552,-21.69442,"Esjumelar"],"víðinesvegur 20":[64.18915,-21.75878,"Álfsnes"],"skrauthólar 1":[64.23046,-21.81641,"Kjalarn.-dreifb."],"gullslétta 1":[64.19553,-21.69762,"Esjumelar"],"skrauthólar 4":[64.23341,-21.8038,"Kjalarn.-dreifb."],"brautarholtsvegur 39":[64.24178,-21.85655,"Kjalarn.-dreifb."],"gullslétta 10x":[64.19671,-21.6987,"Esjumelar"],"esjuberg 8":[64.20897,-21.74308,"Kjalarn.-dreifb."],"brautarholtsvegur 41":[64.24147,-21.85701,"Kjalarn.-dreifb."],"gullslétta 10c":[64.19707,-21.69874,"Esjumelar"],"gullslétta 10e":[64.19714,-21.69854,"Esjumelar"],"gullslétta 10h":[64.19707,-21.69831,"Esjumelar"],"gullslétta 10i":[64.19704,-21.69841,"Esjumelar"],"gullslétta 10l":[64.1969,-21.69872,"Esjumelar"]}