{"source":"Wikipedia — Next Icelandic parliamentary election","sourceUrl":"https://en.wikipedia.org/wiki/Next_Icelandic_parliamentary_election","license":"CC BY-SA 4.0","parties":["S","C","F","D","M","B","J","P","V"],"polls":[{"date":"2024-12-19","pollster":"Maskína","sample":2803,"v":{"S":23.1,"C":16.5,"F":10.6,"D":16.3,"M":9,"B":8.4,"J":6,"P":5.2,"V":3.8}},{"date":"2025-01-02","pollster":"Gallup","sample":10908,"v":{"S":21.7,"C":16.2,"F":10.6,"D":20.5,"M":12.7,"B":6.7,"J":5.2,"P":3.5,"V":2.2}},{"date":"2025-01-14","pollster":"Maskína","sample":966,"v":{"S":22.2,"C":14,"F":12.9,"D":19.3,"M":11.6,"B":7.2,"J":4.1,"P":3.6,"V":3.1}},{"date":"2025-02-02","pollster":"Gallup","sample":9652,"v":{"S":26,"C":14.1,"F":8.3,"D":21.5,"M":10.1,"B":6.3,"J":6.2,"P":3.6,"V":3.1}},{"date":"2025-02-26","pollster":"Maskína","sample":2899,"v":{"S":21.9,"C":14.9,"F":9.1,"D":21.4,"M":11.5,"B":7.3,"J":5.5,"P":3.2,"V":2.8}},{"date":"2025-03-19","pollster":"Maskína","sample":1899,"v":{"S":23.3,"C":14.8,"F":8.5,"D":24.3,"M":10.9,"B":6.8,"J":4.9,"P":3.1,"V":3.3}},{"date":"2025-03-31","pollster":"Gallup","sample":10324,"v":{"S":27,"C":14.6,"F":7.7,"D":22.4,"M":9.3,"B":5.7,"J":5.4,"P":4,"V":3.3}},{"date":"2025-04-22","pollster":"Maskína","sample":1453,"v":{"S":26.2,"C":15.8,"F":7.9,"D":20.9,"M":10.3,"B":7.2,"J":4.9,"P":3.9,"V":2.9}},{"date":"2025-04-30","pollster":"Gallup","sample":10005,"v":{"S":29.4,"C":13.9,"F":7.4,"D":22.3,"M":8.9,"B":6.1,"J":4.7,"P":3.2,"V":3.3}},{"date":"2025-05-01","pollster":"Gallup","sample":11521,"v":{"S":30.7,"C":14.4,"F":7.5,"D":21.7,"M":9.1,"B":5.5,"J":3.5,"P":3.3,"V":3.6}},{"date":"2025-05-22","pollster":"Maskína","sample":1962,"v":{"S":27.4,"C":16.8,"F":7.2,"D":18.9,"M":9.7,"B":6.8,"J":5,"P":4.6,"V":3.6}},{"date":"2025-06-22","pollster":"Maskína","sample":null,"v":{"S":28.1,"C":15.3,"F":6.6,"D":17.3,"M":13,"B":7,"J":4.4,"P":4.6,"V":3.7}},{"date":"2025-06-30","pollster":"Gallup","sample":null,"v":{"S":31.8,"C":13.7,"F":6.5,"D":20.6,"M":10.7,"B":5.6,"J":3.3,"P":4.1,"V":3.2}},{"date":"2025-07-23","pollster":"Maskína","sample":1855,"v":{"S":31.2,"C":16.2,"F":6.6,"D":18,"M":9.9,"B":6.8,"J":2.9,"P":5,"V":3.4}},{"date":"2025-07-31","pollster":"Gallup","sample":11541,"v":{"S":34.7,"C":14.6,"F":6.7,"D":18.7,"M":10.5,"B":4.9,"J":2.4,"P":3.5,"V":3.4}},{"date":"2025-08-21","pollster":"Maskína","sample":null,"v":{"S":31.6,"C":16.1,"F":6.3,"D":18.6,"M":9.6,"B":6.5,"J":2.6,"P":4.5,"V":4.2}},{"date":"2025-08-31","pollster":"Gallup","sample":10.055,"v":{"S":34.6,"C":12.9,"F":7.4,"D":19.7,"M":10.7,"B":4.5,"J":1.9,"P":3.5,"V":3.7}},{"date":"2025-09-19","pollster":"Maskína","sample":null,"v":{"S":31.9,"C":14.3,"F":6.3,"D":18.6,"M":9.1,"B":6.3,"J":3.5,"P":5.8,"V":4.1}},{"date":"2025-09-30","pollster":"Prósent","sample":2000,"v":{"S":32,"C":14.4,"F":7.6,"D":18.3,"M":9.9,"B":7.1,"J":2.7,"P":5.2,"V":2.1}},{"date":"2025-09-30","pollster":"Gallup","sample":10887,"v":{"S":34,"C":12.6,"F":6.9,"D":19.5,"M":11.8,"B":5.8,"J":2.1,"P":2.9,"V":3.6}},{"date":"2025-10-02","pollster":"Gallup","sample":11225,"v":{"S":31.9,"C":13.5,"F":5.9,"D":17.6,"M":16.3,"B":5.5,"J":2.3,"P":3.9,"V":2.6}},{"date":"2025-11-30","pollster":"Gallup","sample":10332,"v":{"S":31.1,"C":12.8,"F":5.2,"D":16.5,"M":19.5,"B":5.6,"J":2.3,"P":3.3,"V":3.2}},{"date":"2025-12-01","pollster":"Gallup","sample":3460,"v":{"S":21.4,"C":13.8,"F":13.1,"D":20.1,"M":12.4,"B":6.3,"J":6,"P":3.1,"V":2.1}},{"date":"2025-12-28","pollster":"Gallup","sample":9091,"v":{"S":30.9,"C":10.9,"F":5.5,"D":16.9,"M":21.7,"B":5.2,"J":1.6,"P":3.4,"V":3.6}},{"date":"2026-01-01","pollster":"Gallup","sample":9713,"v":{"S":31.2,"C":11.3,"F":5.3,"D":17.1,"M":20.8,"B":5.4,"J":1.9,"P":3.4,"V":3.1}},{"date":"2026-01-13","pollster":"Maskína","sample":886,"v":{"S":27,"C":14.1,"F":4.3,"D":13.5,"M":22.2,"B":7.1,"J":4.1,"P":4.1,"V":3.7}},{"date":"2026-01-16","pollster":"Prósent","sample":3900,"v":{"S":30.1,"C":13.5,"F":7.7,"D":13.7,"M":19.6,"B":5.9,"J":2.4,"P":3.6,"V":3.3}},{"date":"2026-02-01","pollster":"Gallup","sample":9958,"v":{"S":28.5,"C":10.9,"F":5.8,"D":18.1,"M":20.3,"B":6.6,"J":2,"P":2.7,"V":4.2}},{"date":"2026-02-19","pollster":"Maskína","sample":2617,"v":{"S":25.5,"C":14,"F":5.8,"D":16.1,"M":18.4,"B":7.1,"J":3.5,"P":5,"V":4.4}},{"date":"2026-03-31","pollster":"Gallup","sample":10746,"v":{"S":30,"C":10,"F":5.8,"D":19.5,"M":20.6,"B":4.7,"J":2,"P":3,"V":4.3}}],"election2024":{"date":"2024-11-30","v":{"S":20.75,"C":15.82,"F":13.78,"D":19.36,"M":12.1,"B":7.8,"J":3.96,"P":3.02,"V":2.34}}}