[{"a":"Sólgarður","d":"2026-04-07","kv":19500,"fm":104.6,"teg":"Einbýli","herb":4,"ar":1945,"ppm":186424},{"a":"Sjávarborg","d":"2025-09-26","kv":45000,"fm":113,"teg":"Einbýli","herb":4,"ar":1976,"ppm":398230},{"a":"Gamla frystihúsið","d":"2025-09-26","kv":35000,"fm":96.2,"teg":"Fjölbýli","herb":null,"ar":1946,"ppm":363825},{"a":"Bakkastekkur","d":"2025-09-04","kv":59600,"fm":126.3,"teg":"Einbýli","herb":4,"ar":1928,"ppm":471892},{"a":"Þórshamar","d":"2025-02-13","kv":48500,"fm":155.6,"teg":"Einbýli","herb":5,"ar":1974,"ppm":311697},{"a":"Smáragrund","d":"2024-03-14","kv":26700,"fm":87,"teg":"Sérbýli","herb":2,"ar":1984,"ppm":306897},{"a":"Bakkavegur 9","d":"2022-11-22","kv":25000,"fm":68.7,"teg":"Einbýli","herb":2,"ar":2011,"ppm":363901},{"a":"Laufás","d":"2021-05-31","kv":15000,"fm":132,"teg":"Einbýli","herb":6,"ar":1957,"ppm":113636}]